Workbook

Sheet CrossRef
E1: AMT DATA | I1: MACMAHON DATA SERIAL PREFIX | O1: MATCHING LOGIC
A2: AMT Concat | B2: Concat Code | C2: Comp Code | D2: Mod Code | E2: AMT Model | F2: AMT Serial Prefix | G2: AMT Component Code | H2: AMT Modifier Code | I2: MacMahon Serial Prefix | J2: Functional Location | K2: Position Code | L2: Maintenance Item Description | M2: Functional Location Code | N2: Customer data Concat | O2: Match Reason
A3: =F3&C3&D3 -> 1701353LT | B3: =F3&C3&D3 -> 1701353LT | C3: =LEFT(G3,4) -> 1353 | D3: =LEFT(H3,2) -> LT | E3: 6040 | F3: 170 | G3: 1353 - RADIATOR | H3: LT - LEFT | I3: 170 | J3: EXBH054-ENG1-COSY | K3: LH | L3: 18000H RADIATOR CHANGE LH | M3: =_xlfn.TEXTAFTER(J3,"-") -> ENG1-COSY | N3: =I3&M3&K3 -> 170ENG1-COSYLH
A4: =F4&C4&D4 -> 1701353RI | B4: =F4&C4&D4 -> 1701353RI | C4: =LEFT(G4,4) -> 1353 | D4: =LEFT(H4,2) -> RI | E4: 6040 | F4: 170 | G4: 1353 - RADIATOR | H4: RI - RIGHT | I4: 170 | J4: EXBH054-ENG2-COSY | K4: RH | L4: 18000H RADIATOR CHANGE RH | M4: =_xlfn.TEXTAFTER(J4,"-") -> ENG2-COSY | N4: =I4&M4&K4 -> 170ENG2-COSYRH
A5: =F5&C5&D5 -> 1704050LT | B5: =F5&C5&D5 -> 1704050LT | C5: =LEFT(G5,4) -> 4050 | D5: =LEFT(H5,2) -> LT | E5: 6040 | F5: 170 | G5: 4050 - FINAL DRIVE | H5: LT - LEFT | I5: 170 | J5: EXBH054-UCRG-FIDV-FIDL | K5: LH | L5: 18000H FINAL DRIVE CHANGE LH | M5: =_xlfn.TEXTAFTER(J5,"-") -> UCRG-FIDV-FIDL | N5: =I5&M5&K5 -> 170UCRG-FIDV-FIDLLH
A6: =F6&C6&D6 -> 1704050RI | B6: =F6&C6&D6 -> 1704050RI | C6: =LEFT(G6,4) -> 4050 | D6: =LEFT(H6,2) -> RI | E6: 6040 | F6: 170 | G6: 4050 - FINAL DRIVE | H6: RI - RIGHT | I6: 170 | J6: EXBH054-UCRG-FIDV-FIDR | K6: RH | L6: 18000H FINAL DRIVE CHANGE RH | M6: =_xlfn.TEXTAFTER(J6,"-") -> UCRG-FIDV-FIDR | N6: =I6&M6&K6 -> 170UCRG-FIDV-FIDRRH
A7: =F7&C7&D7 -> 1704159LT | B7: =F7&C7&D7 -> 1704159LT | C7: =LEFT(G7,4) -> 4159 | D7: =LEFT(H7,2) -> LT | E7: 6040 | F7: 170 | G7: 4159 - IDLER/IDLER WHEEL | H7: LT - LEFT | I7: 170 | J7: EXBH054-UCRG-TCID | K7: LH | L7: 10000H IDLER CHANGE LH | M7: =_xlfn.TEXTAFTER(J7,"-") -> UCRG-TCID | N7: =I7&M7&K7 -> 170UCRG-TCIDLH | O7: Description mentions IDLER
A8: =F8&C8&D8 -> 1704159RI | B8: =F8&C8&D8 -> 1704159RI | C8: =LEFT(G8,4) -> 4159 | D8: =LEFT(H8,2) -> RI | E8: 6040 | F8: 170 | G8: 4159 - IDLER/IDLER WHEEL | H8: RI - RIGHT | I8: 170 | J8: EXBH054-UCRG-TCID | K8: RH | L8: 10000H IDLER CHANGE RH | M8: =_xlfn.TEXTAFTER(J8,"-") -> UCRG-TCID | N8: =I8&M8&K8 -> 170UCRG-TCIDRH | O8: Description mentions IDLER
A9: =F9&C9&D9 -> 1704170RI | B9: =F9&C9&D9 -> 1704170RI | C9: =LEFT(G9,4) -> 4170 | D9: =LEFT(H9,2) -> RI | E9: 6040 | F9: 170 | G9: 4170 - TRACK ASSEMBLY | H9: RI - RIGHT | I9: 170 | J9: EXBH054-TCKS | K9: RH | L9: 16000H TRACK CHANGE RH | M9: =_xlfn.TEXTAFTER(J9,"-") -> TCKS | N9: =I9&M9&K9 -> 170TCKSRH
A10: =F10&C10&D10 -> 1704170LT | B10: =F10&C10&D10 -> 1704170LT | C10: =LEFT(G10,4) -> 4170 | D10: =LEFT(H10,2) -> LT | E10: 6040 | F10: 170 | G10: 4170 - TRACK ASSEMBLY | H10: LT - LEFT | I10: 170 | J10: EXBH054-TCKS | K10: LH | L10: 16000H TRACK CHANGE LH | M10: =_xlfn.TEXTAFTER(J10,"-") -> TCKS | N10: =I10&M10&K10 -> 170TCKSLH
A11: =F11&C11&D11 -> 1704351LF | B11: =F11&C11&D11 -> 1704351LF | C11: =LEFT(G11,4) -> 4351 | D11: =LEFT(H11,2) -> LF | E11: 6040 | F11: 170 | G11: 4351 - HYD PROPEL/DRIVE MOTOR | H11: LF - LEFT FRONT | I11: 170 | J11: EXBH054-HYSY-MOHY | K11: LHF | L11: 15000H TRAVEL MOTOR CHANGE LHF | M11: =_xlfn.TEXTAFTER(J11,"-") -> HYSY-MOHY | N11: =I11&M11&K11 -> 170HYSY-MOHYLHF | O11: Travel motor is hydraulic propel/drive motor
A12: =F12&C12&D12 -> 1704351LR | B12: =F12&C12&D12 -> 1704351LR | C12: =LEFT(G12,4) -> 4351 | D12: =LEFT(H12,2) -> LR | E12: 6040 | F12: 170 | G12: 4351 - HYD PROPEL/DRIVE MOTOR | H12: LR - LEFT REAR | I12: 170 | J12: EXBH054-HYSY-MOHY | K12: LHR | L12: 15000H TRAVEL MOTOR CHANGE LHR | M12: =_xlfn.TEXTAFTER(J12,"-") -> HYSY-MOHY | N12: =I12&M12&K12 -> 170HYSY-MOHYLHR | O12: Travel motor is hydraulic propel/drive motor
A13: =F13&C13&D13 -> 1704351RF | B13: =F13&C13&D13 -> 1704351RF | C13: =LEFT(G13,4) -> 4351 | D13: =LEFT(H13,2) -> RF | E13: 6040 | F13: 170 | G13: 4351 - HYD PROPEL/DRIVE MOTOR | H13: RF - RIGHT FRONT | I13: 170 | J13: EXBH054-HYSY-MOHY | K13: RHF | L13: 15000H TRAVEL MOTOR CHANGE RHF | M13: =_xlfn.TEXTAFTER(J13,"-") -> HYSY-MOHY | N13: =I13&M13&K13 -> 170HYSY-MOHYRHF | O13: Travel motor is hydraulic propel/drive motor
A14: =F14&C14&D14 -> 1704351RR | B14: =F14&C14&D14 -> 1704351RR | C14: =LEFT(G14,4) -> 4351 | D14: =LEFT(H14,2) -> RR | E14: 6040 | F14: 170 | G14: 4351 - HYD PROPEL/DRIVE MOTOR | H14: RR - RIGHT REAR | I14: 170 | J14: EXBH054-HYSY-MOHY | K14: RHR | L14: 15000H TRAVEL MOTOR CHANGE RHR | M14: =_xlfn.TEXTAFTER(J14,"-") -> HYSY-MOHY | N14: =I14&M14&K14 -> 170HYSY-MOHYRHR | O14: Travel motor is hydraulic propel/drive motor
A15: =F15&C15&D15 -> 170508400 | B15: =F15&C15&D15 -> 170508400 | C15: =LEFT(G15,4) -> 5084 | D15: =LEFT(H15,2) -> 00 | E15: 6040 | F15: 170 | G15: 5084 - IMPLEMENT PUMP | H15: 00 - (NONE) | I15: 170 | J15: EXBH054-HYSY-PUHY | K15: POS.3 | L15: 12000H MAIN PUMP CHANGE POS.3 | M15: =_xlfn.TEXTAFTER(J15,"-") -> HYSY-PUHY | N15: =I15&M15&K15 -> 170HYSY-PUHYPOS.3
A16: =F16&C16&D16 -> 1705084P0 | B16: =F16&C16&D16 -> 1705084P0 | C16: =LEFT(G16,4) -> 5084 | D16: =LEFT(H16,2) -> P0 | E16: 6040 | F16: 170 | G16: 5084 - IMPLEMENT PUMP | H16: P02 | I16: 170 | J16: EXBH054-HYSY-PUHY | K16: POS.2 | L16: 12000H MAIN PUMP CHANGE POS.2 | M16: =_xlfn.TEXTAFTER(J16,"-") -> HYSY-PUHY | N16: =I16&M16&K16 -> 170HYSY-PUHYPOS.2
A17: =F17&C17&D17 -> 1705459RF | B17: =F17&C17&D17 -> 1705459RF | C17: =LEFT(G17,4) -> 5459 | D17: =LEFT(H17,2) -> RF | E17: 6040 | F17: 170 | G17: 5459 - SWING DRIVE | H17: RF - RIGHT FRONT | I17: 170 | J17: EXBH054-SURE-TMSG-SGB2 | K17: RHF | L17: 15000H SWING DRIVE CHANGE RHF | M17: =_xlfn.TEXTAFTER(J17,"-") -> SURE-TMSG-SGB2 | N17: =I17&M17&K17 -> 170SURE-TMSG-SGB2RHF
A18: =F18&C18&D18 -> 1705459LR | B18: =F18&C18&D18 -> 1705459LR | C18: =LEFT(G18,4) -> 5459 | D18: =LEFT(H18,2) -> LR | E18: 6040 | F18: 170 | G18: 5459 - SWING DRIVE | H18: LR - LEFT REAR | I18: 170 | J18: EXBH054-SURE-TMSG-SGB3 | K18: LHR | L18: 15000H SWING DRIVE CHANGE LHR | M18: =_xlfn.TEXTAFTER(J18,"-") -> SURE-TMSG-SGB3 | N18: =I18&M18&K18 -> 170SURE-TMSG-SGB3LHR
A19: =F19&C19&D19 -> 1705459RR | B19: =F19&C19&D19 -> 1705459RR | C19: =LEFT(G19,4) -> 5459 | D19: =LEFT(H19,2) -> RR | E19: 6040 | F19: 170 | G19: 5459 - SWING DRIVE | H19: RR - RIGHT REAR | I19: 170 | J19: EXBH054-SURE-TMSG-SGB4 | K19: RHR | L19: 15000H SWING DRIVE CHANGE RHR | M19: =_xlfn.TEXTAFTER(J19,"-") -> SURE-TMSG-SGB4 | N19: =I19&M19&K19 -> 170SURE-TMSG-SGB4RHR
A20: =F20&C20&D20 -> 185100000 | B20: =F20&C20&D20 -> 185100000 | C20: =LEFT(G20,4) -> 1000 | D20: =LEFT(H20,2) -> 00 | E20: R9350 | F20: 185 | G20: 1000 - ENGINE | H20: 00 - (NONE) | I20: 185 | J20: EXBH011-ENGI | L20: 8000H ENGINE HALF LIFE | M20: =_xlfn.TEXTAFTER(J20,"-") -> ENGI | N20: =I20&M20&K20 -> 185ENGI
A21: =F21&C21&D21 -> 185135300 | B21: =F21&C21&D21 -> 185135300 | C21: =LEFT(G21,4) -> 1353 | D21: =LEFT(H21,2) -> 00 | E21: R9350 | F21: 185 | G21: 1353 - RADIATOR | H21: 00 - (NONE) | I21: 185 | J21: EXBH011-ENGI-COSY | L21: 16000H RADIATOR CHANGE | M21: =_xlfn.TEXTAFTER(J21,"-") -> ENGI-COSY | N21: =I21&M21&K21 -> 185ENGI-COSY
A22: =F22&C22&D22 -> 185310800 | B22: =F22&C22&D22 -> 185310800 | C22: =LEFT(G22,4) -> 3108 | D22: =LEFT(H22,2) -> 00 | E22: R9350 | F22: 185 | G22: 3108 - Pump Drive | H22: 00 - (NONE) | I22: 185 | J22: EXBH011-PUDR | L22: 12000H PUMP DRIVE CHANGE | M22: =_xlfn.TEXTAFTER(J22,"-") -> PUDR | N22: =I22&M22&K22 -> 185PUDR
A23: =F23&C23&D23 -> 1854050RI | B23: =F23&C23&D23 -> 1854050RI | C23: =LEFT(G23,4) -> 4050 | D23: =LEFT(H23,2) -> RI | E23: R9350 | F23: 185 | G23: 4050 - FINAL DRIVE | H23: RI - RIGHT | I23: 185 | J23: EXBH011-UCRG-FIDV | K23: RH | L23: 12000H FINAL DRIVE CHANGE RH | M23: =_xlfn.TEXTAFTER(J23,"-") -> UCRG-FIDV | N23: =I23&M23&K23 -> 185UCRG-FIDVRH
A24: =F24&C24&D24 -> 1854050LT | B24: =F24&C24&D24 -> 1854050LT | C24: =LEFT(G24,4) -> 4050 | D24: =LEFT(H24,2) -> LT | E24: R9350 | F24: 185 | G24: 4050 - FINAL DRIVE | H24: LT - LEFT | I24: 185 | J24: EXBH011-UCRG-FIDV | K24: LH | L24: 12000H FINAL DRIVE CHANGE LH | M24: =_xlfn.TEXTAFTER(J24,"-") -> UCRG-FIDV | N24: =I24&M24&K24 -> 185UCRG-FIDVLH
A25: =F25&C25&D25 -> 1854159LT | B25: =F25&C25&D25 -> 1854159LT | C25: =LEFT(G25,4) -> 4159 | D25: =LEFT(H25,2) -> LT | E25: R9350 | F25: 185 | G25: 4159 - IDLER/IDLER WHEEL | H25: LT - LEFT | I25: 185 | J25: EXBH011-UCRG | K25: LH | L25: 15000H IDLER CHANGE LH | M25: =_xlfn.TEXTAFTER(J25,"-") -> UCRG | N25: =I25&M25&K25 -> 185UCRGLH | O25: Description mentions IDLER
A26: =F26&C26&D26 -> 1854159RI | B26: =F26&C26&D26 -> 1854159RI | C26: =LEFT(G26,4) -> 4159 | D26: =LEFT(H26,2) -> RI | E26: R9350 | F26: 185 | G26: 4159 - IDLER/IDLER WHEEL | H26: RI - RIGHT | I26: 185 | J26: EXBH011-UCRG | K26: RH | L26: 15000H IDLER CHANGE RH | M26: =_xlfn.TEXTAFTER(J26,"-") -> UCRG | N26: =I26&M26&K26 -> 185UCRGRH | O26: Description mentions IDLER
A27: =F27&C27&D27 -> 1854351LF | B27: =F27&C27&D27 -> 1854351LF | C27: =LEFT(G27,4) -> 4351 | D27: =LEFT(H27,2) -> LF | E27: R9350 | F27: 185 | G27: 4351 - HYD PROPEL/DRIVE MOTOR | H27: LF - LEFT FRONT | I27: 185 | J27: EXBH011-HYSY-MOHY | K27: LHF | L27: 12000H TRAVEL MOTOR CHANGE LHF | M27: =_xlfn.TEXTAFTER(J27,"-") -> HYSY-MOHY | N27: =I27&M27&K27 -> 185HYSY-MOHYLHF | O27: Travel motor is hydraulic propel/drive motor
A28: =F28&C28&D28 -> 1854351LR | B28: =F28&C28&D28 -> 1854351LR | C28: =LEFT(G28,4) -> 4351 | D28: =LEFT(H28,2) -> LR | E28: R9350 | F28: 185 | G28: 4351 - HYD PROPEL/DRIVE MOTOR | H28: LR - LEFT REAR | I28: 185 | J28: EXBH011-HYSY-MOHY | K28: LHR | L28: 12000H TRAVEL MOTOR CHANGE LHR | M28: =_xlfn.TEXTAFTER(J28,"-") -> HYSY-MOHY | N28: =I28&M28&K28 -> 185HYSY-MOHYLHR | O28: Travel motor is hydraulic propel/drive motor
A29: =F29&C29&D29 -> 1854351RF | B29: =F29&C29&D29 -> 1854351RF | C29: =LEFT(G29,4) -> 4351 | D29: =LEFT(H29,2) -> RF | E29: R9350 | F29: 185 | G29: 4351 - HYD PROPEL/DRIVE MOTOR | H29: RF - RIGHT FRONT | I29: 185 | J29: EXBH011-HYSY-MOHY | K29: RHF | L29: 12000H TRAVEL MOTOR CHANGE RHF | M29: =_xlfn.TEXTAFTER(J29,"-") -> HYSY-MOHY | N29: =I29&M29&K29 -> 185HYSY-MOHYRHF | O29: Travel motor is hydraulic propel/drive motor
A30: =F30&C30&D30 -> 1854351RR | B30: =F30&C30&D30 -> 1854351RR | C30: =LEFT(G30,4) -> 4351 | D30: =LEFT(H30,2) -> RR | E30: R9350 | F30: 185 | G30: 4351 - HYD PROPEL/DRIVE MOTOR | H30: RR - RIGHT REAR | I30: 185 | J30: EXBH011-HYSY-MOHY | K30: RHR | L30: 12000H TRAVEL MOTOR CHANGE RHR | M30: =_xlfn.TEXTAFTER(J30,"-") -> HYSY-MOHY | N30: =I30&M30&K30 -> 185HYSY-MOHYRHR | O30: Travel motor is hydraulic propel/drive motor
A31: =F31&C31&D31 -> 185508400 | B31: =F31&C31&D31 -> 185508400 | C31: =LEFT(G31,4) -> 5084 | D31: =LEFT(H31,2) -> 00 | E31: R9350 | F31: 185 | G31: 5084 - IMPLEMENT PUMP | H31: 00 - (NONE) | I31: 185 | J31: EXBH011-HYSY | K31: POS.3-4 | L31: 12000H MAIN PUMP POS.3-4 | M31: =_xlfn.TEXTAFTER(J31,"-") -> HYSY | N31: =I31&M31&K31 -> 185HYSYPOS.3-4
A32: =F32&C32&D32 -> 1855459FR | B32: =F32&C32&D32 -> 1855459FR | C32: =LEFT(G32,4) -> 5459 | D32: =LEFT(H32,2) -> FR | E32: R9350 | F32: 185 | G32: 5459 - SWING DRIVE | H32: FR - FRONT | I32: 185 | J32: EXBH011-SURE-TMSG-SGBF | K32: FR | L32: 12000H SWING DRIVE CHANGE FR | M32: =_xlfn.TEXTAFTER(J32,"-") -> SURE-TMSG-SGBF | N32: =I32&M32&K32 -> 185SURE-TMSG-SGBFFR
A33: =F33&C33&D33 -> 1855459RE | B33: =F33&C33&D33 -> 1855459RE | C33: =LEFT(G33,4) -> 5459 | D33: =LEFT(H33,2) -> RE | E33: R9350 | F33: 185 | G33: 5459 - SWING DRIVE | H33: RE - REAR | I33: 185 | J33: EXBH011-SURE-TMSG-SGBR | K33: RR | L33: 12000H SWING DRIVE CHANGE RR | M33: =_xlfn.TEXTAFTER(J33,"-") -> SURE-TMSG-SGBR | N33: =I33&M33&K33 -> 185SURE-TMSG-SGBRRR
A34: =F34&C34&D34 -> 1855473P0 | B34: =F34&C34&D34 -> 1855473P0 | C34: =LEFT(G34,4) -> 5473 | D34: =LEFT(H34,2) -> P0 | E34: R9350 | F34: 185 | G34: 5473 - SWING PUMP | H34: P01 | I34: 185 | J34: EXBH011-HYSY | K34: POS.1-2 | L34: 12000H SWING PUMP POS.1-2 | M34: =_xlfn.TEXTAFTER(J34,"-") -> HYSY | N34: =I34&M34&K34 -> 185HYSYPOS.1-2
A35: =F35&C35&D35 -> 18579PAFR | B35: =F35&C35&D35 -> 18579PAFR | C35: =LEFT(G35,4) -> 79PA | D35: =LEFT(H35,2) -> FR | E35: R9350 | F35: 185 | G35: 79PA - SWING DRIVE MOTOR | H35: FR - FRONT | I35: 185 | J35: EXBH011-HYSY-MOHY | K35: FR | L35: 12000H SWING MOTOR CHANGE FR | M35: =_xlfn.TEXTAFTER(J35,"-") -> HYSY-MOHY | N35: =I35&M35&K35 -> 185HYSY-MOHYFR | O35: Swing motor is swing drive motor
A36: =F36&C36&D36 -> 18579PARE | B36: =F36&C36&D36 -> 18579PARE | C36: =LEFT(G36,4) -> 79PA | D36: =LEFT(H36,2) -> RE | E36: R9350 | F36: 185 | G36: 79PA - SWING DRIVE MOTOR | H36: RE - REAR | I36: 185 | J36: EXBH011-HYSY-MOHY | K36: RR | L36: 12000H SWING MOTOR CHANGE RR | M36: =_xlfn.TEXTAFTER(J36,"-") -> HYSY-MOHY | N36: =I36&M36&K36 -> 185HYSY-MOHYRR | O36: Swing motor is swing drive motor
A37: =F37&C37&D37 -> 3401000RI | B37: =F37&C37&D37 -> 3401000RI | C37: =LEFT(G37,4) -> 1000 | D37: =LEFT(H37,2) -> RI | E37: 6060 | F37: 340 | G37: 1000 - ENGINE | H37: RI - RIGHT | I37: 340 | J37: EXBH047-ENG2 | K37: RH | L37: 14300H ENGINE CHANGE RH | M37: =_xlfn.TEXTAFTER(J37,"-") -> ENG2 | N37: =I37&M37&K37 -> 340ENG2RH
A38: =F38&C38&D38 -> 3401000LT | B38: =F38&C38&D38 -> 3401000LT | C38: =LEFT(G38,4) -> 1000 | D38: =LEFT(H38,2) -> LT | E38: 6060 | F38: 340 | G38: 1000 - ENGINE | H38: LT - LEFT | I38: 340 | J38: EXBH047-ENG1 | K38: LH | L38: 14300H ENGINE CHANGE LH | M38: =_xlfn.TEXTAFTER(J38,"-") -> ENG1 | N38: =I38&M38&K38 -> 340ENG1LH
A39: =F39&C39&D39 -> 3401353LT | B39: =F39&C39&D39 -> 3401353LT | C39: =LEFT(G39,4) -> 1353 | D39: =LEFT(H39,2) -> LT | E39: 6060 | F39: 340 | G39: 1353 - RADIATOR | H39: LT - LEFT | I39: 340 | J39: EXBH047-ENG1-COSY-RADT | K39: LH | L39: 14300H RADIATOR CHANGE LH | M39: =_xlfn.TEXTAFTER(J39,"-") -> ENG1-COSY-RADT | N39: =I39&M39&K39 -> 340ENG1-COSY-RADTLH
A40: =F40&C40&D40 -> 3401353RI | B40: =F40&C40&D40 -> 3401353RI | C40: =LEFT(G40,4) -> 1353 | D40: =LEFT(H40,2) -> RI | E40: 6060 | F40: 340 | G40: 1353 - RADIATOR | H40: RI - RIGHT | I40: 340 | J40: EXBH047-ENG2-COSY-RADT | K40: RH | L40: 14300H RADIATOR CHANGE RH | M40: =_xlfn.TEXTAFTER(J40,"-") -> ENG2-COSY-RADT | N40: =I40&M40&K40 -> 340ENG2-COSY-RADTRH
A41: =F41&C41&D41 -> 3403108RI | B41: =F41&C41&D41 -> 3403108RI | C41: =LEFT(G41,4) -> 3108 | D41: =LEFT(H41,2) -> RI | E41: 6060 | F41: 340 | G41: 3108 - PUMP DRIVE GRP | H41: RI - RIGHT | I41: 340 | J41: EXBH047-PUD2 | K41: RH | L41: 16500H PUMP DRIVE CHANGE RH | M41: =_xlfn.TEXTAFTER(J41,"-") -> PUD2 | N41: =I41&M41&K41 -> 340PUD2RH | O41: Description mentions PUMP DRIVE
A42: =F42&C42&D42 -> 3404028LT | B42: =F42&C42&D42 -> 3404028LT | C42: =LEFT(G42,4) -> 4028 | D42: =LEFT(H42,2) -> LT | E42: 6060 | F42: 340 | G42: 4028 - TRACK FRAME | H42: LT - LEFT | I42: 340 | J42: EXBH009-UCRG-TCFS-TCFL | K42: LH | L42: 22000H TRACK ROLLER FRAME CHANGE LH | M42: =_xlfn.TEXTAFTER(J42,"-") -> UCRG-TCFS-TCFL | N42: =I42&M42&K42 -> 340UCRG-TCFS-TCFLLH | O42: Description contains TRACK FRAME
A43: =F43&C43&D43 -> 3404028RI | B43: =F43&C43&D43 -> 3404028RI | C43: =LEFT(G43,4) -> 4028 | D43: =LEFT(H43,2) -> RI | E43: 6060 | F43: 340 | G43: 4028 - TRACK FRAME | H43: RI - RIGHT | I43: 340 | J43: EXBH009-UCRG-TCFS-TCFR | K43: RH | L43: 22000H TRACK ROLLER FRAME CHANGE RH | M43: =_xlfn.TEXTAFTER(J43,"-") -> UCRG-TCFS-TCFR | N43: =I43&M43&K43 -> 340UCRG-TCFS-TCFRRH | O43: Description contains TRACK FRAME
A44: =F44&C44&D44 -> 3404050RI | B44: =F44&C44&D44 -> 3404050RI | C44: =LEFT(G44,4) -> 4050 | D44: =LEFT(H44,2) -> RI | E44: 6060 | F44: 340 | G44: 4050 - FINAL DRIVE | H44: RI - RIGHT | I44: 340 | J44: EXBH047-UCRG-FIDV-FIDR | K44: RH | L44: 33000H FINAL DRIVE CHANGE RH | M44: =_xlfn.TEXTAFTER(J44,"-") -> UCRG-FIDV-FIDR | N44: =I44&M44&K44 -> 340UCRG-FIDV-FIDRRH
A45: =F45&C45&D45 -> 3404050LT | B45: =F45&C45&D45 -> 3404050LT | C45: =LEFT(G45,4) -> 4050 | D45: =LEFT(H45,2) -> LT | E45: 6060 | F45: 340 | G45: 4050 - FINAL DRIVE | H45: LT - LEFT | I45: 340 | J45: EXBH047-UCRG-FIDV-FIDL | K45: LH | L45: 33000H FINAL DRIVE CHANGE LH | M45: =_xlfn.TEXTAFTER(J45,"-") -> UCRG-FIDV-FIDL | N45: =I45&M45&K45 -> 340UCRG-FIDV-FIDLLH
A46: =F46&C46&D46 -> 3404159RI | B46: =F46&C46&D46 -> 3404159RI | C46: =LEFT(G46,4) -> 4159 | D46: =LEFT(H46,2) -> RI | E46: 6060 | F46: 340 | G46: 4159 - IDLER/IDLER WHEEL | H46: RI - RIGHT | I46: 340 | J46: EXBH009-UCRG-TCID-TCIR | K46: RH | L46: 22000H IDLER CHANGE RH | M46: =_xlfn.TEXTAFTER(J46,"-") -> UCRG-TCID-TCIR | N46: =I46&M46&K46 -> 340UCRG-TCID-TCIRRH | O46: Description contains IDLER
A47: =F47&C47&D47 -> 3404159LT | B47: =F47&C47&D47 -> 3404159LT | C47: =LEFT(G47,4) -> 4159 | D47: =LEFT(H47,2) -> LT | E47: 6060 | F47: 340 | G47: 4159 - IDLER/IDLER WHEEL | H47: LT - LEFT | I47: 340 | J47: EXBH009-UCRG-TCID-TCIL | K47: LH | L47: 22000H IDLER CHANGE LH | M47: =_xlfn.TEXTAFTER(J47,"-") -> UCRG-TCID-TCIL | N47: =I47&M47&K47 -> 340UCRG-TCID-TCILLH | O47: Description contains IDLER
A48: =F48&C48&D48 -> 3404164LT | B48: =F48&C48&D48 -> 3404164LT | C48: =LEFT(G48,4) -> 4164 | D48: =LEFT(H48,2) -> LT | E48: 6060 | F48: 340 | G48: 4164 - SPROCKET ASSEMBLY | H48: LT - LEFT | I48: 340 | J48: EXBH047-UCRG-DRSP-DRSL | K48: LH | L48: 22000H DRIVE SPROCKET CHANGE LH | M48: =_xlfn.TEXTAFTER(J48,"-") -> UCRG-DRSP-DRSL | N48: =I48&M48&K48 -> 340UCRG-DRSP-DRSLLH
A49: =F49&C49&D49 -> 3404164RI | B49: =F49&C49&D49 -> 3404164RI | C49: =LEFT(G49,4) -> 4164 | D49: =LEFT(H49,2) -> RI | E49: 6060 | F49: 340 | G49: 4164 - SPROCKET ASSEMBLY | H49: RI - RIGHT | I49: 340 | J49: EXBH047-UCRG-DRSP-DRSR | K49: RH | L49: 22000H DRIVE SPROCKET CHANGE RH | M49: =_xlfn.TEXTAFTER(J49,"-") -> UCRG-DRSP-DRSR | N49: =I49&M49&K49 -> 340UCRG-DRSP-DRSRRH
A50: =F50&C50&D50 -> 3404351LR | B50: =F50&C50&D50 -> 3404351LR | C50: =LEFT(G50,4) -> 4351 | D50: =LEFT(H50,2) -> LR | E50: 6060 | F50: 340 | G50: 4351 - HYD PROPEL/DRIVE MOTOR | H50: LR - LEFT REAR | I50: 340 | J50: EXBH009-HYSY-MOHY-TRLL | K50: LHR | L50: 16500H TRAVEL MOTOR CHANGE LHR | M50: =_xlfn.TEXTAFTER(J50,"-") -> HYSY-MOHY-TRLL | N50: =I50&M50&K50 -> 340HYSY-MOHY-TRLLLHR | O50: Description contains TRAVEL MOTOR (hydraulic propel)
A51: =F51&C51&D51 -> 3404351RF | B51: =F51&C51&D51 -> 3404351RF | C51: =LEFT(G51,4) -> 4351 | D51: =LEFT(H51,2) -> RF | E51: 6060 | F51: 340 | G51: 4351 - HYD PROPEL/DRIVE MOTOR | H51: RF - RIGHT FRONT | I51: 340 | J51: EXBH009-HYSY-MOHY-TRLR | K51: RHF | L51: 16500H TRAVEL MOTOR CHANGE RHF | M51: =_xlfn.TEXTAFTER(J51,"-") -> HYSY-MOHY-TRLR | N51: =I51&M51&K51 -> 340HYSY-MOHY-TRLRRHF | O51: Description contains TRAVEL MOTOR (hydraulic propel)
A52: =F52&C52&D52 -> 3405070LF | B52: =F52&C52&D52 -> 3405070LF | C52: =LEFT(G52,4) -> 5070 | D52: =LEFT(H52,2) -> LF | E52: 6060 | F52: 340 | G52: 5070 - PISTON PUMP | H52: LF - LEFT FRONT | I52: 340 | M52: =_xlfn.TEXTAFTER(J52,"-") -> #N/A | N52: =I52&M52&K52 -> #N/A | O52: Hydraulic control valve is part of hydraulic system
A53: =F53&C53&D53 -> 3405070RF | B53: =F53&C53&D53 -> 3405070RF | C53: =LEFT(G53,4) -> 5070 | D53: =LEFT(H53,2) -> RF | E53: 6060 | F53: 340 | G53: 5070 - PISTON PUMP | H53: RF - RIGHT FRONT | I53: 340 | M53: =_xlfn.TEXTAFTER(J53,"-") -> #N/A | N53: =I53&M53&K53 -> #N/A | O53: Hydraulic control valve is part of hydraulic system
A54: =F54&C54&D54 -> 3405070LR | B54: =F54&C54&D54 -> 3405070LR | C54: =LEFT(G54,4) -> 5070 | D54: =LEFT(H54,2) -> LR | E54: 6060 | F54: 340 | G54: 5070 - PISTON PUMP | H54: LR - LEFT REAR | I54: 340 | M54: =_xlfn.TEXTAFTER(J54,"-") -> #N/A | N54: =I54&M54&K54 -> #N/A | O54: Hydraulic control valve is part of hydraulic system
A55: =F55&C55&D55 -> 3405070RR | B55: =F55&C55&D55 -> 3405070RR | C55: =LEFT(G55,4) -> 5070 | D55: =LEFT(H55,2) -> RR | E55: 6060 | F55: 340 | G55: 5070 - PISTON PUMP | H55: RR - RIGHT REAR | I55: 340 | M55: =_xlfn.TEXTAFTER(J55,"-") -> #N/A | N55: =I55&M55&K55 -> #N/A | O55: Hydraulic control valve is part of hydraulic system
A56: =F56&C56&D56 -> 3405070LT | B56: =F56&C56&D56 -> 3405070LT | C56: =LEFT(G56,4) -> 5070 | D56: =LEFT(H56,2) -> LT | E56: 6060 | F56: 340 | G56: 5070 - PISTON PUMP | H56: LT - LEFT | I56: 340 | M56: =_xlfn.TEXTAFTER(J56,"-") -> #N/A | N56: =I56&M56&K56 -> #N/A | O56: Travel speed valve is hydraulic system
A57: =F57&C57&D57 -> 340507000 | B57: =F57&C57&D57 -> 340507000 | C57: =LEFT(G57,4) -> 5070 | D57: =LEFT(H57,2) -> 00 | E57: 6060 | F57: 340 | G57: 5070 - PISTON PUMP | H57: 00 - (NONE) | I57: 340 | M57: =_xlfn.TEXTAFTER(J57,"-") -> #N/A | N57: =I57&M57&K57 -> #N/A | O57: Description contains MAIN/IMPLEMENT PUMP
A58: =F58&C58&D58 -> 3405070RI | B58: =F58&C58&D58 -> 3405070RI | C58: =LEFT(G58,4) -> 5070 | D58: =LEFT(H58,2) -> RI | E58: 6060 | F58: 340 | G58: 5070 - PISTON PUMP | H58: RI - RIGHT | I58: 340 | M58: =_xlfn.TEXTAFTER(J58,"-") -> #N/A | N58: =I58&M58&K58 -> #N/A | O58: Description contains SWING PUMP (hydraulic pump)
A59: =F59&C59&D59 -> 3405084P0 | B59: =F59&C59&D59 -> 3405084P0 | C59: =LEFT(G59,4) -> 5084 | D59: =LEFT(H59,2) -> P0 | E59: 6060 | F59: 340 | G59: 5084 - IMPLEMENT PUMP | H59: P01 | I59: 340 | J59: EXBH047-HYSY-PUHY-PUM1 | K59: P1 | L59: 13200H IMPLEMENT PUMP CHANGE POS.1 | M59: =_xlfn.TEXTAFTER(J59,"-") -> HYSY-PUHY-PUM1 | N59: =I59&M59&K59 -> 340HYSY-PUHY-PUM1P1
A60: =F60&C60&D60 -> 340508400 | B60: =F60&C60&D60 -> 340508400 | C60: =LEFT(G60,4) -> 5084 | D60: =LEFT(H60,2) -> 00 | E60: 6060 | F60: 340 | G60: 5084 - IMPLEMENT PUMP | H60: 00 - (NONE) | I60: 340 | J60: EXBH047-HYSY-PUHY-PUM4 | K60: P4 | L60: 13200H IMPLEMENT PUMP CHANGE POS.4 | M60: =_xlfn.TEXTAFTER(J60,"-") -> HYSY-PUHY-PUM4 | N60: =I60&M60&K60 -> 340HYSY-PUHY-PUM4P4
A61: =F61&C61&D61 -> 3405456LT | B61: =F61&C61&D61 -> 3405456LT | C61: =LEFT(G61,4) -> 5456 | D61: =LEFT(H61,2) -> LT | E61: 6060 | F61: 340 | G61: 5456 - BOOM CYLINDER | H61: LT - LEFT | I61: 340 | J61: EXBH047-HYSY-CYHY-CYBL | K61: LH | L61: 13200H BOOM CYLINDER CHANGE LH | M61: =_xlfn.TEXTAFTER(J61,"-") -> HYSY-CYHY-CYBL | N61: =I61&M61&K61 -> 340HYSY-CYHY-CYBLLH | O61: Description contains BOOM CHANGE (major structural)
A62: =F62&C62&D62 -> 3405456RI | B62: =F62&C62&D62 -> 3405456RI | C62: =LEFT(G62,4) -> 5456 | D62: =LEFT(H62,2) -> RI | E62: 6060 | F62: 340 | G62: 5456 - BOOM CYLINDER | H62: RI - RIGHT | I62: 340 | J62: EXBH009-HYSY-CYHY-CYBR | K62: RH | L62: 13200H BOOM CYLINDER CHANGE RH | M62: =_xlfn.TEXTAFTER(J62,"-") -> HYSY-CYHY-CYBR | N62: =I62&M62&K62 -> 340HYSY-CYHY-CYBRRH | O62: Description contains BOOM CHANGE (major structural)
A63: =F63&C63&D63 -> 3405459LF | B63: =F63&C63&D63 -> 3405459LF | C63: =LEFT(G63,4) -> 5459 | D63: =LEFT(H63,2) -> LF | E63: 6060 | F63: 340 | G63: 5459 - SWING DRIVE | H63: LF - LEFT FRONT | I63: 340 | J63: EXBH047-SURE-TMSG-SGB1 | K63: LHF | L63: 16500H SWING DRIVE CHANGE LHF | M63: =_xlfn.TEXTAFTER(J63,"-") -> SURE-TMSG-SGB1 | N63: =I63&M63&K63 -> 340SURE-TMSG-SGB1LHF
A64: =F64&C64&D64 -> 3405459RF | B64: =F64&C64&D64 -> 3405459RF | C64: =LEFT(G64,4) -> 5459 | D64: =LEFT(H64,2) -> RF | E64: 6060 | F64: 340 | G64: 5459 - SWING DRIVE | H64: RF - RIGHT FRONT | I64: 340 | J64: EXBH047-SURE-TMSG-SGB2 | K64: RHF | L64: 16500H SWING DRIVE CHANGE RHF | M64: =_xlfn.TEXTAFTER(J64,"-") -> SURE-TMSG-SGB2 | N64: =I64&M64&K64 -> 340SURE-TMSG-SGB2RHF
A65: =F65&C65&D65 -> 3405459LR | B65: =F65&C65&D65 -> 3405459LR | C65: =LEFT(G65,4) -> 5459 | D65: =LEFT(H65,2) -> LR | E65: 6060 | F65: 340 | G65: 5459 - SWING DRIVE | H65: LR - LEFT REAR | I65: 340 | J65: EXBH047-SURE-TMSG-SGB3 | K65: LHR | L65: 16500H SWING DRIVE CHANGE LHR | M65: =_xlfn.TEXTAFTER(J65,"-") -> SURE-TMSG-SGB3 | N65: =I65&M65&K65 -> 340SURE-TMSG-SGB3LHR
A66: =F66&C66&D66 -> 3405459RR | B66: =F66&C66&D66 -> 3405459RR | C66: =LEFT(G66,4) -> 5459 | D66: =LEFT(H66,2) -> RR | E66: 6060 | F66: 340 | G66: 5459 - SWING DRIVE | H66: RR - RIGHT REAR | I66: 340 | J66: EXBH047-SURE-TMSG-SGB4 | K66: RHR | L66: 16500H SWING DRIVE CHANGE RHR | M66: =_xlfn.TEXTAFTER(J66,"-") -> SURE-TMSG-SGB4 | N66: =I66&M66&K66 -> 340SURE-TMSG-SGB4RHR
A67: =F67&C67&D67 -> 3405459RI | B67: =F67&C67&D67 -> 3405459RI | C67: =LEFT(G67,4) -> 5459 | D67: =LEFT(H67,2) -> RI | E67: 6060 | F67: 340 | G67: 5459 - SWING DRIVE | H67: RI - RIGHT | I67: 340 | J67: EXBH009-SURE-TMSG-SGB4 | K67: RHR | L67: 16500H SWING DRIVE CHANGE RHR | M67: =_xlfn.TEXTAFTER(J67,"-") -> SURE-TMSG-SGB4 | N67: =I67&M67&K67 -> 340SURE-TMSG-SGB4RHR | O67: Description contains SWING DRIVE
A68: =F68&C68&D68 -> 3405473LT | B68: =F68&C68&D68 -> 3405473LT | C68: =LEFT(G68,4) -> 5473 | D68: =LEFT(H68,2) -> LT | E68: 6060 | F68: 340 | G68: 5473 - SWING PUMP | H68: LT - LEFT | I68: 340 | J68: EXBH047-HYSY-PUHY | K68: LHP2 | L68: 13200H SWING PUMP CHANGE LH POS.2 | M68: =_xlfn.TEXTAFTER(J68,"-") -> HYSY-PUHY | N68: =I68&M68&K68 -> 340HYSY-PUHYLHP2
A69: =F69&C69&D69 -> 442100000 | B69: =F69&C69&D69 -> 442100000 | C69: =LEFT(G69,4) -> 1000 | D69: =LEFT(H69,2) -> 00 | E69: 994F | F69: 442 | G69: 1000 - ENGINE | H69: 00 - (NONE) | I69: 442 | J69: LOFE043-ENGI | L69: 19800H ENGINE CHANGE | M69: =_xlfn.TEXTAFTER(J69,"-") -> ENGI | N69: =I69&M69&K69 -> 442ENGI
A70: =F70&C70&D70 -> 442135300 | B70: =F70&C70&D70 -> 442135300 | C70: =LEFT(G70,4) -> 1353 | D70: =LEFT(H70,2) -> 00 | E70: 994F | F70: 442 | G70: 1353 - RADIATOR | H70: 00 - (NONE) | I70: 442 | J70: LOFE043-ENGI-COSY | L70: 19800H RADIATOR CHANGE | M70: =_xlfn.TEXTAFTER(J70,"-") -> ENGI-COSY | N70: =I70&M70&K70 -> 442ENGI-COSY
A71: =F71&C71&D71 -> 442300600 | B71: =F71&C71&D71 -> 442300600 | C71: =LEFT(G71,4) -> 3006 | D71: =LEFT(H71,2) -> 00 | E71: 994F | F71: 442 | G71: 3006 - TRANSMISSION & DIFFERENTIAL UNIT | H71: 00 - (NONE) | I71: 442 | J71: LOFE043-DRIV | L71: 11000H TRANSFER GEARS CHANGE | M71: =_xlfn.TEXTAFTER(J71,"-") -> DRIV | N71: =I71&M71&K71 -> 442DRIV | O71: Transfer gears are part of transmission system
A72: =F72&C72&D72 -> 442303000 | B72: =F72&C72&D72 -> 442303000 | C72: =LEFT(G72,4) -> 3030 | D72: =LEFT(H72,2) -> 00 | E72: 994F | F72: 442 | G72: 3030 - TRANSMISSION | H72: 00 - (NONE) | I72: 442 | J72: LOFE043-DRIV-TMSN | L72: 11000H TRANSMISSION CHANGE | M72: =_xlfn.TEXTAFTER(J72,"-") -> DRIV-TMSN | N72: =I72&M72&K72 -> 442DRIV-TMSN
A73: =F73&C73&D73 -> 442310100 | B73: =F73&C73&D73 -> 442310100 | C73: =LEFT(G73,4) -> 3101 | D73: =LEFT(H73,2) -> 00 | E73: 994F | F73: 442 | G73: 3101 - TORQUE CONVERTER | H73: 00 - (NONE) | I73: 442 | J73: LOFE043-DRIV-TQCV | L73: 19800H TORQUE CONVERTER CHANGE | M73: =_xlfn.TEXTAFTER(J73,"-") -> DRIV-TQCV | N73: =I73&M73&K73 -> 442DRIV-TQCV
A74: =F74&C74&D74 -> 4423108RE | B74: =F74&C74&D74 -> 4423108RE | C74: =LEFT(G74,4) -> 3108 | D74: =LEFT(H74,2) -> RE | E74: 994F | F74: 442 | G74: 3108 - PUMP DRIVE GRP | H74: RE - REAR | I74: 442 | J74: LOFE043-DRIV | K74: RR | L74: 16500H PUMP DRIVE CHANGE RR | M74: =_xlfn.TEXTAFTER(J74,"-") -> DRIV | N74: =I74&M74&K74 -> 442DRIVRR | O74: Description mentions PUMP DRIVE
A75: =F75&C75&D75 -> 4423258RE | B75: =F75&C75&D75 -> 4423258RE | C75: =LEFT(G75,4) -> 3258 | D75: =LEFT(H75,2) -> RE | E75: 994F | F75: 442 | G75: 3258 - DIFFERENTIAL | H75: RE - REAR | I75: 442 | J75: LOFE043-DRIV-DIFF | K75: RR | L75: 16500H DIFFERENTIAL CHANGE RR | M75: =_xlfn.TEXTAFTER(J75,"-") -> DRIV-DIFF | N75: =I75&M75&K75 -> 442DRIV-DIFFRR
A76: =F76&C76&D76 -> 4423258FR | B76: =F76&C76&D76 -> 4423258FR | C76: =LEFT(G76,4) -> 3258 | D76: =LEFT(H76,2) -> FR | E76: 994F | F76: 442 | G76: 3258 - DIFFERENTIAL | H76: FR - FRONT | I76: 442 | J76: LOFE043-DRIV-DIFF | K76: FR | L76: 16500H DIFFERENTIAL CHANGE FR | M76: =_xlfn.TEXTAFTER(J76,"-") -> DRIV-DIFF | N76: =I76&M76&K76 -> 442DRIV-DIFFFR
A77: =F77&C77&D77 -> 4424050LR | B77: =F77&C77&D77 -> 4424050LR | C77: =LEFT(G77,4) -> 4050 | D77: =LEFT(H77,2) -> LR | E77: 994F | F77: 442 | G77: 4050 - FINAL DRIVE | H77: LR - LEFT REAR | I77: 442 | J77: LOFE043-DRIV-FIDV | K77: LHR | L77: 19800H WHEEL END CHANGE LHR | M77: =_xlfn.TEXTAFTER(J77,"-") -> DRIV-FIDV | N77: =I77&M77&K77 -> 442DRIV-FIDVLHR
A78: =F78&C78&D78 -> 4424050RF | B78: =F78&C78&D78 -> 4424050RF | C78: =LEFT(G78,4) -> 4050 | D78: =LEFT(H78,2) -> RF | E78: 994F | F78: 442 | G78: 4050 - FINAL DRIVE | H78: RF - RIGHT FRONT | I78: 442 | J78: LOFE043-DRIV-FIDV | K78: RHF | L78: 19800H WHEEL END CHANGE RHF | M78: =_xlfn.TEXTAFTER(J78,"-") -> DRIV-FIDV | N78: =I78&M78&K78 -> 442DRIV-FIDVRHF
A79: =F79&C79&D79 -> 4424050LF | B79: =F79&C79&D79 -> 4424050LF | C79: =LEFT(G79,4) -> 4050 | D79: =LEFT(H79,2) -> LF | E79: 994F | F79: 442 | G79: 4050 - FINAL DRIVE | H79: LF - LEFT FRONT | I79: 442 | J79: LOFE043-DRIV-FIDV | K79: LHF | L79: 19800H WHEEL END CHANGE LHF | M79: =_xlfn.TEXTAFTER(J79,"-") -> DRIV-FIDV | N79: =I79&M79&K79 -> 442DRIV-FIDVLHF
A80: =F80&C80&D80 -> 4424050RR | B80: =F80&C80&D80 -> 4424050RR | C80: =LEFT(G80,4) -> 4050 | D80: =LEFT(H80,2) -> RR | E80: 994F | F80: 442 | G80: 4050 - FINAL DRIVE | H80: RR - RIGHT REAR | I80: 442 | J80: LOFE043-DRIV-FIDV | K80: RHR | L80: 19800H WHEEL END CHANGE RHR | M80: =_xlfn.TEXTAFTER(J80,"-") -> DRIV-FIDV | N80: =I80&M80&K80 -> 442DRIV-FIDVRHR
A81: =F81&C81&D81 -> 442405000 | B81: =F81&C81&D81 -> 442405000 | C81: =LEFT(G81,4) -> 4050 | D81: =LEFT(H81,2) -> 00 | E81: 994F | F81: 442 | G81: 4050 - FINAL DRIVE | H81: 00 - (NONE) | I81: 442 | J81: LOFE043-DRIV-DRSH | L81: 16500H DRIVE SHAFT CHANGE | M81: =_xlfn.TEXTAFTER(J81,"-") -> DRIV-DRSH | N81: =I81&M81&K81 -> 442DRIV-DRSH | O81: Description contains DRIVE SHAFT (power transfer)
A82: =F82&C82&D82 -> 615100000 | B82: =F82&C82&D82 -> 615100000 | C82: =LEFT(G82,4) -> 1000 | D82: =LEFT(H82,2) -> 00 | E82: WA600-6LC | F82: 615 | G82: 1000 - ENGINE | H82: 00 - (NONE) | I82: 615 | J82: LOFE137-ENGI | L82: 18000H ENGINE CHANGE | M82: =_xlfn.TEXTAFTER(J82,"-") -> ENGI | N82: =I82&M82&K82 -> 615ENGI
A83: =F83&C83&D83 -> 615135300 | B83: =F83&C83&D83 -> 615135300 | C83: =LEFT(G83,4) -> 1353 | D83: =LEFT(H83,2) -> 00 | E83: WA600-6LC | F83: 615 | G83: 1353 - RADIATOR | H83: 00 - (NONE) | I83: 615 | J83: LOFE137-ENGI-COSY | L83: 18000H RADIATOR CHANGE | M83: =_xlfn.TEXTAFTER(J83,"-") -> ENGI-COSY | N83: =I83&M83&K83 -> 615ENGI-COSY
A84: =F84&C84&D84 -> 615303000 | B84: =F84&C84&D84 -> 615303000 | C84: =LEFT(G84,4) -> 3030 | D84: =LEFT(H84,2) -> 00 | E84: WA600-6LC | F84: 615 | G84: 3030 - TRANSMISSION | H84: 00 - (NONE) | I84: 615 | J84: LOFE137-DRIV-TMSN | L84: 18000H TRANSMISSION CHANGE | M84: =_xlfn.TEXTAFTER(J84,"-") -> DRIV-TMSN | N84: =I84&M84&K84 -> 615DRIV-TMSN
A85: =F85&C85&D85 -> 615310100 | B85: =F85&C85&D85 -> 615310100 | C85: =LEFT(G85,4) -> 3101 | D85: =LEFT(H85,2) -> 00 | E85: WA600-6LC | F85: 615 | G85: 3101 - TORQUE CONVERTER | H85: 00 - (NONE) | I85: 615 | J85: LOFE137-DRIV-TQCV | L85: 18000H TORQUE CONVERTER CHANGE | M85: =_xlfn.TEXTAFTER(J85,"-") -> DRIV-TQCV | N85: =I85&M85&K85 -> 615DRIV-TQCV
A86: =F86&C86&D86 -> 6153258FR | B86: =F86&C86&D86 -> 6153258FR | C86: =LEFT(G86,4) -> 3258 | D86: =LEFT(H86,2) -> FR | E86: WA600-6LC | F86: 615 | G86: 3258 - DIFFERENTIAL | H86: FR - FRONT | I86: 615 | J86: LOFE137-DRIV-DIFF | K86: FR | L86: 18000H DIFFERENTIAL CHANGE FR | M86: =_xlfn.TEXTAFTER(J86,"-") -> DRIV-DIFF | N86: =I86&M86&K86 -> 615DRIV-DIFFFR
A87: =F87&C87&D87 -> 6153258RE | B87: =F87&C87&D87 -> 6153258RE | C87: =LEFT(G87,4) -> 3258 | D87: =LEFT(H87,2) -> RE | E87: WA600-6LC | F87: 615 | G87: 3258 - DIFFERENTIAL | H87: RE - REAR | I87: 615 | J87: LOFE137-DRIV-DIFF | K87: RR | L87: 18000H DIFFERENTIAL CHANGE RR | M87: =_xlfn.TEXTAFTER(J87,"-") -> DRIV-DIFF | N87: =I87&M87&K87 -> 615DRIV-DIFFRR
A88: =F88&C88&D88 -> 6154008RI | B88: =F88&C88&D88 -> 6154008RI | C88: =LEFT(G88,4) -> 4008 | D88: =LEFT(H88,2) -> RI | E88: WA600-6LC | F88: 615 | G88: 4008 - FINAL DRIVE, BRAKE & WHEEL | H88: RI - RIGHT | I88: 615 | J88: LOFE136-DRIV-FIDV | K88: RHR | L88: 18000H WHEEL END CHANGE RHR | M88: =_xlfn.TEXTAFTER(J88,"-") -> DRIV-FIDV | N88: =I88&M88&K88 -> 615DRIV-FIDVRHR | O88: Description contains WHEEL END/GROUP (final drive+brake+wheel)
A89: =F89&C89&D89 -> 6154050LF | B89: =F89&C89&D89 -> 6154050LF | C89: =LEFT(G89,4) -> 4050 | D89: =LEFT(H89,2) -> LF | E89: WA600-6LC | F89: 615 | G89: 4050 - FINAL DRIVE | H89: LF - LEFT FRONT | I89: 615 | J89: LOFE137-DRIV-FIDV | K89: LHF | L89: 18000H WHEEL END CHANGE LHF | M89: =_xlfn.TEXTAFTER(J89,"-") -> DRIV-FIDV | N89: =I89&M89&K89 -> 615DRIV-FIDVLHF
A90: =F90&C90&D90 -> 6154050RF | B90: =F90&C90&D90 -> 6154050RF | C90: =LEFT(G90,4) -> 4050 | D90: =LEFT(H90,2) -> RF | E90: WA600-6LC | F90: 615 | G90: 4050 - FINAL DRIVE | H90: RF - RIGHT FRONT | I90: 615 | J90: LOFE137-DRIV-FIDV | K90: RHF | L90: 18000H WHEEL END CHANGE RHF | M90: =_xlfn.TEXTAFTER(J90,"-") -> DRIV-FIDV | N90: =I90&M90&K90 -> 615DRIV-FIDVRHF
A91: =F91&C91&D91 -> 6154050LR | B91: =F91&C91&D91 -> 6154050LR | C91: =LEFT(G91,4) -> 4050 | D91: =LEFT(H91,2) -> LR | E91: WA600-6LC | F91: 615 | G91: 4050 - FINAL DRIVE | H91: LR - LEFT REAR | I91: 615 | J91: LOFE137-DRIV-FIDV | K91: LHR | L91: 18000H WHEEL END CHANGE LHR | M91: =_xlfn.TEXTAFTER(J91,"-") -> DRIV-FIDV | N91: =I91&M91&K91 -> 615DRIV-FIDVLHR
A92: =F92&C92&D92 -> 6154050RR | B92: =F92&C92&D92 -> 6154050RR | C92: =LEFT(G92,4) -> 4050 | D92: =LEFT(H92,2) -> RR | E92: WA600-6LC | F92: 615 | G92: 4050 - FINAL DRIVE | H92: RR - RIGHT REAR | I92: 615 | J92: LOFE137-DRIV-FIDV | K92: RHR | L92: 18000H WHEEL END CHANGE RHR | M92: =_xlfn.TEXTAFTER(J92,"-") -> DRIV-FIDV | N92: =I92&M92&K92 -> 615DRIV-FIDVRHR
A93: =F93&C93&D93 -> 050100000 | B93: =F93&C93&D93 -> 050100000 | C93: =LEFT(G93,4) -> 1000 | D93: =LEFT(H93,2) -> 00 | E93: 988B | F93: 050 | G93: 1000 - ENGINE | H93: 00 - (NONE) | I93: 050 | J93: LOFE046-ENGI | L93: 15400H ENGINE CHANGE | M93: =_xlfn.TEXTAFTER(J93,"-") -> ENGI | N93: =I93&M93&K93 -> 050ENGI
A94: =F94&C94&D94 -> DHJ1000LT | B94: =F94&C94&D94 -> DHJ1000LT | C94: =LEFT(G94,4) -> 1000 | D94: =LEFT(H94,2) -> LT | E94: 6040 | F94: DHJ | G94: 1000 - ENGINE | H94: LT - LEFT | I94: DHJ | L94: 18000H CHANGE LH ENGINE COUPLING | M94: =_xlfn.TEXTAFTER(J94,"-") -> #N/A | N94: =I94&M94&K94 -> #N/A
A95: =F95&C95&D95 -> DHJ1000RI | B95: =F95&C95&D95 -> DHJ1000RI | C95: =LEFT(G95,4) -> 1000 | D95: =LEFT(H95,2) -> RI | E95: 6040 | F95: DHJ | G95: 1000 - ENGINE | H95: RI - RIGHT | I95: DHJ | L95: 18000H CHANGE RH ENGINE COUPLING | M95: =_xlfn.TEXTAFTER(J95,"-") -> #N/A | N95: =I95&M95&K95 -> #N/A
A96: =F96&C96&D96 -> DHJ1353LT | B96: =F96&C96&D96 -> DHJ1353LT | C96: =LEFT(G96,4) -> 1353 | D96: =LEFT(H96,2) -> LT | E96: 6040 | F96: DHJ | G96: 1353 - RADIATOR | H96: LT - LEFT | I96: DHJ | J96: EXBH055-ENG1-COSY | L96: 18000H RADIATOR CHANGE LH | M96: =_xlfn.TEXTAFTER(J96,"-") -> ENG1-COSY | N96: =I96&M96&K96 -> DHJENG1-COSY
A97: =F97&C97&D97 -> DHJ1386FR | B97: =F97&C97&D97 -> DHJ1386FR | C97: =LEFT(G97,4) -> 1386 | D97: =LEFT(H97,2) -> FR | E97: 6040 | F97: DHJ | G97: 1386 - HYDRAULIC FAN MOTOR | H97: FR - FRONT | I97: DHJ | L97: 15000H MOTOR HYD COOLING FR | M97: =_xlfn.TEXTAFTER(J97,"-") -> #N/A | N97: =I97&M97&K97 -> #N/A
A98: =F98&C98&D98 -> DHJ3108LT | B98: =F98&C98&D98 -> DHJ3108LT | C98: =LEFT(G98,4) -> 3108 | D98: =LEFT(H98,2) -> LT | E98: 6040 | F98: DHJ | G98: 3108 - PUMP DRIVE GRP | H98: LT - LEFT | I98: DHJ | L98: 18000H PUMP DRIVE BOX CHANGE LH | M98: =_xlfn.TEXTAFTER(J98,"-") -> #N/A | N98: =I98&M98&K98 -> #N/A
A99: =F99&C99&D99 -> DHJ4050LT | B99: =F99&C99&D99 -> DHJ4050LT | C99: =LEFT(G99,4) -> 4050 | D99: =LEFT(H99,2) -> LT | E99: 6040 | F99: DHJ | G99: 4050 - FINAL DRIVE | H99: LT - LEFT | I99: DHJ | J99: DZTR070-DRIV-FIDV | L99: 18000H FINAL DRIVE CHANGE LH | M99: =_xlfn.TEXTAFTER(J99,"-") -> DRIV-FIDV | N99: =I99&M99&K99 -> DHJDRIV-FIDV
A100: =F100&C100&D100 -> DHJ4050RI | B100: =F100&C100&D100 -> DHJ4050RI | C100: =LEFT(G100,4) -> 4050 | D100: =LEFT(H100,2) -> RI | E100: 6040 | F100: DHJ | G100: 4050 - FINAL DRIVE | H100: RI - RIGHT | I100: DHJ | J100: DZTR070-DRIV-FIDV | L100: 18000H FINAL DRIVE CHANGE RH | M100: =_xlfn.TEXTAFTER(J100,"-") -> DRIV-FIDV | N100: =I100&M100&K100 -> DHJDRIV-FIDV
...

Sheet Macmahon
A1: Crossref Concat | B1: AMT Concat | C1: AMT Mod Code | D1: AMT Comp Code | E1: Serial Prefix | F1: Functional Location Code | G1: Project | H1: Plant | I1: Op Asset ID | J1: Functional Location | K1: Op Manufacturer | L1: Op Model | M1: Op Serial Number | N1: Op Asset Status | O1: Ownership | P1: Maintenance Activity Type | Q1: Plan Status | R1: Maintenance Item | S1: Change Rule | T1: Component Code | U1: Position Code | V1: Maintenance Item Description | W1: Frequency | X1: Maintenance Plan | Y1: Task List Key | Z1: Current Meter Reading (Hours) | AA1: Average Daily Usage | AB1: Total Budget | AC1: Maintenance Plan Text | AD1: Work Order | AE1: Last Done Date | AF1: Last Usage Done | AG1: Life Remaining Hours | AH1: % Life Remaining | AI1: Days Remaining | AJ1: Predicted Change Date | AK1: Next Planned WO Execution Date | AL1: Next WO Predicted Days Variance | AM1: Next WO Predicted Life at Exec Date | AN1: Next WO Predicted Usage % at Exec Date | AO1: MacMahon Lookup Key | AP1: AMT Lookup Key | AQ1: AMT Model | AR1: AMT Component Code | AS1: AMT Modifier Code
A2: =E2&F2&U2 -> ATYHYSY-CYHYRH | B2: =I2&D2&C2 -> QTD185102RI | C2: =_xlfn.XLOOKUP(A2,CrossRef!N:N,CrossRef!D:D,"",0) -> RI | D2: =_xlfn.XLOOKUP(A2,CrossRef!N:N,CrossRef!C:C,"",0) -> 5102 | E2: =LEFT(M2,3) -> ATY | F2: =_xlfn.TEXTAFTER(J2,"-") -> HYSY-CYHY | G2: M350 | H2: M11D | I2: QTD18 | J2: TKHL109-HYSY-CYHY | K2: CATERPILLAR | L2: 793C | M2: ATY00536 | N2: Active | O2: MEC | P2: Z01 | Q2: Active | R2: 96724 | S2: CC | T2: 001044 | U2: RH | V2: 20000H HOIST CYLINDER CHANGE RH | W2: 20000 | X2: 74394 | Y2: A/6620/1 | Z2: 122373 | AA2: 15.21 | AB2: 20259.99 | AD2: 5022747 | AG2: -102373 | AH2: -5.11865 | AI2: -6730.6377 | AJ2: 39494.362 | AK2: 44639 | AL2: -5145 | AM2: 98249.94 | AO2: =E2&F2&U2 -> ATYHYSY-CYHYRH | AP2: =_xlfn.XLOOKUP(AO2,CrossRef!N:N,CrossRef!A:A,"NOT FOUND",0) -> ATY5102RI | AQ2: =IFERROR(_xlfn.XLOOKUP(AO2,CrossRef!$N:$N,CrossRef!$E:$E,"Not Found"),"-") -> 793C | AR2: =IFERROR(_xlfn.XLOOKUP(AO2,CrossRef!$N:$N,CrossRef!$G:$G,"Not Found"),"-") -> 5102 - LIFT/HOIST CYLINDER | AS2: =IFERROR(_xlfn.XLOOKUP(AO2,CrossRef!$N:$N,CrossRef!$H:$H,"Not Found"),"-") -> RI - RIGHT
A3: =E3&F3&U3 -> 6HKDRIV-DIFF | B3: =I3&D3&C3 -> TD6039325800 | C3: =_xlfn.XLOOKUP(A3,CrossRef!N:N,CrossRef!D:D,"",0) -> 00 | D3: =_xlfn.XLOOKUP(A3,CrossRef!N:N,CrossRef!C:C,"",0) -> 3258 | E3: =LEFT(M3,3) -> 6HK | F3: =_xlfn.TEXTAFTER(J3,"-") -> DRIV-DIFF | G3: M215 | H3: M11L | I3: TD6039 | J3: TKHL004-DRIV-DIFF | K3: CATERPILLAR | L3: 785B | M3: 6HK00379 | N3: Suspended | O3: MEO | P3: Z01 | Q3: Active | R3: 3163 | S3: CH | T3: 001003 | V3: 18000H DIFFERENTIAL CHANGE | W3: 18000 | X3: 2601 | Y3: A/18255/1 | Z3: 86728.9 | AA3: 17.5 | AB3: 64396.82 | AG3: -68728.9 | AH3: -3.8182722 | AI3: -3927.3657 | AJ3: 42297.634 | AO3: =E3&F3&U3 -> 6HKDRIV-DIFF | AP3: =_xlfn.XLOOKUP(AO3,CrossRef!N:N,CrossRef!A:A,"NOT FOUND",0) -> 6HK325800 | AQ3: =IFERROR(_xlfn.XLOOKUP(AO3,CrossRef!$N:$N,CrossRef!$E:$E,"Not Found"),"-") -> 785B | AR3: =IFERROR(_xlfn.XLOOKUP(AO3,CrossRef!$N:$N,CrossRef!$G:$G,"Not Found"),"-") -> 3258 - DIFFERENTIAL | AS3: =IFERROR(_xlfn.XLOOKUP(AO3,CrossRef!$N:$N,CrossRef!$H:$H,"Not Found"),"-") -> 00 - (NONE)
A4: =E4&F4&U4 -> 3TZDRIV | B4: =I4&D4&C4 -> QLO06405000 | C4: =_xlfn.XLOOKUP(A4,CrossRef!N:N,CrossRef!D:D,"",0) -> 00 | D4: =_xlfn.XLOOKUP(A4,CrossRef!N:N,CrossRef!C:C,"",0) -> 4050 | E4: =LEFT(M4,3) -> 3TZ | F4: =_xlfn.TEXTAFTER(J4,"-") -> DRIV | G4: M350 | H4: M11D | I4: QLO06 | J4: LOFE045-DRIV | K4: CATERPILLAR | L4: 994D | M4: 3TZ00258 | N4: Active | O4: MEC | P4: Z01 | Q4: Inactive | R4: 100610 | S4: CH | T4: 001042 | V4: 19800H AXLE SHAFT CHANGE | W4: 19800 | X4: 77309 | Y4: A/4706/1 | Z4: 88046 | AA4: 8.01 | AB4: 38963.97 | AD4: 0 | AG4: -68246 | AH4: -3.4467677 | AI4: -8520.0999 | AJ4: 37704.9 | AK4: 46958 | AL4: -9254 | AM4: 93917.33 | AO4: =E4&F4&U4 -> 3TZDRIV | AP4: =_xlfn.XLOOKUP(AO4,CrossRef!N:N,CrossRef!A:A,"NOT FOUND",0) -> 3TZ405000 | AQ4: =IFERROR(_xlfn.XLOOKUP(AO4,CrossRef!$N:$N,CrossRef!$E:$E,"Not Found"),"-") -> 994D | AR4: =IFERROR(_xlfn.XLOOKUP(AO4,CrossRef!$N:$N,CrossRef!$G:$G,"Not Found"),"-") -> 4050 - FINAL DRIVE | AS4: =IFERROR(_xlfn.XLOOKUP(AO4,CrossRef!$N:$N,CrossRef!$H:$H,"Not Found"),"-") -> 00 - (NONE)
A5: =E5&F5&U5 -> HCMBCKT | B5: =I5&D5&C5 -> EX7061 | C5: =_xlfn.XLOOKUP(A5,CrossRef!N:N,CrossRef!D:D,"",0) | D5: =_xlfn.XLOOKUP(A5,CrossRef!N:N,CrossRef!C:C,"",0) | E5: =LEFT(M5,3) -> HCM | F5: =_xlfn.TEXTAFTER(J5,"-") -> BCKT | G5: M350 | H5: M11D | I5: EX7061 | J5: EXBH042-BCKT | K5: HITACHI | L5: EX3600-6 | M5: HCM18M00P00001043 | N5: Suspended | O5: MEO | P5: Z01 | Q5: Inactive | R5: 98707 | S5: CW | T5: 001030 | V5: 10000H BUCKET CHANGE | W5: 10000 | X5: 75839 | Y5: A/6418/1 | Z5: 65494 | AA5: 0 | AB5: 322980 | AG5: -55494 | AH5: -5.5494 | AI5: 0 | AJ5: 46225 | AO5: =E5&F5&U5 -> HCMBCKT | AP5: =_xlfn.XLOOKUP(AO5,CrossRef!N:N,CrossRef!A:A,"NOT FOUND",0) -> NOT FOUND | AQ5: =IFERROR(_xlfn.XLOOKUP(AO5,CrossRef!$N:$N,CrossRef!$E:$E,"Not Found"),"-") -> Not Found | AR5: =IFERROR(_xlfn.XLOOKUP(AO5,CrossRef!$N:$N,CrossRef!$G:$G,"Not Found"),"-") -> Not Found | AS5: =IFERROR(_xlfn.XLOOKUP(AO5,CrossRef!$N:$N,CrossRef!$H:$H,"Not Found"),"-") -> Not Found
A6: =E6&F6&U6 -> 6HKDRIV-TQCV | B6: =I6&D6&C6 -> TD6193310100 | C6: =_xlfn.XLOOKUP(A6,CrossRef!N:N,CrossRef!D:D,"",0) -> 00 | D6: =_xlfn.XLOOKUP(A6,CrossRef!N:N,CrossRef!C:C,"",0) -> 3101 | E6: =LEFT(M6,3) -> 6HK | F6: =_xlfn.TEXTAFTER(J6,"-") -> DRIV-TQCV | G6: M215 | H6: M11L | I6: TD6193 | J6: TKHL014-DRIV-TQCV | K6: CATERPILLAR | L6: 785B | M6: 6HK00734 | N6: Suspended | O6: MEO | P6: Z01 | Q6: Active | R6: 3576 | S6: CH | T6: 001015 | V6: 20000H TORQUE CONVERTER CHANGE | W6: 20000 | X6: 2963 | Y6: A/18257/1 | Z6: 72245.5 | AA6: 17.34 | AB6: 44865.6 | AG6: -52245.5 | AH6: -2.612275 | AI6: -3013.0046 | AJ6: 43211.995 | AO6: =E6&F6&U6 -> 6HKDRIV-TQCV | AP6: =_xlfn.XLOOKUP(AO6,CrossRef!N:N,CrossRef!A:A,"NOT FOUND",0) -> 6HK310100 | AQ6: =IFERROR(_xlfn.XLOOKUP(AO6,CrossRef!$N:$N,CrossRef!$E:$E,"Not Found"),"-") -> 785B | AR6: =IFERROR(_xlfn.XLOOKUP(AO6,CrossRef!$N:$N,CrossRef!$G:$G,"Not Found"),"-") -> 3101 - TORQUE CONVERTER | AS6: =IFERROR(_xlfn.XLOOKUP(AO6,CrossRef!$N:$N,CrossRef!$H:$H,"Not Found"),"-") -> 00 - (NONE)
A7: =E7&F7&U7 -> 6HKDRIV-FIDVRHR | B7: =I7&D7&C7 -> TD61934008RI | C7: =_xlfn.XLOOKUP(A7,CrossRef!N:N,CrossRef!D:D,"",0) -> RI | D7: =_xlfn.XLOOKUP(A7,CrossRef!N:N,CrossRef!C:C,"",0) -> 4008 | E7: =LEFT(M7,3) -> 6HK | F7: =_xlfn.TEXTAFTER(J7,"-") -> DRIV-FIDV | G7: M215 | H7: M11L | I7: TD6193 | J7: TKHL014-DRIV-FIDV | K7: CATERPILLAR | L7: 785B | M7: 6HK00734 | N7: Suspended | O7: MEO | P7: Z01 | Q7: Active | R7: 3581 | S7: CH | T7: 001019 | U7: RHR | V7: 22000H WHEEL END CHANGE RHR | W7: 22000 | X7: 2968 | Y7: A/18812/1 | Z7: 72245.5 | AA7: 17.34 | AB7: 128611.53 | AG7: -50245.5 | AH7: -2.2838864 | AI7: -2897.6644 | AJ7: 43327.336 | AO7: =E7&F7&U7 -> 6HKDRIV-FIDVRHR | AP7: =_xlfn.XLOOKUP(AO7,CrossRef!N:N,CrossRef!A:A,"NOT FOUND",0) -> 6HK4008RI | AQ7: =IFERROR(_xlfn.XLOOKUP(AO7,CrossRef!$N:$N,CrossRef!$E:$E,"Not Found"),"-") -> 785B | AR7: =IFERROR(_xlfn.XLOOKUP(AO7,CrossRef!$N:$N,CrossRef!$G:$G,"Not Found"),"-") -> 4008 - FINAL DRIVE, BRAKE & WHEEL | AS7: =IFERROR(_xlfn.XLOOKUP(AO7,CrossRef!$N:$N,CrossRef!$H:$H,"Not Found"),"-") -> RI - RIGHT
A8: =E8&F8&U8 -> 6HKDRIV-FIDVLHR | B8: =I8&D8&C8 -> TD61934050LR | C8: =_xlfn.XLOOKUP(A8,CrossRef!N:N,CrossRef!D:D,"",0) -> LR | D8: =_xlfn.XLOOKUP(A8,CrossRef!N:N,CrossRef!C:C,"",0) -> 4050 | E8: =LEFT(M8,3) -> 6HK | F8: =_xlfn.TEXTAFTER(J8,"-") -> DRIV-FIDV | G8: M215 | H8: M11L | I8: TD6193 | J8: TKHL014-DRIV-FIDV | K8: CATERPILLAR | L8: 785B | M8: 6HK00734 | N8: Suspended | O8: MEO | P8: Z01 | Q8: Active | R8: 3582 | S8: CH | T8: 001019 | U8: LHR | V8: 22000H WHEEL END CHANGE LHR | W8: 22000 | X8: 2969 | Y8: A/18812/1 | Z8: 72245.5 | AA8: 17.34 | AB8: 128611.53 | AG8: -50245.5 | AH8: -2.2838864 | AI8: -2897.6644 | AJ8: 43327.336 | AO8: =E8&F8&U8 -> 6HKDRIV-FIDVLHR | AP8: =_xlfn.XLOOKUP(AO8,CrossRef!N:N,CrossRef!A:A,"NOT FOUND",0) -> 6HK4050LR | AQ8: =IFERROR(_xlfn.XLOOKUP(AO8,CrossRef!$N:$N,CrossRef!$E:$E,"Not Found"),"-") -> 785B | AR8: =IFERROR(_xlfn.XLOOKUP(AO8,CrossRef!$N:$N,CrossRef!$G:$G,"Not Found"),"-") -> 4050 - FINAL DRIVE | AS8: =IFERROR(_xlfn.XLOOKUP(AO8,CrossRef!$N:$N,CrossRef!$H:$H,"Not Found"),"-") -> LR - LEFT REAR
A9: =E9&F9&U9 -> 6HKDRIV-WHGPLHF | B9: =I9&D9&C9 -> TD61934008LF | C9: =_xlfn.XLOOKUP(A9,CrossRef!N:N,CrossRef!D:D,"",0) -> LF | D9: =_xlfn.XLOOKUP(A9,CrossRef!N:N,CrossRef!C:C,"",0) -> 4008 | E9: =LEFT(M9,3) -> 6HK | F9: =_xlfn.TEXTAFTER(J9,"-") -> DRIV-WHGP | G9: M215 | H9: M11L | I9: TD6193 | J9: TKHL014-DRIV-WHGP | K9: CATERPILLAR | L9: 785B | M9: 6HK00734 | N9: Suspended | O9: MEO | P9: Z01 | Q9: Active | R9: 3580 | S9: CH | T9: 001020 | U9: LHF | V9: 22000H WHEEL GROUP CHANGE LHF | W9: 22000 | X9: 2967 | Y9: A/18259/1 | Z9: 72245.5 | AA9: 17.34 | AB9: 37793.87 | AG9: -50245.5 | AH9: -2.2838864 | AI9: -2897.6644 | AJ9: 43327.336 | AO9: =E9&F9&U9 -> 6HKDRIV-WHGPLHF | AP9: =_xlfn.XLOOKUP(AO9,CrossRef!N:N,CrossRef!A:A,"NOT FOUND",0) -> 6HK4008LF | AQ9: =IFERROR(_xlfn.XLOOKUP(AO9,CrossRef!$N:$N,CrossRef!$E:$E,"Not Found"),"-") -> 785B | AR9: =IFERROR(_xlfn.XLOOKUP(AO9,CrossRef!$N:$N,CrossRef!$G:$G,"Not Found"),"-") -> 4008 - FINAL DRIVE, BRAKE & WHEEL | AS9: =IFERROR(_xlfn.XLOOKUP(AO9,CrossRef!$N:$N,CrossRef!$H:$H,"Not Found"),"-") -> LF - LEFT FRONT
A10: =E10&F10&U10 -> 6HKDRIV-DIFF | B10: =I10&D10&C10 -> TD6100325800 | C10: =_xlfn.XLOOKUP(A10,CrossRef!N:N,CrossRef!D:D,"",0) -> 00 | D10: =_xlfn.XLOOKUP(A10,CrossRef!N:N,CrossRef!C:C,"",0) -> 3258 | E10: =LEFT(M10,3) -> 6HK | F10: =_xlfn.TEXTAFTER(J10,"-") -> DRIV-DIFF | G10: M215 | H10: M11L | I10: TD6100 | J10: TKHL009-DRIV-DIFF | K10: CATERPILLAR | L10: 785B | M10: 6HK00331 | N10: Suspended | O10: MEO | P10: Z01 | Q10: Active | R10: 3363 | S10: CH | T10: 001003 | V10: 18000H DIFFERENTIAL CHANGE | W10: 18000 | X10: 2776 | Y10: A/18255/1 | Z10: 63465.2 | AA10: 9.89 | AB10: 64396.82 | AG10: -45465.2 | AH10: -2.5258444 | AI10: -4597.088 | AJ10: 41627.912 | AO10: =E10&F10&U10 -> 6HKDRIV-DIFF | AP10: =_xlfn.XLOOKUP(AO10,CrossRef!N:N,CrossRef!A:A,"NOT FOUND",0) -> 6HK325800 | AQ10: =IFERROR(_xlfn.XLOOKUP(AO10,CrossRef!$N:$N,CrossRef!$E:$E,"Not Found"),"-") -> 785B | AR10: =IFERROR(_xlfn.XLOOKUP(AO10,CrossRef!$N:$N,CrossRef!$G:$G,"Not Found"),"-") -> 3258 - DIFFERENTIAL | AS10: =IFERROR(_xlfn.XLOOKUP(AO10,CrossRef!$N:$N,CrossRef!$H:$H,"Not Found"),"-") -> 00 - (NONE)
A11: =E11&F11&U11 -> HCMBCKT | B11: =I11&D11&C11 -> EX7219 | C11: =_xlfn.XLOOKUP(A11,CrossRef!N:N,CrossRef!D:D,"",0) | D11: =_xlfn.XLOOKUP(A11,CrossRef!N:N,CrossRef!C:C,"",0) | E11: =LEFT(M11,3) -> HCM | F11: =_xlfn.TEXTAFTER(J11,"-") -> BCKT | G11: M147 | H11: M11J | I11: EX7219 | J11: EXBH088-BCKT | K11: HITACHI | L11: EX1900-6 | M11: HCM18K00E00001074 | N11: Active | O11: MEO | P11: Z01 | Q11: Active | R11: 174647 | S11: CW | T11: 001030 | V11: 10000H BUCKET CHANGE | W11: 10000 | X11: 137852 | Y11: A/24400/1 | Z11: 55009.3 | AA11: 13.06 | AB11: 217480 | AD11: 0 | AG11: -45009.3 | AH11: -4.50093 | AI11: -3446.3476 | AJ11: 42778.652 | AK11: 46377 | AL11: -3599 | AM11: 56994.42 | AO11: =E11&F11&U11 -> HCMBCKT | AP11: =_xlfn.XLOOKUP(AO11,CrossRef!N:N,CrossRef!A:A,"NOT FOUND",0) -> NOT FOUND | AQ11: =IFERROR(_xlfn.XLOOKUP(AO11,CrossRef!$N:$N,CrossRef!$E:$E,"Not Found"),"-") -> Not Found | AR11: =IFERROR(_xlfn.XLOOKUP(AO11,CrossRef!$N:$N,CrossRef!$G:$G,"Not Found"),"-") -> Not Found | AS11: =IFERROR(_xlfn.XLOOKUP(AO11,CrossRef!$N:$N,CrossRef!$H:$H,"Not Found"),"-") -> Not Found
A12: =E12&F12&U12 -> R9HBKSY-SVBKRHR | B12: =I12&D12&C12 -> GD13444006RR | C12: =_xlfn.XLOOKUP(A12,CrossRef!N:N,CrossRef!D:D,"",0) -> RR | D12: =_xlfn.XLOOKUP(A12,CrossRef!N:N,CrossRef!C:C,"",0) -> 4006 | E12: =LEFT(M12,3) -> R9H | F12: =_xlfn.TEXTAFTER(J12,"-") -> BKSY-SVBK | G12: M215 | H12: M11L | I12: GD1344 | J12: GDGN006-BKSY-SVBK | K12: CATERPILLAR | L12: 16M | M12: R9H00573 | N12: Active | O12: MEO | P12: Z01 | Q12: Active | R12: 179287 | S12: CW | T12: 001029 | U12: RHR | V12: 12000H BRAKE GROUP CHANGE RHR | W12: 12000 | X12: 142386 | Y12: A/20812/1 | Z12: 55330.5 | AA12: 12.21 | AB12: 24303.32 | AG12: -43330.5 | AH12: -3.610875 | AI12: -3548.7715 | AJ12: 42676.229 | AO12: =E12&F12&U12 -> R9HBKSY-SVBKRHR | AP12: =_xlfn.XLOOKUP(AO12,CrossRef!N:N,CrossRef!A:A,"NOT FOUND",0) -> R9H4006RR | AQ12: =IFERROR(_xlfn.XLOOKUP(AO12,CrossRef!$N:$N,CrossRef!$E:$E,"Not Found"),"-") -> 16M | AR12: =IFERROR(_xlfn.XLOOKUP(AO12,CrossRef!$N:$N,CrossRef!$G:$G,"Not Found"),"-") -> 4006 - WHEEL & BRAKE ASSEMBLY | AS12: =IFERROR(_xlfn.XLOOKUP(AO12,CrossRef!$N:$N,CrossRef!$H:$H,"Not Found"),"-") -> RR - RIGHT REAR
A13: =E13&F13&U13 -> R9HBKSY-SVBKLHR | B13: =I13&D13&C13 -> GD13444006LR | C13: =_xlfn.XLOOKUP(A13,CrossRef!N:N,CrossRef!D:D,"",0) -> LR | D13: =_xlfn.XLOOKUP(A13,CrossRef!N:N,CrossRef!C:C,"",0) -> 4006 | E13: =LEFT(M13,3) -> R9H | F13: =_xlfn.TEXTAFTER(J13,"-") -> BKSY-SVBK | G13: M215 | H13: M11L | I13: GD1344 | J13: GDGN006-BKSY-SVBK | K13: CATERPILLAR | L13: 16M | M13: R9H00573 | N13: Active | O13: MEO | P13: Z01 | Q13: Active | R13: 179288 | S13: CW | T13: 001029 | U13: LHR | V13: 12000H BRAKE GROUP CHANGE LHR | W13: 12000 | X13: 142387 | Y13: A/20812/1 | Z13: 55330.5 | AA13: 12.21 | AB13: 24303.32 | AG13: -43330.5 | AH13: -3.610875 | AI13: -3548.7715 | AJ13: 42676.229 | AO13: =E13&F13&U13 -> R9HBKSY-SVBKLHR | AP13: =_xlfn.XLOOKUP(AO13,CrossRef!N:N,CrossRef!A:A,"NOT FOUND",0) -> R9H4006LR | AQ13: =IFERROR(_xlfn.XLOOKUP(AO13,CrossRef!$N:$N,CrossRef!$E:$E,"Not Found"),"-") -> 16M | AR13: =IFERROR(_xlfn.XLOOKUP(AO13,CrossRef!$N:$N,CrossRef!$G:$G,"Not Found"),"-") -> 4006 - WHEEL & BRAKE ASSEMBLY | AS13: =IFERROR(_xlfn.XLOOKUP(AO13,CrossRef!$N:$N,CrossRef!$H:$H,"Not Found"),"-") -> LR - LEFT REAR
A14: =E14&F14&U14 -> R9HBKSY-SVBKLHF | B14: =I14&D14&C14 -> GD13444006LF | C14: =_xlfn.XLOOKUP(A14,CrossRef!N:N,CrossRef!D:D,"",0) -> LF | D14: =_xlfn.XLOOKUP(A14,CrossRef!N:N,CrossRef!C:C,"",0) -> 4006 | E14: =LEFT(M14,3) -> R9H | F14: =_xlfn.TEXTAFTER(J14,"-") -> BKSY-SVBK | G14: M215 | H14: M11L | I14: GD1344 | J14: GDGN006-BKSY-SVBK | K14: CATERPILLAR | L14: 16M | M14: R9H00573 | N14: Active | O14: MEO | P14: Z01 | Q14: Active | R14: 179289 | S14: CW | T14: 001029 | U14: LHF | V14: 12000H BRAKE GROUP CHANGE LHF | W14: 12000 | X14: 142388 | Y14: A/20811/1 | Z14: 55330.5 | AA14: 12.21 | AB14: 23153.37 | AG14: -43330.5 | AH14: -3.610875 | AI14: -3548.7715 | AJ14: 42676.229 | AO14: =E14&F14&U14 -> R9HBKSY-SVBKLHF | AP14: =_xlfn.XLOOKUP(AO14,CrossRef!N:N,CrossRef!A:A,"NOT FOUND",0) -> R9H4006LF | AQ14: =IFERROR(_xlfn.XLOOKUP(AO14,CrossRef!$N:$N,CrossRef!$E:$E,"Not Found"),"-") -> 16M | AR14: =IFERROR(_xlfn.XLOOKUP(AO14,CrossRef!$N:$N,CrossRef!$G:$G,"Not Found"),"-") -> 4006 - WHEEL & BRAKE ASSEMBLY | AS14: =IFERROR(_xlfn.XLOOKUP(AO14,CrossRef!$N:$N,CrossRef!$H:$H,"Not Found"),"-") -> LF - LEFT FRONT
A15: =E15&F15&U15 -> R9HBKSY-SVBKRHF | B15: =I15&D15&C15 -> GD13444006RF | C15: =_xlfn.XLOOKUP(A15,CrossRef!N:N,CrossRef!D:D,"",0) -> RF | D15: =_xlfn.XLOOKUP(A15,CrossRef!N:N,CrossRef!C:C,"",0) -> 4006 | E15: =LEFT(M15,3) -> R9H | F15: =_xlfn.TEXTAFTER(J15,"-") -> BKSY-SVBK | G15: M215 | H15: M11L | I15: GD1344 | J15: GDGN006-BKSY-SVBK | K15: CATERPILLAR | L15: 16M | M15: R9H00573 | N15: Active | O15: MEO | P15: Z01 | Q15: Active | R15: 179290 | S15: CW | T15: 001029 | U15: RHF | V15: 12000H BRAKE GROUP CHANGE RHF | W15: 12000 | X15: 142389 | Y15: A/20811/1 | Z15: 55330.5 | AA15: 12.21 | AB15: 23153.37 | AG15: -43330.5 | AH15: -3.610875 | AI15: -3548.7715 | AJ15: 42676.229 | AO15: =E15&F15&U15 -> R9HBKSY-SVBKRHF | AP15: =_xlfn.XLOOKUP(AO15,CrossRef!N:N,CrossRef!A:A,"NOT FOUND",0) -> R9H4006RF | AQ15: =IFERROR(_xlfn.XLOOKUP(AO15,CrossRef!$N:$N,CrossRef!$E:$E,"Not Found"),"-") -> 16M | AR15: =IFERROR(_xlfn.XLOOKUP(AO15,CrossRef!$N:$N,CrossRef!$G:$G,"Not Found"),"-") -> 4006 - WHEEL & BRAKE ASSEMBLY | AS15: =IFERROR(_xlfn.XLOOKUP(AO15,CrossRef!$N:$N,CrossRef!$H:$H,"Not Found"),"-") -> RF - RIGHT FRONT
A16: =E16&F16&U16 -> R9HDRIV-DIFF | B16: =I16&D16&C16 -> GD1344325800 | C16: =_xlfn.XLOOKUP(A16,CrossRef!N:N,CrossRef!D:D,"",0) -> 00 | D16: =_xlfn.XLOOKUP(A16,CrossRef!N:N,CrossRef!C:C,"",0) -> 3258 | E16: =LEFT(M16,3) -> R9H | F16: =_xlfn.TEXTAFTER(J16,"-") -> DRIV-DIFF | G16: M215 | H16: M11L | I16: GD1344 | J16: GDGN006-DRIV-DIFF | K16: CATERPILLAR | L16: 16M | M16: R9H00573 | N16: Active | O16: MEO | P16: Z01 | Q16: Active | R16: 179284 | S16: CH | T16: 001003 | V16: 12000H DIFFERENTIAL CHANGE | W16: 12000 | X16: 142383 | Y16: A/20808/1 | Z16: 55330.5 | AA16: 12.21 | AB16: 50576.32 | AG16: -43330.5 | AH16: -3.610875 | AI16: -3548.7715 | AJ16: 42676.229 | AO16: =E16&F16&U16 -> R9HDRIV-DIFF | AP16: =_xlfn.XLOOKUP(AO16,CrossRef!N:N,CrossRef!A:A,"NOT FOUND",0) -> R9H325800 | AQ16: =IFERROR(_xlfn.XLOOKUP(AO16,CrossRef!$N:$N,CrossRef!$E:$E,"Not Found"),"-") -> 16M | AR16: =IFERROR(_xlfn.XLOOKUP(AO16,CrossRef!$N:$N,CrossRef!$G:$G,"Not Found"),"-") -> 3258 - DIFFERENTIAL | AS16: =IFERROR(_xlfn.XLOOKUP(AO16,CrossRef!$N:$N,CrossRef!$H:$H,"Not Found"),"-") -> 00 - (NONE)
A17: =E17&F17&U17 -> 6HKSURE-SPSNRHF | B17: =I17&D17&C17 -> TD61007201RF | C17: =_xlfn.XLOOKUP(A17,CrossRef!N:N,CrossRef!D:D,"",0) -> RF | D17: =_xlfn.XLOOKUP(A17,CrossRef!N:N,CrossRef!C:C,"",0) -> 7201 | E17: =LEFT(M17,3) -> 6HK | F17: =_xlfn.TEXTAFTER(J17,"-") -> SURE-SPSN | G17: M215 | H17: M11L | I17: TD6100 | J17: TKHL009-SURE-SPSN | K17: CATERPILLAR | L17: 785B | M17: 6HK00331 | N17: Suspended | O17: MEO | P17: Z01 | Q17: Active | R17: 3367 | S17: CC | T17: 001027 | U17: RHF | V17: 22000H SUSPENSION CYLINDER CHANGE RHF | W17: 22000 | X17: 2780 | Y17: A/18258/1 | Z17: 63465.2 | AA17: 9.89 | AB17: 29554.47 | AG17: -41465.2 | AH17: -1.8847818 | AI17: -4192.639 | AJ17: 42032.361 | AO17: =E17&F17&U17 -> 6HKSURE-SPSNRHF | AP17: =_xlfn.XLOOKUP(AO17,CrossRef!N:N,CrossRef!A:A,"NOT FOUND",0) -> 6HK7201RF | AQ17: =IFERROR(_xlfn.XLOOKUP(AO17,CrossRef!$N:$N,CrossRef!$E:$E,"Not Found"),"-") -> 785B | AR17: =IFERROR(_xlfn.XLOOKUP(AO17,CrossRef!$N:$N,CrossRef!$G:$G,"Not Found"),"-") -> 7201 - SUSPENSION CYLINDER | AS17: =IFERROR(_xlfn.XLOOKUP(AO17,CrossRef!$N:$N,CrossRef!$H:$H,"Not Found"),"-") -> RF - RIGHT FRONT
A18: =E18&F18&U18 -> 6HKSURE-SPSNLHF | B18: =I18&D18&C18 -> TD61007201LF | C18: =_xlfn.XLOOKUP(A18,CrossRef!N:N,CrossRef!D:D,"",0) -> LF | D18: =_xlfn.XLOOKUP(A18,CrossRef!N:N,CrossRef!C:C,"",0) -> 7201 | E18: =LEFT(M18,3) -> 6HK | F18: =_xlfn.TEXTAFTER(J18,"-") -> SURE-SPSN | G18: M215 | H18: M11L | I18: TD6100 | J18: TKHL009-SURE-SPSN | K18: CATERPILLAR | L18: 785B | M18: 6HK00331 | N18: Suspended | O18: MEO | P18: Z01 | Q18: Active | R18: 3368 | S18: CC | T18: 001027 | U18: LHF | V18: 22000H SUSPENSION CYLINDER CHANGE LHF | W18: 22000 | X18: 2781 | Y18: A/18258/1 | Z18: 63465.2 | AA18: 9.89 | AB18: 29554.47 | AG18: -41465.2 | AH18: -1.8847818 | AI18: -4192.639 | AJ18: 42032.361 | AO18: =E18&F18&U18 -> 6HKSURE-SPSNLHF | AP18: =_xlfn.XLOOKUP(AO18,CrossRef!N:N,CrossRef!A:A,"NOT FOUND",0) -> 6HK7201LF | AQ18: =IFERROR(_xlfn.XLOOKUP(AO18,CrossRef!$N:$N,CrossRef!$E:$E,"Not Found"),"-") -> 785B | AR18: =IFERROR(_xlfn.XLOOKUP(AO18,CrossRef!$N:$N,CrossRef!$G:$G,"Not Found"),"-") -> 7201 - SUSPENSION CYLINDER | AS18: =IFERROR(_xlfn.XLOOKUP(AO18,CrossRef!$N:$N,CrossRef!$H:$H,"Not Found"),"-") -> LF - LEFT FRONT
A19: =E19&F19&U19 -> DHJHYSY-CYHY-CYKLLH | B19: =I19&D19&C19 -> EX7094 | C19: =_xlfn.XLOOKUP(A19,CrossRef!N:N,CrossRef!D:D,"",0) | D19: =_xlfn.XLOOKUP(A19,CrossRef!N:N,CrossRef!C:C,"",0) | E19: =MID(M19,FIND("DH",M19),3) -> DHJ | F19: =_xlfn.TEXTAFTER(J19,"-") -> HYSY-CYHY-CYKL | G19: M776 | H19: M11E | I19: EX7094 | J19: EXBH055-HYSY-CYHY-CYKL | K19: CATERPILLAR | L19: 6040 | M19: 170120 (DHJ40120) | N19: Active | O19: MEO | P19: Z01 | Q19: Active | R19: 111926 | S19: CC | T19: 001024 | U19: LH | V19: 10000H BUCKET CYLINDER CHANGE LH | W19: 10000 | X19: 86074 | Y19: A/8119/1 | Z19: 70079 | AA19: 2.64 | AB19: 55686.35 | AD19: 4730296 | AE19: 45162 | AF19: 58961.9 | AG19: -1117.1 | AH19: -0.11171 | AI19: -423.14394 | AJ19: 45801.856 | AK19: 45941 | AL19: -140 | AM19: 69329.24 | AN19: 1.036734 | AO19: =E19&F19&U19 -> DHJHYSY-CYHY-CYKLLH | AP19: =_xlfn.XLOOKUP(AO19,CrossRef!N:N,CrossRef!A:A,"NOT FOUND",0) -> NOT FOUND | AQ19: =IFERROR(_xlfn.XLOOKUP(AO19,CrossRef!$N:$N,CrossRef!$E:$E,"Not Found"),"-") -> Not Found | AR19: =IFERROR(_xlfn.XLOOKUP(AO19,CrossRef!$N:$N,CrossRef!$G:$G,"Not Found"),"-") -> Not Found | AS19: =IFERROR(_xlfn.XLOOKUP(AO19,CrossRef!$N:$N,CrossRef!$H:$H,"Not Found"),"-") -> Not Found
A20: =E20&F20&U20 -> DHJHYSY-CYHY-CYKRRH | B20: =I20&D20&C20 -> EX7094 | C20: =_xlfn.XLOOKUP(A20,CrossRef!N:N,CrossRef!D:D,"",0) | D20: =_xlfn.XLOOKUP(A20,CrossRef!N:N,CrossRef!C:C,"",0) | E20: =MID(M20,FIND("DH",M20),3) -> DHJ | F20: =_xlfn.TEXTAFTER(J20,"-") -> HYSY-CYHY-CYKR | G20: M776 | H20: M11E | I20: EX7094 | J20: EXBH055-HYSY-CYHY-CYKR | K20: CATERPILLAR | L20: 6040 | M20: 170120 (DHJ40120) | N20: Active | O20: MEO | P20: Z01 | Q20: Active | R20: 111925 | S20: CC | T20: 001024 | U20: RH | V20: 10000H BUCKET CYLINDER CHANGE RH | W20: 10000 | X20: 86073 | Y20: A/8119/1 | Z20: 70079 | AA20: 2.64 | AB20: 55686.35 | AD20: 4701026 | AE20: 45060 | AF20: 58479 | AG20: -1600 | AH20: -0.16 | AI20: -606.06061 | AJ20: 45618.939 | AK20: 45895 | AL20: -277 | AM20: 69207.8 | AN20: 1.07288 | AO20: =E20&F20&U20 -> DHJHYSY-CYHY-CYKRRH | AP20: =_xlfn.XLOOKUP(AO20,CrossRef!N:N,CrossRef!A:A,"NOT FOUND",0) -> NOT FOUND | AQ20: =IFERROR(_xlfn.XLOOKUP(AO20,CrossRef!$N:$N,CrossRef!$E:$E,"Not Found"),"-") -> Not Found | AR20: =IFERROR(_xlfn.XLOOKUP(AO20,CrossRef!$N:$N,CrossRef!$G:$G,"Not Found"),"-") -> Not Found | AS20: =IFERROR(_xlfn.XLOOKUP(AO20,CrossRef!$N:$N,CrossRef!$H:$H,"Not Found"),"-") -> Not Found
A21: =E21&F21&U21 -> HCMIMAT-BOOM | B21: =I21&D21&C21 -> EX7219 | C21: =_xlfn.XLOOKUP(A21,CrossRef!N:N,CrossRef!D:D,"",0) | D21: =_xlfn.XLOOKUP(A21,CrossRef!N:N,CrossRef!C:C,"",0) | E21: =LEFT(M21,3) -> HCM | F21: =_xlfn.TEXTAFTER(J21,"-") -> IMAT-BOOM | G21: M147 | H21: M11J | I21: EX7219 | J21: EXBH088-IMAT-BOOM | K21: HITACHI | L21: EX1900-6 | M21: HCM18K00E00001074 | N21: Active | O21: MEO | P21: Z01 | Q21: Active | R21: 192689 | S21: CW | T21: 001028 | V21: 18000H BOOM CHANGE | W21: 18000 | X21: 153810 | Y21: A/24411/1 | Z21: 55009.3 | AA21: 13.06 | AB21: 273450 | AD21: 4890449 | AG21: -37009.3 | AH21: -2.0560722 | AI21: -2833.7902 | AJ21: 43391.21 | AK21: 46058 | AL21: -2667 | AM21: 52828.28 | AO21: =E21&F21&U21 -> HCMIMAT-BOOM | AP21: =_xlfn.XLOOKUP(AO21,CrossRef!N:N,CrossRef!A:A,"NOT FOUND",0) -> NOT FOUND | AQ21: =IFERROR(_xlfn.XLOOKUP(AO21,CrossRef!$N:$N,CrossRef!$E:$E,"Not Found"),"-") -> Not Found | AR21: =IFERROR(_xlfn.XLOOKUP(AO21,CrossRef!$N:$N,CrossRef!$G:$G,"Not Found"),"-") -> Not Found | AS21: =IFERROR(_xlfn.XLOOKUP(AO21,CrossRef!$N:$N,CrossRef!$H:$H,"Not Found"),"-") -> Not Found
A22: =E22&F22&U22 -> DHNUCRGRH | B22: =I22&D22&C22 -> EX71084170RI | C22: =_xlfn.XLOOKUP(A22,CrossRef!N:N,CrossRef!D:D,"",0) -> RI | D22: =_xlfn.XLOOKUP(A22,CrossRef!N:N,CrossRef!C:C,"",0) -> 4170 | E22: =MID(M22,FIND("DH",M22),3) -> DHN | F22: =_xlfn.TEXTAFTER(J22,"-") -> UCRG | G22: M776 | H22: M11E | I22: EX7108 | J22: EXBH056-UCRG | K22: CATERPILLAR | L22: 6060 BH | M22: DHN60189 | N22: Active | O22: MEO | P22: Z01 | Q22: Active | R22: 112452 | S22: CW | T22: 001035 | U22: RH | V22: 16000H TRACKS CHANGE RH | W22: 16000 | X22: 86486 | Y22: A/8570/1 | Z22: 51971.6 | AA22: 13.9 | AB22: 453166.75 | AD22: 4675478 | AE22: 46213 | AF22: 0 | AG22: -35971.6 | AH22: -2.248225 | AI22: -2587.8849 | AJ22: 43637.115 | AK22: 46787 | AL22: -3150 | AM22: 59783.4 | AN22: 3.7364625 | AO22: =E22&F22&U22 -> DHNUCRGRH | AP22: =_xlfn.XLOOKUP(AO22,CrossRef!N:N,CrossRef!A:A,"NOT FOUND",0) -> DHN4170RI | AQ22: =IFERROR(_xlfn.XLOOKUP(AO22,CrossRef!$N:$N,CrossRef!$E:$E,"Not Found"),"-") -> 6060 BH | AR22: =IFERROR(_xlfn.XLOOKUP(AO22,CrossRef!$N:$N,CrossRef!$G:$G,"Not Found"),"-") -> 4170 - TRACK ASSEMBLY | AS22: =IFERROR(_xlfn.XLOOKUP(AO22,CrossRef!$N:$N,CrossRef!$H:$H,"Not Found"),"-") -> RI - RIGHT
A23: =E23&F23&U23 -> DHNUCRGLH | B23: =I23&D23&C23 -> EX71084170LT | C23: =_xlfn.XLOOKUP(A23,CrossRef!N:N,CrossRef!D:D,"",0) -> LT | D23: =_xlfn.XLOOKUP(A23,CrossRef!N:N,CrossRef!C:C,"",0) -> 4170 | E23: =MID(M23,FIND("DH",M23),3) -> DHN | F23: =_xlfn.TEXTAFTER(J23,"-") -> UCRG | G23: M776 | H23: M11E | I23: EX7108 | J23: EXBH056-UCRG | K23: CATERPILLAR | L23: 6060 BH | M23: DHN60189 | N23: Active | O23: MEO | P23: Z01 | Q23: Active | R23: 112453 | S23: CW | T23: 001035 | U23: LH | V23: 16000H TRACKS CHANGE LH | W23: 16000 | X23: 86487 | Y23: A/8570/1 | Z23: 51971.6 | AA23: 13.9 | AB23: 453166.75 | AD23: 4675479 | AE23: 46213 | AF23: 0 | AG23: -35971.6 | AH23: -2.248225 | AI23: -2587.8849 | AJ23: 43637.115 | AK23: 46787 | AL23: -3150 | AM23: 59783.4 | AN23: 3.7364625 | AO23: =E23&F23&U23 -> DHNUCRGLH | AP23: =_xlfn.XLOOKUP(AO23,CrossRef!N:N,CrossRef!A:A,"NOT FOUND",0) -> DHN4170LT | AQ23: =IFERROR(_xlfn.XLOOKUP(AO23,CrossRef!$N:$N,CrossRef!$E:$E,"Not Found"),"-") -> 6060 BH | AR23: =IFERROR(_xlfn.XLOOKUP(AO23,CrossRef!$N:$N,CrossRef!$G:$G,"Not Found"),"-") -> 4170 - TRACK ASSEMBLY | AS23: =IFERROR(_xlfn.XLOOKUP(AO23,CrossRef!$N:$N,CrossRef!$H:$H,"Not Found"),"-") -> LT - LEFT
A24: =E24&F24&U24 -> DHJUCRG-TCID-TCILLH | B24: =I24&D24&C24 -> EX7094 | C24: =_xlfn.XLOOKUP(A24,CrossRef!N:N,CrossRef!D:D,"",0) | D24: =_xlfn.XLOOKUP(A24,CrossRef!N:N,CrossRef!C:C,"",0) | E24: =MID(M24,FIND("DH",M24),3) -> DHJ | F24: =_xlfn.TEXTAFTER(J24,"-") -> UCRG-TCID-TCIL | G24: M776 | H24: M11E | I24: EX7094 | J24: EXBH055-UCRG-TCID-TCIL | K24: CATERPILLAR | L24: 6040 | M24: 170120 (DHJ40120) | N24: Active | O24: MEO | P24: Z01 | Q24: Active | R24: 111983 | S24: CW | T24: 001033 | U24: LH | V24: 10000H IDLER CHANGE LH | W24: 10000 | X24: 92236 | Y24: A/7563/1 | Z24: 70079 | AA24: 2.64 | AB24: 81162.92 | AD24: 4199826 | AE24: 45532 | AF24: 63795.1 | AG24: 3716.1 | AH24: 0.37161 | AI24: 1407.6136 | AJ24: 47632.614 | AK24: 47228 | AL24: 404 | AM24: 72726.92 | AN24: 0.893182 | AO24: =E24&F24&U24 -> DHJUCRG-TCID-TCILLH | AP24: =_xlfn.XLOOKUP(AO24,CrossRef!N:N,CrossRef!A:A,"NOT FOUND",0) -> NOT FOUND | AQ24: =IFERROR(_xlfn.XLOOKUP(AO24,CrossRef!$N:$N,CrossRef!$E:$E,"Not Found"),"-") -> Not Found | AR24: =IFERROR(_xlfn.XLOOKUP(AO24,CrossRef!$N:$N,CrossRef!$G:$G,"Not Found"),"-") -> Not Found | AS24: =IFERROR(_xlfn.XLOOKUP(AO24,CrossRef!$N:$N,CrossRef!$H:$H,"Not Found"),"-") -> Not Found
A25: =E25&F25&U25 -> DHNSURE-SWBR-SWBR | B25: =I25&D25&C25 -> QEX010706300 | C25: =_xlfn.XLOOKUP(A25,CrossRef!N:N,CrossRef!D:D,"",0) -> 00 | D25: =_xlfn.XLOOKUP(A25,CrossRef!N:N,CrossRef!C:C,"",0) -> 7063 | E25: =MID(M25,FIND("DH",M25),3) -> DHN | F25: =_xlfn.TEXTAFTER(J25,"-") -> SURE-SWBR-SWBR | G25: M350 | H25: M11D | I25: QEX010 | J25: EXBH047-SURE-SWBR-SWBR | K25: CATERPILLAR | L25: 6060 | M25: 340137 DHN60137 | N25: Suspended | O25: MEC | P25: Z01 | Q25: Inactive | R25: 97133 | S25: CW | T25: 001038 | V25: 33000H SWING BEARING CHANGE | W25: 33000 | X25: 74743 | Y25: A/5300/1 | Z25: 67445 | AA25: 9.04 | AB25: 963605.7 | AD25: 0 | AG25: -34445 | AH25: -1.0437879 | AI25: -3810.2876 | AJ25: 42414.712 | AK25: 47229 | AL25: -4815 | AM25: 76521.16 | AO25: =E25&F25&U25 -> DHNSURE-SWBR-SWBR | AP25: =_xlfn.XLOOKUP(AO25,CrossRef!N:N,CrossRef!A:A,"NOT FOUND",0) -> DHN706300 | AQ25: =IFERROR(_xlfn.XLOOKUP(AO25,CrossRef!$N:$N,CrossRef!$E:$E,"Not Found"),"-") -> 6060 | AR25: =IFERROR(_xlfn.XLOOKUP(AO25,CrossRef!$N:$N,CrossRef!$G:$G,"Not Found"),"-") -> 7063 - SWING GEAR/BEARING | AS25: =IFERROR(_xlfn.XLOOKUP(AO25,CrossRef!$N:$N,CrossRef!$H:$H,"Not Found"),"-") -> 00 - (NONE)
A26: =E26&F26&U26 -> R9HSUREFR | B26: =I26&D26&C26 -> GD13443258FR | C26: =_xlfn.XLOOKUP(A26,CrossRef!N:N,CrossRef!D:D,"",0) -> FR | D26: =_xlfn.XLOOKUP(A26,CrossRef!N:N,CrossRef!C:C,"",0) -> 3258 | E26: =LEFT(M26,3) -> R9H | F26: =_xlfn.TEXTAFTER(J26,"-") -> SURE | G26: M215 | H26: M11L | I26: GD1344 | J26: GDGN006-SURE | K26: CATERPILLAR | L26: 16M | M26: R9H00573 | N26: Active | O26: MEO | P26: Z01 | Q26: Active | R26: 200352 | S26: CC | U26: FR | V26: 24000H FRONT AXLE ASSEMBLY CHANGE | W26: 24000 | X26: 160364 | Y26: A/26574/1 | Z26: 55330.5 | AA26: 12.21 | AB26: 85694.93 | AG26: -31330.5 | AH26: -1.3054375 | AI26: -2565.9705 | AJ26: 43659.029 | AO26: =E26&F26&U26 -> R9HSUREFR | AP26: =_xlfn.XLOOKUP(AO26,CrossRef!N:N,CrossRef!A:A,"NOT FOUND",0) -> R9H3258FR | AQ26: =IFERROR(_xlfn.XLOOKUP(AO26,CrossRef!$N:$N,CrossRef!$E:$E,"Not Found"),"-") -> 16M | AR26: =IFERROR(_xlfn.XLOOKUP(AO26,CrossRef!$N:$N,CrossRef!$G:$G,"Not Found"),"-") -> 3258 - DIFFERENTIAL | AS26: =IFERROR(_xlfn.XLOOKUP(AO26,CrossRef!$N:$N,CrossRef!$H:$H,"Not Found"),"-") -> FR - FRONT
A27: =E27&F27&U27 -> HCMSURE-SWBR-SWBR | B27: =I27&D27&C27 -> EX7061 | C27: =_xlfn.XLOOKUP(A27,CrossRef!N:N,CrossRef!D:D,"",0) | D27: =_xlfn.XLOOKUP(A27,CrossRef!N:N,CrossRef!C:C,"",0) | E27: =LEFT(M27,3) -> HCM | F27: =_xlfn.TEXTAFTER(J27,"-") -> SURE-SWBR-SWBR | G27: M350 | H27: M11D | I27: EX7061 | J27: EXBH042-SURE-SWBR-SWBR | K27: HITACHI | L27: EX3600-6 | M27: HCM18M00P00001043 | N27: Suspended | O27: MEO | P27: Z01 | Q27: Inactive | R27: 97145 | S27: CW | T27: 001038 | V27: 35000H SWING BEARING CHANGE | W27: 35000 | X27: 74752 | Y27: A/6333/1 | Z27: 65494 | AA27: 0 | AB27: 599266.39 | AG27: -30494 | AH27: -0.87125714 | AI27: 0 | AJ27: 46225 | AO27: =E27&F27&U27 -> HCMSURE-SWBR-SWBR | AP27: =_xlfn.XLOOKUP(AO27,CrossRef!N:N,CrossRef!A:A,"NOT FOUND",0) -> NOT FOUND | AQ27: =IFERROR(_xlfn.XLOOKUP(AO27,CrossRef!$N:$N,CrossRef!$E:$E,"Not Found"),"-") -> Not Found | AR27: =IFERROR(_xlfn.XLOOKUP(AO27,CrossRef!$N:$N,CrossRef!$G:$G,"Not Found"),"-") -> Not Found | AS27: =IFERROR(_xlfn.XLOOKUP(AO27,CrossRef!$N:$N,CrossRef!$H:$H,"Not Found"),"-") -> Not Found
A28: =E28&F28&U28 -> HCMUCRG-TCFS-TCFLLH | B28: =I28&D28&C28 -> EX70614028LT | C28: =_xlfn.XLOOKUP(A28,CrossRef!N:N,CrossRef!D:D,"",0) -> LT | D28: =_xlfn.XLOOKUP(A28,CrossRef!N:N,CrossRef!C:C,"",0) -> 4028 | E28: =LEFT(M28,3) -> HCM | F28: =_xlfn.TEXTAFTER(J28,"-") -> UCRG-TCFS-TCFL | G28: M350 | H28: M11D | I28: EX7061 | J28: EXBH042-UCRG-TCFS-TCFL | K28: HITACHI | L28: EX3600-6 | M28: HCM18M00P00001043 | N28: Suspended | O28: MEO | P28: Z01 | Q28: Inactive | R28: 97144 | S28: CW | T28: 001036 | U28: LH | V28: 35000H TRACK FRAME CHANGE LH | W28: 35000 | X28: 74751 | Y28: A/4536/1 | Z28: 65494 | AA28: 0 | AB28: 350560 | AG28: -30494 | AH28: -0.87125714 | AI28: 0 | AJ28: 46225 | AO28: =E28&F28&U28 -> HCMUCRG-TCFS-TCFLLH | AP28: =_xlfn.XLOOKUP(AO28,CrossRef!N:N,CrossRef!A:A,"NOT FOUND",0) -> HCM4028LT | AQ28: =IFERROR(_xlfn.XLOOKUP(AO28,CrossRef!$N:$N,CrossRef!$E:$E,"Not Found"),"-") -> EX2500 | AR28: =IFERROR(_xlfn.XLOOKUP(AO28,CrossRef!$N:$N,CrossRef!$G:$G,"Not Found"),"-") -> 4028 - TRACK FRAME | AS28: =IFERROR(_xlfn.XLOOKUP(AO28,CrossRef!$N:$N,CrossRef!$H:$H,"Not Found"),"-") -> LT - LEFT
A29: =E29&F29&U29 -> HCMUCRG-TCFS-TCFRRH | B29: =I29&D29&C29 -> EX70614028RI | C29: =_xlfn.XLOOKUP(A29,CrossRef!N:N,CrossRef!D:D,"",0) -> RI | D29: =_xlfn.XLOOKUP(A29,CrossRef!N:N,CrossRef!C:C,"",0) -> 4028 | E29: =LEFT(M29,3) -> HCM | F29: =_xlfn.TEXTAFTER(J29,"-") -> UCRG-TCFS-TCFR | G29: M350 | H29: M11D | I29: EX7061 | J29: EXBH042-UCRG-TCFS-TCFR | K29: HITACHI | L29: EX3600-6 | M29: HCM18M00P00001043 | N29: Suspended | O29: MEO | P29: Z01 | Q29: Inactive | R29: 97143 | S29: CW | T29: 001036 | U29: RH | V29: 35000H TRACK FRAME CHANGE RH | W29: 35000 | X29: 74750 | Y29: A/4536/1 | Z29: 65494 | AA29: 0 | AB29: 350560 | AG29: -30494 | AH29: -0.87125714 | AI29: 0 | AJ29: 46225 | AO29: =E29&F29&U29 -> HCMUCRG-TCFS-TCFRRH | AP29: =_xlfn.XLOOKUP(AO29,CrossRef!N:N,CrossRef!A:A,"NOT FOUND",0) -> HCM4028RI | AQ29: =IFERROR(_xlfn.XLOOKUP(AO29,CrossRef!$N:$N,CrossRef!$E:$E,"Not Found"),"-") -> EX2500 | AR29: =IFERROR(_xlfn.XLOOKUP(AO29,CrossRef!$N:$N,CrossRef!$G:$G,"Not Found"),"-") -> 4028 - TRACK FRAME | AS29: =IFERROR(_xlfn.XLOOKUP(AO29,CrossRef!$N:$N,CrossRef!$H:$H,"Not Found"),"-") -> RI - RIGHT
A30: =E30&F30&U30 -> HCMHYSY-VAHYLHL | B30: =I30&D30&C30 -> EX7096 | C30: =_xlfn.XLOOKUP(A30,CrossRef!N:N,CrossRef!D:D,"",0) | D30: =_xlfn.XLOOKUP(A30,CrossRef!N:N,CrossRef!C:C,"",0) | E30: =LEFT(M30,3) -> HCM | F30: =_xlfn.TEXTAFTER(J30,"-") -> HYSY-VAHY | G30: M350 | H30: M11D | I30: EX7096 | J30: EXBH045-HYSY-VAHY | K30: HITACHI | L30: EX3600-6 | M30: HCM18M00H00001232 | N30: Active | O30: MEO | P30: Z01 | Q30: Inactive | R30: 194583 | S30: CW | T30: 001002 | U30: LHL | V30: 24000H MAIN CONTROL VALVE CHANGE LHL | W30: 24000 | X30: 155227 | Y30: A/25116/1 | Z30: 49793 | AA30: 6.54 | AB30: 72100.67 | AD30: 4658781 | AF30: 0 | AG30: -25793 | AH30: -1.0747083 | AI30: -3943.8838 | AJ30: 42281.116 | AK30: 45636 | AL30: -3355 | AM30: 45940.94 | AN30: 1.9142058 | AO30: =E30&F30&U30 -> HCMHYSY-VAHYLHL | AP30: =_xlfn.XLOOKUP(AO30,CrossRef!N:N,CrossRef!A:A,"NOT FOUND",0) -> NOT FOUND | AQ30: =IFERROR(_xlfn.XLOOKUP(AO30,CrossRef!$N:$N,CrossRef!$E:$E,"Not Found"),"-") -> Not Found | AR30: =IFERROR(_xlfn.XLOOKUP(AO30,CrossRef!$N:$N,CrossRef!$G:$G,"Not Found"),"-") -> Not Found | AS30: =IFERROR(_xlfn.XLOOKUP(AO30,CrossRef!$N:$N,CrossRef!$H:$H,"Not Found"),"-") -> Not Found
A31: =E31&F31&U31 -> HCMHYSY-VAHYLHU | B31: =I31&D31&C31 -> EX7096 | C31: =_xlfn.XLOOKUP(A31,CrossRef!N:N,CrossRef!D:D,"",0) | D31: =_xlfn.XLOOKUP(A31,CrossRef!N:N,CrossRef!C:C,"",0) | E31: =LEFT(M31,3) -> HCM | F31: =_xlfn.TEXTAFTER(J31,"-") -> HYSY-VAHY | G31: M350 | H31: M11D | I31: EX7096 | J31: EXBH045-HYSY-VAHY | K31: HITACHI | L31: EX3600-6 | M31: HCM18M00H00001232 | N31: Active | O31: MEO | P31: Z01 | Q31: Inactive | R31: 194584 | S31: CW | T31: 001002 | U31: LHU | V31: 24000H MAIN CONTROL VALVE CHANGE LHU | W31: 24000 | X31: 155228 | Y31: A/25117/1 | Z31: 49793 | AA31: 6.54 | AB31: 72100.67 | AD31: 4658782 | AF31: 0 | AG31: -25793 | AH31: -1.0747083 | AI31: -3943.8838 | AJ31: 42281.116 | AK31: 45636 | AL31: -3355 | AM31: 45940.94 | AN31: 1.9142058 | AO31: =E31&F31&U31 -> HCMHYSY-VAHYLHU | AP31: =_xlfn.XLOOKUP(AO31,CrossRef!N:N,CrossRef!A:A,"NOT FOUND",0) -> NOT FOUND | AQ31: =IFERROR(_xlfn.XLOOKUP(AO31,CrossRef!$N:$N,CrossRef!$E:$E,"Not Found"),"-") -> Not Found | AR31: =IFERROR(_xlfn.XLOOKUP(AO31,CrossRef!$N:$N,CrossRef!$G:$G,"Not Found"),"-") -> Not Found | AS31: =IFERROR(_xlfn.XLOOKUP(AO31,CrossRef!$N:$N,CrossRef!$H:$H,"Not Found"),"-") -> Not Found
A32: =E32&F32&U32 -> HCMHYSY-VAHYRHL | B32: =I32&D32&C32 -> EX7096 | C32: =_xlfn.XLOOKUP(A32,CrossRef!N:N,CrossRef!D:D,"",0) | D32: =_xlfn.XLOOKUP(A32,CrossRef!N:N,CrossRef!C:C,"",0) | E32: =LEFT(M32,3) -> HCM | F32: =_xlfn.TEXTAFTER(J32,"-") -> HYSY-VAHY | G32: M350 | H32: M11D | I32: EX7096 | J32: EXBH045-HYSY-VAHY | K32: HITACHI | L32: EX3600-6 | M32: HCM18M00H00001232 | N32: Active | O32: MEO | P32: Z01 | Q32: Inactive | R32: 194585 | S32: CW | T32: 001002 | U32: RHL | V32: 24000H MAIN CONTROL VALVE CHANGE RHL | W32: 24000 | X32: 155229 | Y32: A/25118/1 | Z32: 49793 | AA32: 6.54 | AB32: 72100.67 | AD32: 4658754 | AF32: 0 | AG32: -25793 | AH32: -1.0747083 | AI32: -3943.8838 | AJ32: 42281.116 | AK32: 45636 | AL32: -3355 | AM32: 45940.94 | AN32: 1.9142058 | AO32: =E32&F32&U32 -> HCMHYSY-VAHYRHL | AP32: =_xlfn.XLOOKUP(AO32,CrossRef!N:N,CrossRef!A:A,"NOT FOUND",0) -> NOT FOUND | AQ32: =IFERROR(_xlfn.XLOOKUP(AO32,CrossRef!$N:$N,CrossRef!$E:$E,"Not Found"),"-") -> Not Found | AR32: =IFERROR(_xlfn.XLOOKUP(AO32,CrossRef!$N:$N,CrossRef!$G:$G,"Not Found"),"-") -> Not Found | AS32: =IFERROR(_xlfn.XLOOKUP(AO32,CrossRef!$N:$N,CrossRef!$H:$H,"Not Found"),"-") -> Not Found
A33: =E33&F33&U33 -> HCMHYSY-VAHYRHU | B33: =I33&D33&C33 -> EX7096 | C33: =_xlfn.XLOOKUP(A33,CrossRef!N:N,CrossRef!D:D,"",0) | D33: =_xlfn.XLOOKUP(A33,CrossRef!N:N,CrossRef!C:C,"",0) | E33: =LEFT(M33,3) -> HCM | F33: =_xlfn.TEXTAFTER(J33,"-") -> HYSY-VAHY | G33: M350 | H33: M11D | I33: EX7096 | J33: EXBH045-HYSY-VAHY | K33: HITACHI | L33: EX3600-6 | M33: HCM18M00H00001232 | N33: Active | O33: MEO | P33: Z01 | Q33: Inactive | R33: 194586 | S33: CW | T33: 001002 | U33: RHU | V33: 24000H MAIN CONTROL VALVE CHANGE RHU | W33: 24000 | X33: 155230 | Y33: A/25119/1 | Z33: 49793 | AA33: 6.54 | AB33: 72100.67 | AD33: 4658783 | AF33: 0 | AG33: -25793 | AH33: -1.0747083 | AI33: -3943.8838 | AJ33: 42281.116 | AK33: 45636 | AL33: -3355 | AM33: 45940.94 | AN33: 1.9142058 | AO33: =E33&F33&U33 -> HCMHYSY-VAHYRHU | AP33: =_xlfn.XLOOKUP(AO33,CrossRef!N:N,CrossRef!A:A,"NOT FOUND",0) -> NOT FOUND | AQ33: =IFERROR(_xlfn.XLOOKUP(AO33,CrossRef!$N:$N,CrossRef!$E:$E,"Not Found"),"-") -> Not Found | AR33: =IFERROR(_xlfn.XLOOKUP(AO33,CrossRef!$N:$N,CrossRef!$G:$G,"Not Found"),"-") -> Not Found | AS33: =IFERROR(_xlfn.XLOOKUP(AO33,CrossRef!$N:$N,CrossRef!$H:$H,"Not Found"),"-") -> Not Found
A34: =E34&F34&U34 -> ATYHYSY-CYHYLH | B34: =I34&D34&C34 -> QTD165102LT | C34: =_xlfn.XLOOKUP(A34,CrossRef!N:N,CrossRef!D:D,"",0) -> LT | D34: =_xlfn.XLOOKUP(A34,CrossRef!N:N,CrossRef!C:C,"",0) -> 5102 | E34: =LEFT(M34,3) -> ATY | F34: =_xlfn.TEXTAFTER(J34,"-") -> HYSY-CYHY | G34: M350 | H34: M11D | I34: QTD16 | J34: TKHL108-HYSY-CYHY | K34: CATERPILLAR | L34: 793C | M34: ATY00535 | N34: Active | O34: MEC | P34: Z01 | Q34: Active | R34: 96721 | S34: CC | T34: 001044 | U34: LH | V34: 20000H HOIST CYLINDER CHANGE LH | W34: 20000 | X34: 78063 | Y34: A/6618/1 | Z34: 121666 | AA34: 14.29 | AB34: 20259.99 | AD34: 4386857 | AE34: 43054 | AF34: 76322 | AG34: -25344 | AH34: -1.2672 | AI34: -1773.5479 | AJ34: 44451.452 | AK34: 45136 | AL34: -685 | AM34: 106104.19 | AN34: 1.4891095 | AO34: =E34&F34&U34 -> ATYHYSY-CYHYLH | AP34: =_xlfn.XLOOKUP(AO34,CrossRef!N:N,CrossRef!A:A,"NOT FOUND",0) -> ATY5102LT | AQ34: =IFERROR(_xlfn.XLOOKUP(AO34,CrossRef!$N:$N,CrossRef!$E:$E,"Not Found"),"-") -> 793C | AR34: =IFERROR(_xlfn.XLOOKUP(AO34,CrossRef!$N:$N,CrossRef!$G:$G,"Not Found"),"-") -> 5102 - LIFT/HOIST CYLINDER | AS34: =IFERROR(_xlfn.XLOOKUP(AO34,CrossRef!$N:$N,CrossRef!$H:$H,"Not Found"),"-") -> LT - LEFT
A35: =E35&F35&U35 -> #N/A | B35: =I35&D35&C35 -> #N/A | C35: =_xlfn.XLOOKUP(A35,CrossRef!N:N,CrossRef!D:D,"",0) -> #N/A | D35: =_xlfn.XLOOKUP(A35,CrossRef!N:N,CrossRef!C:C,"",0) -> #N/A | E35: =LEFT(M35,3) -> HCM | F35: =_xlfn.TEXTAFTER(J35,"-") -> #N/A | G35: M147 | H35: M11J | I35: EX7219 | J35: EXBH088 | K35: HITACHI | L35: EX1900-6 | M35: HCM18K00E00001074 | N35: Active | O35: MEO | P35: Z01 | Q35: Active | R35: 192684 | S35: CW | T35: 001036 | U35: RH | V35: 30000H TRACK FRAME CHANGE RH | W35: 30000 | X35: 153805 | Y35: A/24398/1 | Z35: 55009.3 | AA35: 13.06 | AB35: 276710 | AG35: -25009.3 | AH35: -0.83364333 | AI35: -1914.9541 | AJ35: 44310.046 | AO35: =E35&F35&U35 -> #N/A | AP35: =_xlfn.XLOOKUP(AO35,CrossRef!N:N,CrossRef!A:A,"NOT FOUND",0) -> #N/A | AQ35: =IFERROR(_xlfn.XLOOKUP(AO35,CrossRef!$N:$N,CrossRef!$E:$E,"Not Found"),"-") -> - | AR35: =IFERROR(_xlfn.XLOOKUP(AO35,CrossRef!$N:$N,CrossRef!$G:$G,"Not Found"),"-") -> - | AS35: =IFERROR(_xlfn.XLOOKUP(AO35,CrossRef!$N:$N,CrossRef!$H:$H,"Not Found"),"-") -> -
A36: =E36&F36&U36 -> HCMUCRG-TCFS-TCFLLH | B36: =I36&D36&C36 -> EX72194028LT | C36: =_xlfn.XLOOKUP(A36,CrossRef!N:N,CrossRef!D:D,"",0) -> LT | D36: =_xlfn.XLOOKUP(A36,CrossRef!N:N,CrossRef!C:C,"",0) -> 4028 | E36: =LEFT(M36,3) -> HCM | F36: =_xlfn.TEXTAFTER(J36,"-") -> UCRG-TCFS-TCFL | G36: M147 | H36: M11J | I36: EX7219 | J36: EXBH088-UCRG-TCFS-TCFL | K36: HITACHI | L36: EX1900-6 | M36: HCM18K00E00001074 | N36: Active | O36: MEO | P36: Z01 | Q36: Active | R36: 192683 | S36: CW | T36: 001036 | U36: LH | V36: 30000H TRACK FRAME CHANGE LH | W36: 30000 | X36: 153804 | Y36: A/24398/1 | Z36: 55009.3 | AA36: 13.06 | AB36: 276710 | AG36: -25009.3 | AH36: -0.83364333 | AI36: -1914.9541 | AJ36: 44310.046 | AO36: =E36&F36&U36 -> HCMUCRG-TCFS-TCFLLH | AP36: =_xlfn.XLOOKUP(AO36,CrossRef!N:N,CrossRef!A:A,"NOT FOUND",0) -> HCM4028LT | AQ36: =IFERROR(_xlfn.XLOOKUP(AO36,CrossRef!$N:$N,CrossRef!$E:$E,"Not Found"),"-") -> EX2500 | AR36: =IFERROR(_xlfn.XLOOKUP(AO36,CrossRef!$N:$N,CrossRef!$G:$G,"Not Found"),"-") -> 4028 - TRACK FRAME | AS36: =IFERROR(_xlfn.XLOOKUP(AO36,CrossRef!$N:$N,CrossRef!$H:$H,"Not Found"),"-") -> LT - LEFT
A37: =E37&F37&U37 -> SSPSURE-SPSNRHR | B37: =I37&D37&C37 -> TD63417213RR | C37: =_xlfn.XLOOKUP(A37,CrossRef!N:N,CrossRef!D:D,"",0) -> RR | D37: =_xlfn.XLOOKUP(A37,CrossRef!N:N,CrossRef!C:C,"",0) -> 7213 | E37: =LEFT(M37,3) -> SSP | F37: =_xlfn.TEXTAFTER(J37,"-") -> SURE-SPSN | G37: M776 | H37: M11E | I37: TD6341 | J37: TKHL166-SURE-SPSN | K37: CATERPILLAR | L37: 793F | M37: SSP00993 | N37: Active | O37: MEF | P37: Z01 | Q37: Active | R37: 111352 | S37: CC | T37: 001027 | U37: RHR | V37: 25000H SUSPENSION CYLINDER CHANGE RHR | W37: 25000 | X37: 85599 | Y37: A/7235/1 | Z37: 49448.06 | AA37: 14.81 | AB37: 36270.04 | AD37: 4361457 | AG37: -24448.06 | AH37: -0.9779224 | AI37: -1650.7806 | AJ37: 44574.219 | AK37: 46274 | AL37: -1700 | AM37: 50173.75 | AO37: =E37&F37&U37 -> SSPSURE-SPSNRHR | AP37: =_xlfn.XLOOKUP(AO37,CrossRef!N:N,CrossRef!A:A,"NOT FOUND",0) -> SSP7213RR | AQ37: =IFERROR(_xlfn.XLOOKUP(AO37,CrossRef!$N:$N,CrossRef!$E:$E,"Not Found"),"-") -> 793F | AR37: =IFERROR(_xlfn.XLOOKUP(AO37,CrossRef!$N:$N,CrossRef!$G:$G,"Not Found"),"-") -> 7213 - REAR SUSPENSION CYLINDER | AS37: =IFERROR(_xlfn.XLOOKUP(AO37,CrossRef!$N:$N,CrossRef!$H:$H,"Not Found"),"-") -> RR - RIGHT REAR
A38: =E38&F38&U38 -> DHNUCRG-TCFS-TCFLLH | B38: =I38&D38&C38 -> QEX0104028LT | C38: =_xlfn.XLOOKUP(A38,CrossRef!N:N,CrossRef!D:D,"",0) -> LT | D38: =_xlfn.XLOOKUP(A38,CrossRef!N:N,CrossRef!C:C,"",0) -> 4028 | E38: =MID(M38,FIND("DH",M38),3) -> DHN | F38: =_xlfn.TEXTAFTER(J38,"-") -> UCRG-TCFS-TCFL | G38: M350 | H38: M11D | I38: QEX010 | J38: EXBH047-UCRG-TCFS-TCFL | K38: CATERPILLAR | L38: 6060 | M38: 340137 DHN60137 | N38: Suspended | O38: MEC | P38: Z01 | Q38: Inactive | R38: 96849 | S38: CW | T38: 001036 | U38: LH | V38: 22000H TRACK ROLLER FRAME CHANGE LH | W38: 22000 | X38: 78088 | Y38: A/5374/1 | Z38: 67445 | AA38: 9.04 | AB38: 469206.37 | AD38: 4398751 | AE38: 43014 | AF38: 22167 | AG38: -23278 | AH38: -1.0580909 | AI38: -2575 | AJ38: 43650 | AK38: 48029 | AL38: -4379 | AM38: 83753.16 | AN38: 2.7993709 | AO38: =E38&F38&U38 -> DHNUCRG-TCFS-TCFLLH | AP38: =_xlfn.XLOOKUP(AO38,CrossRef!N:N,CrossRef!A:A,"NOT FOUND",0) -> DHN4028LT | AQ38: =IFERROR(_xlfn.XLOOKUP(AO38,CrossRef!$N:$N,CrossRef!$E:$E,"Not Found"),"-") -> 6060 BH | AR38: =IFERROR(_xlfn.XLOOKUP(AO38,CrossRef!$N:$N,CrossRef!$G:$G,"Not Found"),"-") -> 4028 - TRACK FRAME | AS38: =IFERROR(_xlfn.XLOOKUP(AO38,CrossRef!$N:$N,CrossRef!$H:$H,"Not Found"),"-") -> LT - LEFT
A39: =E39&F39&U39 -> DHNUCRG-TCFS-TCFRRH | B39: =I39&D39&C39 -> QEX0104028RI | C39: =_xlfn.XLOOKUP(A39,CrossRef!N:N,CrossRef!D:D,"",0) -> RI | D39: =_xlfn.XLOOKUP(A39,CrossRef!N:N,CrossRef!C:C,"",0) -> 4028 | E39: =MID(M39,FIND("DH",M39),3) -> DHN | F39: =_xlfn.TEXTAFTER(J39,"-") -> UCRG-TCFS-TCFR | G39: M350 | H39: M11D | I39: QEX010 | J39: EXBH047-UCRG-TCFS-TCFR | K39: CATERPILLAR | L39: 6060 | M39: 340137 DHN60137 | N39: Suspended | O39: MEC | P39: Z01 | Q39: Inactive | R39: 96848 | S39: CW | T39: 001036 | U39: RH | V39: 22000H TRACK ROLLER FRAME CHANGE RH | W39: 22000 | X39: 74481 | Y39: A/5378/1 | Z39: 67445 | AA39: 9.04 | AB39: 469206.37 | AD39: 4396375 | AE39: 43014 | AF39: 22167 | AG39: -23278 | AH39: -1.0580909 | AI39: -2575 | AJ39: 43650 | AK39: 48029 | AL39: -4379 | AM39: 83753.16 | AN39: 2.7993709 | AO39: =E39&F39&U39 -> DHNUCRG-TCFS-TCFRRH | AP39: =_xlfn.XLOOKUP(AO39,CrossRef!N:N,CrossRef!A:A,"NOT FOUND",0) -> DHN4028RI | AQ39: =IFERROR(_xlfn.XLOOKUP(AO39,CrossRef!$N:$N,CrossRef!$E:$E,"Not Found"),"-") -> 6060 BH | AR39: =IFERROR(_xlfn.XLOOKUP(AO39,CrossRef!$N:$N,CrossRef!$G:$G,"Not Found"),"-") -> 4028 - TRACK FRAME | AS39: =IFERROR(_xlfn.XLOOKUP(AO39,CrossRef!$N:$N,CrossRef!$H:$H,"Not Found"),"-") -> RI - RIGHT
A40: =E40&F40&U40 -> JRPDRIV-TMSN | B40: =I40&D40&C40 -> TD2418303000 | C40: =_xlfn.XLOOKUP(A40,CrossRef!N:N,CrossRef!D:D,"",0) -> 00 | D40: =_xlfn.XLOOKUP(A40,CrossRef!N:N,CrossRef!C:C,"",0) -> 3030 | E40: =LEFT(M40,3) -> JRP | F40: =_xlfn.TEXTAFTER(J40,"-") -> DRIV-TMSN | G40: M800 | H40: M11Q | I40: TD2418 | J40: TKHL192-DRIV-TMSN | K40: CATERPILLAR | L40: 777F | M40: JRP00891 | N40: Active | O40: MEF | P40: Z01 | Q40: Inactive | R40: 181970 | S40: CH | T40: 001016 | V40: 16000H TRANSMISSION CHANGE | W40: 16000 | X40: 145074 | Y40: A/23957/1 | Z40: 37823 | AA40: 7.74 | AB40: 94475.98 | AD40: 4709381 | AE40: 45959 | AF40: 0 | AG40: -21823 | AH40: -1.3639375 | AI40: -2819.509 | AJ40: 43405.491 | AK40: 47144 | AL40: -3739 | AM40: 44936.06 | AN40: 2.8085037 | AO40: =E40&F40&U40 -> JRPDRIV-TMSN | AP40: =_xlfn.XLOOKUP(AO40,CrossRef!N:N,CrossRef!A:A,"NOT FOUND",0) -> JRP303000 | AQ40: =IFERROR(_xlfn.XLOOKUP(AO40,CrossRef!$N:$N,CrossRef!$E:$E,"Not Found"),"-") -> 777F | AR40: =IFERROR(_xlfn.XLOOKUP(AO40,CrossRef!$N:$N,CrossRef!$G:$G,"Not Found"),"-") -> 3030 - TRANSMISSION | AS40: =IFERROR(_xlfn.XLOOKUP(AO40,CrossRef!$N:$N,CrossRef!$H:$H,"Not Found"),"-") -> 00 - (NONE)
A41: =E41&F41&U41 -> SSPSURE-SPSNLHF | B41: =I41&D41&C41 -> TD63267201LF | C41: =_xlfn.XLOOKUP(A41,CrossRef!N:N,CrossRef!D:D,"",0) -> LF | D41: =_xlfn.XLOOKUP(A41,CrossRef!N:N,CrossRef!C:C,"",0) -> 7201 | E41: =LEFT(M41,3) -> SSP | F41: =_xlfn.TEXTAFTER(J41,"-") -> SURE-SPSN | G41: M776 | H41: M11E | I41: TD6326 | J41: TKHL162-SURE-SPSN | K41: CATERPILLAR | L41: 793F | M41: SSP01217 | N41: Active | O41: MEF | P41: Z01 | Q41: Active | R41: 111296 | S41: CC | T41: 001027 | U41: LHF | V41: 24000H SUSPENSION CYLINDER CHANGE LHF | W41: 24000 | X41: 85543 | Y41: A/7793/1 | Z41: 45679 | AA41: 12.06 | AB41: 68000.45 | AD41: 4944282 | AE41: 46200 | AF41: 0 | AG41: -21679 | AH41: -0.90329167 | AI41: -1797.5954 | AJ41: 44427.405 | AK41: 47880 | AL41: -3453 | AM41: 65638.3 | AN41: 2.7349292 | AO41: =E41&F41&U41 -> SSPSURE-SPSNLHF | AP41: =_xlfn.XLOOKUP(AO41,CrossRef!N:N,CrossRef!A:A,"NOT FOUND",0) -> SSP7201LF | AQ41: =IFERROR(_xlfn.XLOOKUP(AO41,CrossRef!$N:$N,CrossRef!$E:$E,"Not Found"),"-") -> 793F | AR41: =IFERROR(_xlfn.XLOOKUP(AO41,CrossRef!$N:$N,CrossRef!$G:$G,"Not Found"),"-") -> 7201 - SUSPENSION CYLINDER | AS41: =IFERROR(_xlfn.XLOOKUP(AO41,CrossRef!$N:$N,CrossRef!$H:$H,"Not Found"),"-") -> LF - LEFT FRONT
A42: =E42&F42&U42 -> SSPSURE-SPSNRHR | B42: =I42&D42&C42 -> TD63477213RR | C42: =_xlfn.XLOOKUP(A42,CrossRef!N:N,CrossRef!D:D,"",0) -> RR | D42: =_xlfn.XLOOKUP(A42,CrossRef!N:N,CrossRef!C:C,"",0) -> 7213 | E42: =LEFT(M42,3) -> SSP | F42: =_xlfn.TEXTAFTER(J42,"-") -> SURE-SPSN | G42: M776 | H42: M11E | I42: TD6347 | J42: TKHL172-SURE-SPSN | K42: CATERPILLAR | L42: 793F | M42: SSP01048 | N42: Active | O42: MEF | P42: Z01 | Q42: Active | R42: 111356 | S42: CC | T42: 001027 | U42: RHR | V42: 25000H SUSPENSION CYLINDER CHANGE RHR | W42: 25000 | X42: 85603 | Y42: A/7235/1 | Z42: 46546 | AA42: 12.55 | AB42: 36270.04 | AD42: 4452549 | AE42: 43315 | AF42: 0 | AG42: -21546 | AH42: -0.86184 | AI42: -1716.8127 | AJ42: 44508.187 | AK42: 45260 | AL42: -752 | AM42: 34435.25 | AN42: 1.37741 | AO42: =E42&F42&U42 -> SSPSURE-SPSNRHR | AP42: =_xlfn.XLOOKUP(AO42,CrossRef!N:N,CrossRef!A:A,"NOT FOUND",0) -> SSP7213RR | AQ42: =IFERROR(_xlfn.XLOOKUP(AO42,CrossRef!$N:$N,CrossRef!$E:$E,"Not Found"),"-") -> 793F | AR42: =IFERROR(_xlfn.XLOOKUP(AO42,CrossRef!$N:$N,CrossRef!$G:$G,"Not Found"),"-") -> 7213 - REAR SUSPENSION CYLINDER | AS42: =IFERROR(_xlfn.XLOOKUP(AO42,CrossRef!$N:$N,CrossRef!$H:$H,"Not Found"),"-") -> RR - RIGHT REAR
A43: =E43&F43&U43 -> SSPSURE-SPSNLHR | B43: =I43&D43&C43 -> TD63477201LR | C43: =_xlfn.XLOOKUP(A43,CrossRef!N:N,CrossRef!D:D,"",0) -> LR | D43: =_xlfn.XLOOKUP(A43,CrossRef!N:N,CrossRef!C:C,"",0) -> 7201 | E43: =LEFT(M43,3) -> SSP | F43: =_xlfn.TEXTAFTER(J43,"-") -> SURE-SPSN | G43: M776 | H43: M11E | I43: TD6347 | J43: TKHL172-SURE-SPSN | K43: CATERPILLAR | L43: 793F | M43: SSP01048 | N43: Active | O43: MEF | P43: Z01 | Q43: Active | R43: 111357 | S43: CC | T43: 001027 | U43: LHR | V43: 25000H SUSPENSION CYLINDER CHANGE LHR | W43: 25000 | X43: 85604 | Y43: A/7235/1 | Z43: 46546 | AA43: 12.55 | AB43: 36270.04 | AD43: 4452564 | AE43: 43315 | AF43: 0 | AG43: -21546 | AH43: -0.86184 | AI43: -1716.8127 | AJ43: 44508.187 | AK43: 45260 | AL43: -752 | AM43: 34435.25 | AN43: 1.37741 | AO43: =E43&F43&U43 -> SSPSURE-SPSNLHR | AP43: =_xlfn.XLOOKUP(AO43,CrossRef!N:N,CrossRef!A:A,"NOT FOUND",0) -> SSP7201LR | AQ43: =IFERROR(_xlfn.XLOOKUP(AO43,CrossRef!$N:$N,CrossRef!$E:$E,"Not Found"),"-") -> 793F | AR43: =IFERROR(_xlfn.XLOOKUP(AO43,CrossRef!$N:$N,CrossRef!$G:$G,"Not Found"),"-") -> 7201 - SUSPENSION CYLINDER | AS43: =IFERROR(_xlfn.XLOOKUP(AO43,CrossRef!$N:$N,CrossRef!$H:$H,"Not Found"),"-") -> LR - LEFT REAR
A44: =E44&F44&U44 -> HCMSURE | B44: =I44&D44&C44 -> EX7115 | C44: =_xlfn.XLOOKUP(A44,CrossRef!N:N,CrossRef!D:D,"",0) | D44: =_xlfn.XLOOKUP(A44,CrossRef!N:N,CrossRef!C:C,"",0) | E44: =LEFT(M44,3) -> HCM | F44: =_xlfn.TEXTAFTER(J44,"-") -> SURE | G44: M776 | H44: M11E | I44: EX7115 | J44: EXBH057-SURE | K44: HITACHI | L44: EX5600-6 BH | M44: HCMKCA90J00002085 | N44: Active | O44: MEF | P44: Z01 | Q44: Active | R44: 112604 | S44: CW | T44: 001037 | V44: 20000H STICK CHANGE | W44: 20000 | X44: 86620 | Y44: A/7792/1 | Z44: 41257 | AA44: 14.67 | AB44: 417100 | AD44: 4130300 | AE44: 43466 | AF44: 0 | AG44: -21257 | AH44: -1.06285 | AI44: -1449.0116 | AJ44: 44775.988 | AK44: 44771 | AL44: 4 | AM44: 19926.82 | AN44: 0.996341 | AO44: =E44&F44&U44 -> HCMSURE | AP44: =_xlfn.XLOOKUP(AO44,CrossRef!N:N,CrossRef!A:A,"NOT FOUND",0) -> NOT FOUND | AQ44: =IFERROR(_xlfn.XLOOKUP(AO44,CrossRef!$N:$N,CrossRef!$E:$E,"Not Found"),"-") -> Not Found | AR44: =IFERROR(_xlfn.XLOOKUP(AO44,CrossRef!$N:$N,CrossRef!$G:$G,"Not Found"),"-") -> Not Found | AS44: =IFERROR(_xlfn.XLOOKUP(AO44,CrossRef!$N:$N,CrossRef!$H:$H,"Not Found"),"-") -> Not Found
A45: =E45&F45&U45 -> DHNUCRG-TCFS-TCFLLH | B45: =I45&D45&C45 -> QEX0114028LT | C45: =_xlfn.XLOOKUP(A45,CrossRef!N:N,CrossRef!D:D,"",0) -> LT | D45: =_xlfn.XLOOKUP(A45,CrossRef!N:N,CrossRef!C:C,"",0) -> 4028 | E45: =MID(M45,FIND("DH",M45),3) -> DHN | F45: =_xlfn.TEXTAFTER(J45,"-") -> UCRG-TCFS-TCFL | G45: M350 | H45: M11D | I45: QEX011 | J45: EXBH009-UCRG-TCFS-TCFL | K45: CATERPILLAR | L45: 6060 | M45: 340141 DHN60141 | N45: Active | O45: MEC | P45: Z01 | Q45: Active | R45: 96861 | S45: CW | T45: 001036 | U45: LH | V45: 22000H TRACK ROLLER FRAME CHANGE LH | W45: 22000 | X45: 78114 | Y45: A/5374/1 | Z45: 69943.2 | AA45: 13.19 | AB45: 469206.37 | AD45: 4692745 | AE45: 43357 | AF45: 26828 | AG45: -21115.2 | AH45: -0.95978182 | AI45: -1600.8491 | AJ45: 44624.151 | AK45: 45881 | AL45: -1257 | AM45: 65405.84 | AN45: 1.7535382 | AO45: =E45&F45&U45 -> DHNUCRG-TCFS-TCFLLH | AP45: =_xlfn.XLOOKUP(AO45,CrossRef!N:N,CrossRef!A:A,"NOT FOUND",0) -> DHN4028LT | AQ45: =IFERROR(_xlfn.XLOOKUP(AO45,CrossRef!$N:$N,CrossRef!$E:$E,"Not Found"),"-") -> 6060 BH | AR45: =IFERROR(_xlfn.XLOOKUP(AO45,CrossRef!$N:$N,CrossRef!$G:$G,"Not Found"),"-") -> 4028 - TRACK FRAME | AS45: =IFERROR(_xlfn.XLOOKUP(AO45,CrossRef!$N:$N,CrossRef!$H:$H,"Not Found"),"-") -> LT - LEFT
A46: =E46&F46&U46 -> DHNUCRG-TCFS-TCFRRH | B46: =I46&D46&C46 -> QEX0114028RI | C46: =_xlfn.XLOOKUP(A46,CrossRef!N:N,CrossRef!D:D,"",0) -> RI | D46: =_xlfn.XLOOKUP(A46,CrossRef!N:N,CrossRef!C:C,"",0) -> 4028 | E46: =MID(M46,FIND("DH",M46),3) -> DHN | F46: =_xlfn.TEXTAFTER(J46,"-") -> UCRG-TCFS-TCFR | G46: M350 | H46: M11D | I46: QEX011 | J46: EXBH009-UCRG-TCFS-TCFR | K46: CATERPILLAR | L46: 6060 | M46: 340141 DHN60141 | N46: Active | O46: MEC | P46: Z01 | Q46: Active | R46: 96860 | S46: CW | T46: 001036 | U46: RH | V46: 22000H TRACK ROLLER FRAME CHANGE RH | W46: 22000 | X46: 74488 | Y46: A/5378/1 | Z46: 69943.2 | AA46: 13.19 | AB46: 469206.37 | AD46: 4692708 | AE46: 43357 | AF46: 26828 | AG46: -21115.2 | AH46: -0.95978182 | AI46: -1600.8491 | AJ46: 44624.151 | AK46: 45881 | AL46: -1257 | AM46: 65405.84 | AN46: 1.7535382 | AO46: =E46&F46&U46 -> DHNUCRG-TCFS-TCFRRH | AP46: =_xlfn.XLOOKUP(AO46,CrossRef!N:N,CrossRef!A:A,"NOT FOUND",0) -> DHN4028RI | AQ46: =IFERROR(_xlfn.XLOOKUP(AO46,CrossRef!$N:$N,CrossRef!$E:$E,"Not Found"),"-") -> 6060 BH | AR46: =IFERROR(_xlfn.XLOOKUP(AO46,CrossRef!$N:$N,CrossRef!$G:$G,"Not Found"),"-") -> 4028 - TRACK FRAME | AS46: =IFERROR(_xlfn.XLOOKUP(AO46,CrossRef!$N:$N,CrossRef!$H:$H,"Not Found"),"-") -> RI - RIGHT
A47: =E47&F47&U47 -> JRPDRIV-DIFF | B47: =I47&D47&C47 -> TD2419325800 | C47: =_xlfn.XLOOKUP(A47,CrossRef!N:N,CrossRef!D:D,"",0) -> 00 | D47: =_xlfn.XLOOKUP(A47,CrossRef!N:N,CrossRef!C:C,"",0) -> 3258 | E47: =LEFT(M47,3) -> JRP | F47: =_xlfn.TEXTAFTER(J47,"-") -> DRIV-DIFF | G47: M800 | H47: M11Q | I47: TD2419 | J47: TKHL193-DRIV-DIFF | K47: CATERPILLAR | L47: 777F | M47: JRP00803 | N47: Active | O47: MEF | P47: Z01 | Q47: Inactive | R47: 181973 | S47: CH | T47: 001003 | V47: 18000H DIFFERENTIAL CHANGE | W47: 18000 | X47: 145077 | Y47: A/23954/1 | Z47: 38972 | AA47: 2.95 | AB47: 59611.07 | AD47: 4770085 | AE47: 46127 | AF47: 0 | AG47: -20972 | AH47: -1.1651111 | AI47: -7109.1525 | AJ47: 39115.847 | AK47: 47411 | AL47: -8296 | AM47: 42470.7 | AN47: 2.3594833 | AO47: =E47&F47&U47 -> JRPDRIV-DIFF | AP47: =_xlfn.XLOOKUP(AO47,CrossRef!N:N,CrossRef!A:A,"NOT FOUND",0) -> JRP325800 | AQ47: =IFERROR(_xlfn.XLOOKUP(AO47,CrossRef!$N:$N,CrossRef!$E:$E,"Not Found"),"-") -> 777F | AR47: =IFERROR(_xlfn.XLOOKUP(AO47,CrossRef!$N:$N,CrossRef!$G:$G,"Not Found"),"-") -> 3258 - DIFFERENTIAL | AS47: =IFERROR(_xlfn.XLOOKUP(AO47,CrossRef!$N:$N,CrossRef!$H:$H,"Not Found"),"-") -> 00 - (NONE)
A48: =E48&F48&U48 -> HCMIMAT-SICK | B48: =I48&D48&C48 -> EX7112 | C48: =_xlfn.XLOOKUP(A48,CrossRef!N:N,CrossRef!D:D,"",0) | D48: =_xlfn.XLOOKUP(A48,CrossRef!N:N,CrossRef!C:C,"",0) | E48: =LEFT(M48,3) -> HCM | F48: =_xlfn.TEXTAFTER(J48,"-") -> IMAT-SICK | G48: M215 | H48: M11L | I48: EX7112 | J48: EXBH001-IMAT-SICK | K48: HITACHI | L48: EX2600-6 | M48: HCMKBA90C00002088 | N48: Active | O48: MEF | P48: Z01 | Q48: Active | R48: 2533 | S48: CW | T48: 001037 | V48: 18000H STICK CHANGE | W48: 18000 | X48: 2093 | Y48: A/18368/1 | Z48: 36668.8 | AA48: 13.49 | AB48: 206100 | AD48: 4835340 | AE48: 43354 | AF48: 0 | AG48: -18668.8 | AH48: -1.0371556 | AI48: -1383.8992 | AJ48: 44841.101 | AK48: 46130 | AL48: -1289 | AM48: 35387.25 | AN48: 1.9659583 | AO48: =E48&F48&U48 -> HCMIMAT-SICK | AP48: =_xlfn.XLOOKUP(AO48,CrossRef!N:N,CrossRef!A:A,"NOT FOUND",0) -> NOT FOUND | AQ48: =IFERROR(_xlfn.XLOOKUP(AO48,CrossRef!$N:$N,CrossRef!$E:$E,"Not Found"),"-") -> Not Found | AR48: =IFERROR(_xlfn.XLOOKUP(AO48,CrossRef!$N:$N,CrossRef!$G:$G,"Not Found"),"-") -> Not Found | AS48: =IFERROR(_xlfn.XLOOKUP(AO48,CrossRef!$N:$N,CrossRef!$H:$H,"Not Found"),"-") -> Not Found
A49: =E49&F49&U49 -> B9HSUREFR | B49: =I49&D49&C49 -> GD14013258FR | C49: =_xlfn.XLOOKUP(A49,CrossRef!N:N,CrossRef!D:D,"",0) -> FR | D49: =_xlfn.XLOOKUP(A49,CrossRef!N:N,CrossRef!C:C,"",0) -> 3258 | E49: =LEFT(M49,3) -> B9H | F49: =_xlfn.TEXTAFTER(J49,"-") -> SURE | G49: M350 | H49: M11D | I49: GD1401 | J49: GDGN028-SURE | K49: CATERPILLAR | L49: 16M | M49: B9H00497 | N49: Active | O49: MEO | P49: Z01 | Q49: Active | R49: 200373 | S49: CC | U49: FR | V49: 24000H FRONT AXLE ASSEMBLY CHANGE | W49: 24000 | X49: 160374 | Y49: A/26575/1 | Z49: 42125 | AA49: 5.06 | AB49: 85694.93 | AD49: 4768831 | AF49: 0 | AG49: -18125 | AH49: -0.75520833 | AI49: -3582.0158 | AJ49: 42642.984 | AK49: 45831 | AL49: -3189 | AM49: 40131.36 | AN49: 1.67214 | AO49: =E49&F49&U49 -> B9HSUREFR | AP49: =_xlfn.XLOOKUP(AO49,CrossRef!N:N,CrossRef!A:A,"NOT FOUND",0) -> B9H3258FR | AQ49: =IFERROR(_xlfn.XLOOKUP(AO49,CrossRef!$N:$N,CrossRef!$E:$E,"Not Found"),"-") -> 16M | AR49: =IFERROR(_xlfn.XLOOKUP(AO49,CrossRef!$N:$N,CrossRef!$G:$G,"Not Found"),"-") -> 3258 - DIFFERENTIAL | AS49: =IFERROR(_xlfn.XLOOKUP(AO49,CrossRef!$N:$N,CrossRef!$H:$H,"Not Found"),"-") -> FR - FRONT
A50: =E50&F50&U50 -> FDBHYSY-CYHYLH | B50: =I50&D50&C50 -> QTD385102LT | C50: =_xlfn.XLOOKUP(A50,CrossRef!N:N,CrossRef!D:D,"",0) -> LT | D50: =_xlfn.XLOOKUP(A50,CrossRef!N:N,CrossRef!C:C,"",0) -> 5102 | E50: =LEFT(M50,3) -> FDB | F50: =_xlfn.TEXTAFTER(J50,"-") -> HYSY-CYHY | G50: M350 | H50: M11D | I50: QTD38 | J50: TKHL123-HYSY-CYHY | K50: CATERPILLAR | L50: 793D | M50: FDB00839 | N50: Active | O50: MEC | P50: Z01 | Q50: Active | R50: 96782 | S50: CC | T50: 001044 | U50: LH | V50: 20000H HOIST CYLINDER CHANGE LH | W50: 20000 | X50: 78150 | Y50: A/6619/1 | Z50: 74754 | AA50: 12.95 | AB50: 20259.99 | AD50: 4386611 | AE50: 43083 | AF50: 38744 | AG50: -16010 | AH50: -0.8005 | AI50: -1236.2934 | AJ50: 44988.707 | AK50: 45135 | AL50: -147 | AM50: 60638.5 | AN50: 1.094725 | AO50: =E50&F50&U50 -> FDBHYSY-CYHYLH | AP50: =_xlfn.XLOOKUP(AO50,CrossRef!N:N,CrossRef!A:A,"NOT FOUND",0) -> FDB5102LT | AQ50: =IFERROR(_xlfn.XLOOKUP(AO50,CrossRef!$N:$N,CrossRef!$E:$E,"Not Found"),"-") -> 793D | AR50: =IFERROR(_xlfn.XLOOKUP(AO50,CrossRef!$N:$N,CrossRef!$G:$G,"Not Found"),"-") -> 5102 - LIFT/HOIST CYLINDER | AS50: =IFERROR(_xlfn.XLOOKUP(AO50,CrossRef!$N:$N,CrossRef!$H:$H,"Not Found"),"-") -> LT - LEFT
A51: =E51&F51&U51 -> FDBDRIV-DIFF | B51: =I51&D51&C51 -> QTD20325800 | C51: =_xlfn.XLOOKUP(A51,CrossRef!N:N,CrossRef!D:D,"",0) -> 00 | D51: =_xlfn.XLOOKUP(A51,CrossRef!N:N,CrossRef!C:C,"",0) -> 3258 | E51: =LEFT(M51,3) -> FDB | F51: =_xlfn.TEXTAFTER(J51,"-") -> DRIV-DIFF | G51: M350 | H51: M11D | I51: QTD20 | J51: TKHL111-DRIV-DIFF | K51: CATERPILLAR | L51: 793D | M51: FDB00170 | N51: Active | O51: MEC | P51: Z01 | Q51: Active | R51: 100203 | S51: CH | T51: 001003 | V51: 16500H DIFFERENTIAL CHANGE | W51: 16500 | X51: 76978 | Y51: A/5635/1 | Z51: 98993 | AA51: 12.97 | AB51: 63540.55 | AD51: 4940558 | AE51: 43679 | AF51: 67037 | AG51: -15456 | AH51: -0.93672727 | AI51: -1191.6731 | AJ51: 45033.327 | AK51: 46328 | AL51: -1295 | AM51: 100328.91 | AO51: =E51&F51&U51 -> FDBDRIV-DIFF | AP51: =_xlfn.XLOOKUP(AO51,CrossRef!N:N,CrossRef!A:A,"NOT FOUND",0) -> FDB325800 | AQ51: =IFERROR(_xlfn.XLOOKUP(AO51,CrossRef!$N:$N,CrossRef!$E:$E,"Not Found"),"-") -> 793D | AR51: =IFERROR(_xlfn.XLOOKUP(AO51,CrossRef!$N:$N,CrossRef!$G:$G,"Not Found"),"-") -> 3258 - DIFFERENTIAL | AS51: =IFERROR(_xlfn.XLOOKUP(AO51,CrossRef!$N:$N,CrossRef!$H:$H,"Not Found"),"-") -> 00 - (NONE)
A52: =E52&F52&U52 -> APXSURE-SPSNLHR | B52: =I52&D52&C52 -> TD66617213LR | C52: =_xlfn.XLOOKUP(A52,CrossRef!N:N,CrossRef!D:D,"",0) -> LR | D52: =_xlfn.XLOOKUP(A52,CrossRef!N:N,CrossRef!C:C,"",0) -> 7213 | E52: =LEFT(M52,3) -> APX | F52: =_xlfn.TEXTAFTER(J52,"-") -> SURE-SPSN | G52: M776 | H52: M11E | I52: TD6661 | J52: TKHL186-SURE-SPSN | K52: CATERPILLAR | L52: 785C | M52: APX00878 | N52: Active | O52: MEH | P52: Z01 | Q52: Active | R52: 193935 | S52: CC | T52: 001027 | U52: LHR | V52: 25000H SUSPENSION CYLINDER CHANGE LHR | W52: 25000 | X52: 154771 | Y52: A/24915/1 | Z52: 60494 | AA52: 10.92 | AB52: 19377.97 | AD52: 4639857 | AF52: 20649 | AG52: -14845 | AH52: -0.5938 | AI52: -1359.4322 | AJ52: 44865.568 | AK52: 45602 | AL52: -737 | AM52: 53690.84 | AN52: 1.3216736 | AO52: =E52&F52&U52 -> APXSURE-SPSNLHR | AP52: =_xlfn.XLOOKUP(AO52,CrossRef!N:N,CrossRef!A:A,"NOT FOUND",0) -> APX7213LR | AQ52: =IFERROR(_xlfn.XLOOKUP(AO52,CrossRef!$N:$N,CrossRef!$E:$E,"Not Found"),"-") -> 785C | AR52: =IFERROR(_xlfn.XLOOKUP(AO52,CrossRef!$N:$N,CrossRef!$G:$G,"Not Found"),"-") -> 7213 - REAR SUSPENSION CYLINDER | AS52: =IFERROR(_xlfn.XLOOKUP(AO52,CrossRef!$N:$N,CrossRef!$H:$H,"Not Found"),"-") -> LR - LEFT REAR
A53: =E53&F53&U53 -> HCMUCRG-TCFS-TCFLLH | B53: =I53&D53&C53 -> EX70964028LT | C53: =_xlfn.XLOOKUP(A53,CrossRef!N:N,CrossRef!D:D,"",0) -> LT | D53: =_xlfn.XLOOKUP(A53,CrossRef!N:N,CrossRef!C:C,"",0) -> 4028 | E53: =LEFT(M53,3) -> HCM | F53: =_xlfn.TEXTAFTER(J53,"-") -> UCRG-TCFS-TCFL | G53: M350 | H53: M11D | I53: EX7096 | J53: EXBH045-UCRG-TCFS-TCFL | K53: HITACHI | L53: EX3600-6 | M53: HCM18M00H00001232 | N53: Active | O53: MEO | P53: Z01 | Q53: Inactive | R53: 97151 | S53: CW | T53: 001036 | U53: LH | V53: 35000H TRACK FRAME CHANGE LH | W53: 35000 | X53: 74758 | Y53: A/4536/1 | Z53: 49793 | AA53: 6.54 | AB53: 350560 | AD53: 0 | AE53: 41495 | AF53: 0 | AG53: -14793 | AH53: -0.42265714 | AI53: -2261.9266 | AJ53: 43963.073 | AK53: 47185 | AL53: -3222 | AM53: 56071.4 | AN53: 1.60204 | AO53: =E53&F53&U53 -> HCMUCRG-TCFS-TCFLLH | AP53: =_xlfn.XLOOKUP(AO53,CrossRef!N:N,CrossRef!A:A,"NOT FOUND",0) -> HCM4028LT | AQ53: =IFERROR(_xlfn.XLOOKUP(AO53,CrossRef!$N:$N,CrossRef!$E:$E,"Not Found"),"-") -> EX2500 | AR53: =IFERROR(_xlfn.XLOOKUP(AO53,CrossRef!$N:$N,CrossRef!$G:$G,"Not Found"),"-") -> 4028 - TRACK FRAME | AS53: =IFERROR(_xlfn.XLOOKUP(AO53,CrossRef!$N:$N,CrossRef!$H:$H,"Not Found"),"-") -> LT - LEFT
A54: =E54&F54&U54 -> HCMUCRG-TCFS-TCFRRH | B54: =I54&D54&C54 -> EX70964028RI | C54: =_xlfn.XLOOKUP(A54,CrossRef!N:N,CrossRef!D:D,"",0) -> RI | D54: =_xlfn.XLOOKUP(A54,CrossRef!N:N,CrossRef!C:C,"",0) -> 4028 | E54: =LEFT(M54,3) -> HCM | F54: =_xlfn.TEXTAFTER(J54,"-") -> UCRG-TCFS-TCFR | G54: M350 | H54: M11D | I54: EX7096 | J54: EXBH045-UCRG-TCFS-TCFR | K54: HITACHI | L54: EX3600-6 | M54: HCM18M00H00001232 | N54: Active | O54: MEO | P54: Z01 | Q54: Inactive | R54: 97150 | S54: CW | T54: 001036 | U54: RH | V54: 35000H TRACK FRAME CHANGE RH | W54: 35000 | X54: 74757 | Y54: A/4536/1 | Z54: 49793 | AA54: 6.54 | AB54: 350560 | AD54: 0 | AE54: 41495 | AF54: 0 | AG54: -14793 | AH54: -0.42265714 | AI54: -2261.9266 | AJ54: 43963.073 | AK54: 47185 | AL54: -3222 | AM54: 56071.4 | AN54: 1.60204 | AO54: =E54&F54&U54 -> HCMUCRG-TCFS-TCFRRH | AP54: =_xlfn.XLOOKUP(AO54,CrossRef!N:N,CrossRef!A:A,"NOT FOUND",0) -> HCM4028RI | AQ54: =IFERROR(_xlfn.XLOOKUP(AO54,CrossRef!$N:$N,CrossRef!$E:$E,"Not Found"),"-") -> EX2500 | AR54: =IFERROR(_xlfn.XLOOKUP(AO54,CrossRef!$N:$N,CrossRef!$G:$G,"Not Found"),"-") -> 4028 - TRACK FRAME | AS54: =IFERROR(_xlfn.XLOOKUP(AO54,CrossRef!$N:$N,CrossRef!$H:$H,"Not Found"),"-") -> RI - RIGHT
A55: =E55&F55&U55 -> HCMSURE-SWBR-SWBR | B55: =I55&D55&C55 -> EX7096 | C55: =_xlfn.XLOOKUP(A55,CrossRef!N:N,CrossRef!D:D,"",0) | D55: =_xlfn.XLOOKUP(A55,CrossRef!N:N,CrossRef!C:C,"",0) | E55: =LEFT(M55,3) -> HCM | F55: =_xlfn.TEXTAFTER(J55,"-") -> SURE-SWBR-SWBR | G55: M350 | H55: M11D | I55: EX7096 | J55: EXBH045-SURE-SWBR-SWBR | K55: HITACHI | L55: EX3600-6 | M55: HCM18M00H00001232 | N55: Active | O55: MEO | P55: Z01 | Q55: Inactive | R55: 97152 | S55: CW | T55: 001038 | V55: 35000H SWING BEARING CHANGE | W55: 35000 | X55: 74759 | Y55: A/6333/1 | Z55: 49793 | AA55: 6.54 | AB55: 599266.39 | AD55: 0 | AE55: 41548 | AF55: 16 | AG55: -14777 | AH55: -0.4222 | AI55: -2259.4801 | AJ55: 43965.52 | AK55: 47185 | AL55: -3220 | AM55: 56071.4 | AN55: 1.6015829 | AO55: =E55&F55&U55 -> HCMSURE-SWBR-SWBR | AP55: =_xlfn.XLOOKUP(AO55,CrossRef!N:N,CrossRef!A:A,"NOT FOUND",0) -> NOT FOUND | AQ55: =IFERROR(_xlfn.XLOOKUP(AO55,CrossRef!$N:$N,CrossRef!$E:$E,"Not Found"),"-") -> Not Found | AR55: =IFERROR(_xlfn.XLOOKUP(AO55,CrossRef!$N:$N,CrossRef!$G:$G,"Not Found"),"-") -> Not Found | AS55: =IFERROR(_xlfn.XLOOKUP(AO55,CrossRef!$N:$N,CrossRef!$H:$H,"Not Found"),"-") -> Not Found
A56: =E56&F56&U56 -> DHJUCRG-TCID-TCIRRH | B56: =I56&D56&C56 -> EX7094 | C56: =_xlfn.XLOOKUP(A56,CrossRef!N:N,CrossRef!D:D,"",0) | D56: =_xlfn.XLOOKUP(A56,CrossRef!N:N,CrossRef!C:C,"",0) | E56: =MID(M56,FIND("DH",M56),3) -> DHJ | F56: =_xlfn.TEXTAFTER(J56,"-") -> UCRG-TCID-TCIR | G56: M776 | H56: M11E | I56: EX7094 | J56: EXBH055-UCRG-TCID-TCIR | K56: CATERPILLAR | L56: 6040 | M56: 170120 (DHJ40120) | N56: Active | O56: MEO | P56: Z01 | Q56: Active | R56: 111982 | S56: CW | T56: 001033 | U56: RH | V56: 10000H IDLER CHANGE RH | W56: 10000 | X56: 86116 | Y56: A/7563/1 | Z56: 70079 | AA56: 2.64 | AB56: 81162.92 | AD56: 4151111 | AE56: 45504 | AF56: 63412.2 | AG56: 3333.2 | AH56: 0.33332 | AI56: 1262.5758 | AJ56: 47487.576 | AK56: 47200 | AL56: 287 | AM56: 72653 | AN56: 0.92408 | AO56: =E56&F56&U56 -> DHJUCRG-TCID-TCIRRH | AP56: =_xlfn.XLOOKUP(AO56,CrossRef!N:N,CrossRef!A:A,"NOT FOUND",0) -> NOT FOUND | AQ56: =IFERROR(_xlfn.XLOOKUP(AO56,CrossRef!$N:$N,CrossRef!$E:$E,"Not Found"),"-") -> Not Found | AR56: =IFERROR(_xlfn.XLOOKUP(AO56,CrossRef!$N:$N,CrossRef!$G:$G,"Not Found"),"-") -> Not Found | AS56: =IFERROR(_xlfn.XLOOKUP(AO56,CrossRef!$N:$N,CrossRef!$H:$H,"Not Found"),"-") -> Not Found
A57: =E57&F57&U57 -> 4ARHYSY-CYHYLH | B57: =I57&D57&C57 -> QTD295102LT | C57: =_xlfn.XLOOKUP(A57,CrossRef!N:N,CrossRef!D:D,"",0) -> LT | D57: =_xlfn.XLOOKUP(A57,CrossRef!N:N,CrossRef!C:C,"",0) -> 5102 | E57: =LEFT(M57,3) -> 4AR | F57: =_xlfn.TEXTAFTER(J57,"-") -> HYSY-CYHY | G57: M350 | H57: M11D | I57: QTD29 | J57: TKHL118-HYSY-CYHY | K57: CATERPILLAR | L57: 793C | M57: 4AR00316 | N57: Active | O57: MEC | P57: Z01 | Q57: Active | R57: 96765 | S57: CC | T57: 001044 | U57: LH | V57: 20000H HOIST CYLINDER CHANGE LH | W57: 20000 | X57: 78084 | Y57: A/6618/1 | Z57: 146656 | AA57: 13.35 | AB57: 20259.99 | AD57: 4925132 | AE57: 43072 | AF57: 112167 | AG57: -14489 | AH57: -0.72445 | AI57: -1085.3184 | AJ57: 45139.682 | AK57: 45238 | AL57: -99 | AM57: 133479.55 | AN57: 1.0656275 | AO57: =E57&F57&U57 -> 4ARHYSY-CYHYLH | AP57: =_xlfn.XLOOKUP(AO57,CrossRef!N:N,CrossRef!A:A,"NOT FOUND",0) -> 4AR5102LT | AQ57: =IFERROR(_xlfn.XLOOKUP(AO57,CrossRef!$N:$N,CrossRef!$E:$E,"Not Found"),"-") -> 793C | AR57: =IFERROR(_xlfn.XLOOKUP(AO57,CrossRef!$N:$N,CrossRef!$G:$G,"Not Found"),"-") -> 5102 - LIFT/HOIST CYLINDER | AS57: =IFERROR(_xlfn.XLOOKUP(AO57,CrossRef!$N:$N,CrossRef!$H:$H,"Not Found"),"-") -> LT - LEFT
A58: =E58&F58&U58 -> JRPDRIV-WHGPLHF | B58: =I58&D58&C58 -> TD24184008LF | C58: =_xlfn.XLOOKUP(A58,CrossRef!N:N,CrossRef!D:D,"",0) -> LF | D58: =_xlfn.XLOOKUP(A58,CrossRef!N:N,CrossRef!C:C,"",0) -> 4008 | E58: =LEFT(M58,3) -> JRP | F58: =_xlfn.TEXTAFTER(J58,"-") -> DRIV-WHGP | G58: M800 | H58: M11Q | I58: TD2418 | J58: TKHL192-DRIV-WHGP | K58: CATERPILLAR | L58: 777F | M58: JRP00891 | N58: Active | O58: MEF | P58: Z01 | Q58: Inactive | R58: 182298 | S58: CH | T58: 001020 | U58: LHF | V58: 24000H WHEEL GROUP CHANGE LHF | W58: 24000 | X58: 145398 | Y58: A/25396/1 | Z58: 37823 | AA58: 7.74 | AB58: 107027.44 | AG58: -13823 | AH58: -0.57595833 | AI58: -1785.9173 | AJ58: 44439.083 | AO58: =E58&F58&U58 -> JRPDRIV-WHGPLHF | AP58: =_xlfn.XLOOKUP(AO58,CrossRef!N:N,CrossRef!A:A,"NOT FOUND",0) -> JRP4008LF | AQ58: =IFERROR(_xlfn.XLOOKUP(AO58,CrossRef!$N:$N,CrossRef!$E:$E,"Not Found"),"-") -> 777F | AR58: =IFERROR(_xlfn.XLOOKUP(AO58,CrossRef!$N:$N,CrossRef!$G:$G,"Not Found"),"-") -> 4008 - FINAL DRIVE, BRAKE & WHEEL | AS58: =IFERROR(_xlfn.XLOOKUP(AO58,CrossRef!$N:$N,CrossRef!$H:$H,"Not Found"),"-") -> LF - LEFT FRONT
A59: =E59&F59&U59 -> DHJHYSY-CYHY-CYSLLH | B59: =I59&D59&C59 -> EX7094 | C59: =_xlfn.XLOOKUP(A59,CrossRef!N:N,CrossRef!D:D,"",0) | D59: =_xlfn.XLOOKUP(A59,CrossRef!N:N,CrossRef!C:C,"",0) | E59: =MID(M59,FIND("DH",M59),3) -> DHJ | F59: =_xlfn.TEXTAFTER(J59,"-") -> HYSY-CYHY-CYSL | G59: M776 | H59: M11E | I59: EX7094 | J59: EXBH055-HYSY-CYHY-CYSL | K59: CATERPILLAR | L59: 6040 | M59: 170120 (DHJ40120) | N59: Active | O59: MEO | P59: Z01 | Q59: Active | R59: 111924 | S59: CC | T59: 001026 | U59: LH | V59: 10000H STICK CYLINDER CHANGE LH | W59: 10000 | X59: 86072 | Y59: A/8497/1 | Z59: 70079 | AA59: 2.64 | AB59: 68221.86 | AD59: 4485057 | AE59: 45957 | AF59: 68522 | AG59: 8443 | AH59: 0.8443 | AI59: 3198.1061 | AJ59: 49423.106 | AK59: 47574 | AL59: 1849 | AM59: 73640.36 | AN59: 0.511836 | AO59: =E59&F59&U59 -> DHJHYSY-CYHY-CYSLLH | AP59: =_xlfn.XLOOKUP(AO59,CrossRef!N:N,CrossRef!A:A,"NOT FOUND",0) -> NOT FOUND | AQ59: =IFERROR(_xlfn.XLOOKUP(AO59,CrossRef!$N:$N,CrossRef!$E:$E,"Not Found"),"-") -> Not Found | AR59: =IFERROR(_xlfn.XLOOKUP(AO59,CrossRef!$N:$N,CrossRef!$G:$G,"Not Found"),"-") -> Not Found | AS59: =IFERROR(_xlfn.XLOOKUP(AO59,CrossRef!$N:$N,CrossRef!$H:$H,"Not Found"),"-") -> Not Found
A60: =E60&F60&U60 -> SSPSURERHF | B60: =I60&D60&C60 -> TD65767201RF | C60: =_xlfn.XLOOKUP(A60,CrossRef!N:N,CrossRef!D:D,"",0) -> RF | D60: =_xlfn.XLOOKUP(A60,CrossRef!N:N,CrossRef!C:C,"",0) -> 7201 | E60: =LEFT(M60,3) -> SSP | F60: =_xlfn.TEXTAFTER(J60,"-") -> SURE | G60: M776 | H60: M11E | I60: TD6576 | J60: TKHL242-SURE | K60: CATERPILLAR | L60: 793F | M60: SSP00341 | N60: Active | O60: MEH | P60: Z01 | Q60: Active | R60: 194008 | S60: CC | T60: 001027 | U60: RHF | V60: 25000H SUSPENSION CYLINDER CHANGE RHF | W60: 25000 | X60: 154972 | Y60: A/24921/1 | Z60: 68886 | AA60: 14.49 | AB60: 68000.45 | AD60: 4642730 | AF60: 30998 | AG60: -12888 | AH60: -0.51552 | AI60: -889.44099 | AJ60: 45335.559 | AK60: 45608 | AL60: -273 | AM60: 59945.67 | AN60: 1.1579068 | AO60: =E60&F60&U60 -> SSPSURERHF | AP60: =_xlfn.XLOOKUP(AO60,CrossRef!N:N,CrossRef!A:A,"NOT FOUND",0) -> SSP7201RF | AQ60: =IFERROR(_xlfn.XLOOKUP(AO60,CrossRef!$N:$N,CrossRef!$E:$E,"Not Found"),"-") -> 793F | AR60: =IFERROR(_xlfn.XLOOKUP(AO60,CrossRef!$N:$N,CrossRef!$G:$G,"Not Found"),"-") -> 7201 - SUSPENSION CYLINDER | AS60: =IFERROR(_xlfn.XLOOKUP(AO60,CrossRef!$N:$N,CrossRef!$H:$H,"Not Found"),"-") -> RF - RIGHT FRONT
A61: =E61&F61&U61 -> SSPSURELHR | B61: =I61&D61&C61 -> TD6576 | C61: =_xlfn.XLOOKUP(A61,CrossRef!N:N,CrossRef!D:D,"",0) | D61: =_xlfn.XLOOKUP(A61,CrossRef!N:N,CrossRef!C:C,"",0) | E61: =LEFT(M61,3) -> SSP | F61: =_xlfn.TEXTAFTER(J61,"-") -> SURE | G61: M776 | H61: M11E | I61: TD6576 | J61: TKHL242-SURE | K61: CATERPILLAR | L61: 793F | M61: SSP00341 | N61: Active | O61: MEH | P61: Z01 | Q61: Active | R61: 194176 | S61: CC | T61: 001027 | U61: LHR | V61: 25000H SUSPENSION CYLINDER CHANGE LHR | W61: 25000 | X61: 154964 | Y61: A/24922/1 | Z61: 68886 | AA61: 14.49 | AB61: 36270.04 | AD61: 4642849 | AF61: 30998 | AG61: -12888 | AH61: -0.51552 | AI61: -889.44099 | AJ61: 45335.559 | AK61: 45608 | AL61: -273 | AM61: 59945.67 | AN61: 1.1579068 | AO61: =E61&F61&U61 -> SSPSURELHR | AP61: =_xlfn.XLOOKUP(AO61,CrossRef!N:N,CrossRef!A:A,"NOT FOUND",0) -> NOT FOUND | AQ61: =IFERROR(_xlfn.XLOOKUP(AO61,CrossRef!$N:$N,CrossRef!$E:$E,"Not Found"),"-") -> Not Found | AR61: =IFERROR(_xlfn.XLOOKUP(AO61,CrossRef!$N:$N,CrossRef!$G:$G,"Not Found"),"-") -> Not Found | AS61: =IFERROR(_xlfn.XLOOKUP(AO61,CrossRef!$N:$N,CrossRef!$H:$H,"Not Found"),"-") -> Not Found
A62: =E62&F62&U62 -> SSPSURERHR | B62: =I62&D62&C62 -> TD6576 | C62: =_xlfn.XLOOKUP(A62,CrossRef!N:N,CrossRef!D:D,"",0) | D62: =_xlfn.XLOOKUP(A62,CrossRef!N:N,CrossRef!C:C,"",0) | E62: =LEFT(M62,3) -> SSP | F62: =_xlfn.TEXTAFTER(J62,"-") -> SURE | G62: M776 | H62: M11E | I62: TD6576 | J62: TKHL242-SURE | K62: CATERPILLAR | L62: 793F | M62: SSP00341 | N62: Active | O62: MEH | P62: Z01 | Q62: Active | R62: 194177 | S62: CC | T62: 001027 | U62: RHR | V62: 25000H SUSPENSION CYLINDER CHANGE RHR | W62: 25000 | X62: 154965 | Y62: A/24922/1 | Z62: 68886 | AA62: 14.49 | AB62: 36270.04 | AD62: 4642853 | AF62: 30998 | AG62: -12888 | AH62: -0.51552 | AI62: -889.44099 | AJ62: 45335.559 | AK62: 45608 | AL62: -273 | AM62: 59945.67 | AN62: 1.1579068 | AO62: =E62&F62&U62 -> SSPSURERHR | AP62: =_xlfn.XLOOKUP(AO62,CrossRef!N:N,CrossRef!A:A,"NOT FOUND",0) -> NOT FOUND | AQ62: =IFERROR(_xlfn.XLOOKUP(AO62,CrossRef!$N:$N,CrossRef!$E:$E,"Not Found"),"-") -> Not Found | AR62: =IFERROR(_xlfn.XLOOKUP(AO62,CrossRef!$N:$N,CrossRef!$G:$G,"Not Found"),"-") -> Not Found | AS62: =IFERROR(_xlfn.XLOOKUP(AO62,CrossRef!$N:$N,CrossRef!$H:$H,"Not Found"),"-") -> Not Found
A63: =E63&F63&U63 -> HCMIMAT-BOOM | B63: =I63&D63&C63 -> EX7114 | C63: =_xlfn.XLOOKUP(A63,CrossRef!N:N,CrossRef!D:D,"",0) | D63: =_xlfn.XLOOKUP(A63,CrossRef!N:N,CrossRef!C:C,"",0) | E63: =LEFT(M63,3) -> HCM | F63: =_xlfn.TEXTAFTER(J63,"-") -> IMAT-BOOM | G63: M350 | H63: M11D | I63: EX7114 | J63: EXBH046-IMAT-BOOM | K63: HITACHI | L63: EX1900-6 | M63: HCM18K00P00001032 | N63: Active | O63: MEF | P63: Z01 | Q63: Active | R63: 100406 | S63: CW | T63: 001028 | V63: 18000H BOOM CHANGE | W63: 18000 | X63: 77139 | Y63: A/6267/1 | Z63: 30317 | AA63: 5.39 | AB63: 273450 | AD63: 4772892 | AE63: 39448 | AF63: 0 | AG63: -12317 | AH63: -0.68427778 | AI63: -2285.1577 | AJ63: 43939.842 | AK63: 48023 | AL63: -4084 | AM63: 40008.22 | AN63: 2.2226789 | AO63: =E63&F63&U63 -> HCMIMAT-BOOM | AP63: =_xlfn.XLOOKUP(AO63,CrossRef!N:N,CrossRef!A:A,"NOT FOUND",0) -> NOT FOUND | AQ63: =IFERROR(_xlfn.XLOOKUP(AO63,CrossRef!$N:$N,CrossRef!$E:$E,"Not Found"),"-") -> Not Found | AR63: =IFERROR(_xlfn.XLOOKUP(AO63,CrossRef!$N:$N,CrossRef!$G:$G,"Not Found"),"-") -> Not Found | AS63: =IFERROR(_xlfn.XLOOKUP(AO63,CrossRef!$N:$N,CrossRef!$H:$H,"Not Found"),"-") -> Not Found
A64: =E64&F64&U64 -> HCMIMAT-SICK | B64: =I64&D64&C64 -> EX7114 | C64: =_xlfn.XLOOKUP(A64,CrossRef!N:N,CrossRef!D:D,"",0) | D64: =_xlfn.XLOOKUP(A64,CrossRef!N:N,CrossRef!C:C,"",0) | E64: =LEFT(M64,3) -> HCM | F64: =_xlfn.TEXTAFTER(J64,"-") -> IMAT-SICK | G64: M350 | H64: M11D | I64: EX7114 | J64: EXBH046-IMAT-SICK | K64: HITACHI | L64: EX1900-6 | M64: HCM18K00P00001032 | N64: Active | O64: MEF | P64: Z01 | Q64: Active | R64: 100405 | S64: CW | T64: 001037 | V64: 18000H STICK CHANGE | W64: 18000 | X64: 77138 | Y64: A/6323/1 | Z64: 30317 | AA64: 5.39 | AB64: 176900 | AD64: 4772894 | AE64: 39448 | AF64: 0 | AG64: -12317 | AH64: -0.68427778 | AI64: -2285.1577 | AJ64: 43939.842 | AK64: 48023 | AL64: -4084 | AM64: 40008.22 | AN64: 2.2226789 | AO64: =E64&F64&U64 -> HCMIMAT-SICK | AP64: =_xlfn.XLOOKUP(AO64,CrossRef!N:N,CrossRef!A:A,"NOT FOUND",0) -> NOT FOUND | AQ64: =IFERROR(_xlfn.XLOOKUP(AO64,CrossRef!$N:$N,CrossRef!$E:$E,"Not Found"),"-") -> Not Found | AR64: =IFERROR(_xlfn.XLOOKUP(AO64,CrossRef!$N:$N,CrossRef!$G:$G,"Not Found"),"-") -> Not Found | AS64: =IFERROR(_xlfn.XLOOKUP(AO64,CrossRef!$N:$N,CrossRef!$H:$H,"Not Found"),"-") -> Not Found
A65: =E65&F65&U65 -> HCMSURE-SWBR | B65: =I65&D65&C65 -> EX7086 | C65: =_xlfn.XLOOKUP(A65,CrossRef!N:N,CrossRef!D:D,"",0) | D65: =_xlfn.XLOOKUP(A65,CrossRef!N:N,CrossRef!C:C,"",0) | E65: =LEFT(M65,3) -> HCM | F65: =_xlfn.TEXTAFTER(J65,"-") -> SURE-SWBR | G65: M776 | H65: M11E | I65: EX7086 | J65: EXBH053-SURE-SWBR | K65: HITACHI | L65: EX2600-6 | M65: HCMKBA90V00002013 | N65: Active | O65: MEO | P65: Z01 | Q65: Active | R65: 112668 | S65: CW | T65: 001038 | V65: 36000H SWING BEARING CHANGE | W65: 36000 | X65: 86675 | Y65: A/25285/1 | Z65: 47875.8 | AA65: 8.51 | AB65: 403523.59 | AD65: 4662567 | AF65: 0 | AG65: -11875.8 | AH65: -0.32988333 | AI65: -1395.5112 | AJ65: 44829.489 | AK65: 45643 | AL65: -814 | AM65: 42922.98 | AN65: 1.192305 | AO65: =E65&F65&U65 -> HCMSURE-SWBR | AP65: =_xlfn.XLOOKUP(AO65,CrossRef!N:N,CrossRef!A:A,"NOT FOUND",0) -> NOT FOUND | AQ65: =IFERROR(_xlfn.XLOOKUP(AO65,CrossRef!$N:$N,CrossRef!$E:$E,"Not Found"),"-") -> Not Found | AR65: =IFERROR(_xlfn.XLOOKUP(AO65,CrossRef!$N:$N,CrossRef!$G:$G,"Not Found"),"-") -> Not Found | AS65: =IFERROR(_xlfn.XLOOKUP(AO65,CrossRef!$N:$N,CrossRef!$H:$H,"Not Found"),"-") -> Not Found
A66: =E66&F66&U66 -> SSPSURE-SPSNLHF | B66: =I66&D66&C66 -> TD63107201LF | C66: =_xlfn.XLOOKUP(A66,CrossRef!N:N,CrossRef!D:D,"",0) -> LF | D66: =_xlfn.XLOOKUP(A66,CrossRef!N:N,CrossRef!C:C,"",0) -> 7201 | E66: =LEFT(M66,3) -> SSP | F66: =_xlfn.TEXTAFTER(J66,"-") -> SURE-SPSN | G66: M776 | H66: M11E | I66: TD6310 | J66: TKHL131-SURE-SPSN | K66: CATERPILLAR | L66: 793F | M66: SSP00857 | N66: Active | O66: MEO | P66: Z01 | Q66: Active | R66: 96922 | S66: CC | T66: 001027 | U66: LHF | V66: 24000H SUSPENSION CYLINDER CHANGE LHF | W66: 24000 | X66: 74546 | Y66: A/7793/1 | Z66: 72634.85 | AA66: 14.07 | AB66: 68000.45 | AD66: 4546550 | AE66: 43655 | AF66: 37207 | AG66: -11427.85 | AH66: -0.47616042 | AI66: -812.21393 | AJ66: 45412.786 | AK66: 45432 | AL66: -20 | AM66: 61477.34 | AN66: 1.0112642 | AO66: =E66&F66&U66 -> SSPSURE-SPSNLHF | AP66: =_xlfn.XLOOKUP(AO66,CrossRef!N:N,CrossRef!A:A,"NOT FOUND",0) -> SSP7201LF | AQ66: =IFERROR(_xlfn.XLOOKUP(AO66,CrossRef!$N:$N,CrossRef!$E:$E,"Not Found"),"-") -> 793F | AR66: =IFERROR(_xlfn.XLOOKUP(AO66,CrossRef!$N:$N,CrossRef!$G:$G,"Not Found"),"-") -> 7201 - SUSPENSION CYLINDER | AS66: =IFERROR(_xlfn.XLOOKUP(AO66,CrossRef!$N:$N,CrossRef!$H:$H,"Not Found"),"-") -> LF - LEFT FRONT
A67: =E67&F67&U67 -> RABUCRG-TCFSRH | B67: =I67&D67&C67 -> DZ81664028RI | C67: =_xlfn.XLOOKUP(A67,CrossRef!N:N,CrossRef!D:D,"",0) -> RI | D67: =_xlfn.XLOOKUP(A67,CrossRef!N:N,CrossRef!C:C,"",0) -> 4028 | E67: =LEFT(M67,3) -> RAB | F67: =_xlfn.TEXTAFTER(J67,"-") -> UCRG-TCFS | G67: M147 | H67: M11J | I67: DZ8166 | J67: DZTR021-UCRG-TCFS | K67: CATERPILLAR | L67: D10T2 | M67: RAB00869 | N67: Active | O67: MEF | P67: Z01 | Q67: Active | R67: 26138 | S67: CW | T67: 001036 | U67: RH | V67: 21000H TRACK FRAME CHANGE RH | W67: 16000 | X67: 20001 | Y67: A/27313/1 | Z67: 27423 | AA67: 13.39 | AB67: 184192.64 | AD67: 4848219 | AE67: 43859 | AF67: 0 | AG67: -11423 | AH67: -0.7139375 | AI67: -853.09933 | AJ67: 45371.901 | AK67: 45972 | AL67: -601 | AM67: 24035.33 | AN67: 1.5022081 | AO67: =E67&F67&U67 -> RABUCRG-TCFSRH | AP67: =_xlfn.XLOOKUP(AO67,CrossRef!N:N,CrossRef!A:A,"NOT FOUND",0) -> RAB4028RI | AQ67: =IFERROR(_xlfn.XLOOKUP(AO67,CrossRef!$N:$N,CrossRef!$E:$E,"Not Found"),"-") -> D10T2 | AR67: =IFERROR(_xlfn.XLOOKUP(AO67,CrossRef!$N:$N,CrossRef!$G:$G,"Not Found"),"-") -> 4028 - TRACK FRAME | AS67: =IFERROR(_xlfn.XLOOKUP(AO67,CrossRef!$N:$N,CrossRef!$H:$H,"Not Found"),"-") -> RI - RIGHT
A68: =E68&F68&U68 -> RABUCRG-TCFSLH | B68: =I68&D68&C68 -> DZ81664028LT | C68: =_xlfn.XLOOKUP(A68,CrossRef!N:N,CrossRef!D:D,"",0) -> LT | D68: =_xlfn.XLOOKUP(A68,CrossRef!N:N,CrossRef!C:C,"",0) -> 4028 | E68: =LEFT(M68,3) -> RAB | F68: =_xlfn.TEXTAFTER(J68,"-") -> UCRG-TCFS | G68: M147 | H68: M11J | I68: DZ8166 | J68: DZTR021-UCRG-TCFS | K68: CATERPILLAR | L68: D10T2 | M68: RAB00869 | N68: Active | O68: MEF | P68: Z01 | Q68: Active | R68: 26139 | S68: CW | T68: 001036 | U68: LH | V68: 21000H TRACK FRAME CHANGE LH | W68: 16000 | X68: 20002 | Y68: A/27081/1 | Z68: 27423 | AA68: 13.39 | AB68: 184192.64 | AD68: 4848240 | AE68: 43859 | AF68: 0 | AG68: -11423 | AH68: -0.7139375 | AI68: -853.09933 | AJ68: 45371.901 | AK68: 45972 | AL68: -601 | AM68: 24035.33 | AN68: 1.5022081 | AO68: =E68&F68&U68 -> RABUCRG-TCFSLH | AP68: =_xlfn.XLOOKUP(AO68,CrossRef!N:N,CrossRef!A:A,"NOT FOUND",0) -> RAB4028LT | AQ68: =IFERROR(_xlfn.XLOOKUP(AO68,CrossRef!$N:$N,CrossRef!$E:$E,"Not Found"),"-") -> D10T2 | AR68: =IFERROR(_xlfn.XLOOKUP(AO68,CrossRef!$N:$N,CrossRef!$G:$G,"Not Found"),"-") -> 4028 - TRACK FRAME | AS68: =IFERROR(_xlfn.XLOOKUP(AO68,CrossRef!$N:$N,CrossRef!$H:$H,"Not Found"),"-") -> LT - LEFT
A69: =E69&F69&U69 -> DHJUCRG-TCIDLH | B69: =I69&D69&C69 -> EX7090LT | C69: =_xlfn.XLOOKUP(A69,CrossRef!N:N,CrossRef!D:D,"",0) -> LT | D69: =_xlfn.XLOOKUP(A69,CrossRef!N:N,CrossRef!C:C,"",0) | E69: =MID(M69,FIND("DH",M69),3) -> DHJ | F69: =_xlfn.TEXTAFTER(J69,"-") -> UCRG-TCID | G69: M776 | H69: M11E | I69: EX7090 | J69: EXBH054-UCRG-TCID | K69: CATERPILLAR | L69: 6040 | M69: 170107 (DHJ40107) | N69: Active | O69: MEO | P69: Z01 | Q69: Active | R69: 111985 | S69: CW | T69: 001033 | U69: LH | V69: 10000H IDLER CHANGE LH | W69: 10000 | X69: 92237 | Y69: A/7563/1 | Z69: 68606 | AA69: 12.6 | AB69: 81162.92 | AD69: 4747274 | AE69: 43980 | AF69: 47319 | AG69: -11287 | AH69: -1.1287 | AI69: -895.79365 | AJ69: 45329.206 | AK69: 45975 | AL69: -646 | AM69: 65456 | AN69: 1.8137 | AO69: =E69&F69&U69 -> DHJUCRG-TCIDLH | AP69: =_xlfn.XLOOKUP(AO69,CrossRef!N:N,CrossRef!A:A,"NOT FOUND",0) -> DHJLT | AQ69: =IFERROR(_xlfn.XLOOKUP(AO69,CrossRef!$N:$N,CrossRef!$E:$E,"Not Found"),"-") -> 6040 | AR69: =IFERROR(_xlfn.XLOOKUP(AO69,CrossRef!$N:$N,CrossRef!$G:$G,"Not Found"),"-") -> 0 | AS69: =IFERROR(_xlfn.XLOOKUP(AO69,CrossRef!$N:$N,CrossRef!$H:$H,"Not Found"),"-") -> LT - LEFT
A70: =E70&F70&U70 -> ELZHYSY-CYHY-CYBRRH | B70: =I70&D70&C70 -> EX7128 | C70: =_xlfn.XLOOKUP(A70,CrossRef!N:N,CrossRef!D:D,"",0) | D70: =_xlfn.XLOOKUP(A70,CrossRef!N:N,CrossRef!C:C,"",0) | E70: =LEFT(M70,3) -> ELZ | F70: =_xlfn.TEXTAFTER(J70,"-") -> HYSY-CYHY-CYBR | G70: M776 | H70: M11E | I70: EX7128 | J70: EXBH072-HYSY-CYHY-CYBR | K70: CATERPILLAR | L70: 6040 | M70: ELZ00107 | N70: Active | O70: MEF | P70: Z01 | Q70: Active | R70: 159529 | S70: CC | T70: 001023 | U70: RH | V70: 12000H BOOM CYLINDER CHANGE RH | W70: 12000 | X70: 125295 | Y70: A/8143/1 | Z70: 22566.4 | AA70: 14.49 | AB70: 96075.11 | AD70: 4930702 | AG70: -10566.4 | AH70: -0.88053333 | AI70: -729.22015 | AJ70: 45495.78 | AK70: 45368 | AL70: 127 | AM70: 10148.47 | AO70: =E70&F70&U70 -> ELZHYSY-CYHY-CYBRRH | AP70: =_xlfn.XLOOKUP(AO70,CrossRef!N:N,CrossRef!A:A,"NOT FOUND",0) -> NOT FOUND | AQ70: =IFERROR(_xlfn.XLOOKUP(AO70,CrossRef!$N:$N,CrossRef!$E:$E,"Not Found"),"-") -> Not Found | AR70: =IFERROR(_xlfn.XLOOKUP(AO70,CrossRef!$N:$N,CrossRef!$G:$G,"Not Found"),"-") -> Not Found | AS70: =IFERROR(_xlfn.XLOOKUP(AO70,CrossRef!$N:$N,CrossRef!$H:$H,"Not Found"),"-") -> Not Found
A71: =E71&F71&U71 -> FARHYSY-CYHY | B71: =I71&D71&C71 -> QEX035456LT | C71: =_xlfn.XLOOKUP(A71,CrossRef!N:N,CrossRef!D:D,"",0) -> LT | D71: =_xlfn.XLOOKUP(A71,CrossRef!N:N,CrossRef!C:C,"",0) -> 5456 | E71: =LEFT(M71,3) -> FAR | F71: =_xlfn.TEXTAFTER(J71,"-") -> HYSY-CYHY | G71: M350 | H71: M11D | I71: QEX03 | J71: EXRB005-HYSY-CYHY | K71: CATERPILLAR | L71: 336DL | M71: FAR00209 | N71: Active | O71: MEC | P71: Z01 | Q71: Active | R71: 101135 | S71: CC | T71: 001026 | V71: 8000H STICK CYLINDER CHANGE | W71: 8000 | X71: 77748 | Y71: A/5264/1 | Z71: 18543 | AA71: 1.77 | AB71: 8848 | AG71: -10543 | AH71: -1.317875 | AI71: -5956.4972 | AJ71: 40268.503 | AO71: =E71&F71&U71 -> FARHYSY-CYHY | AP71: =_xlfn.XLOOKUP(AO71,CrossRef!N:N,CrossRef!A:A,"NOT FOUND",0) -> FAR5456LT | AQ71: =IFERROR(_xlfn.XLOOKUP(AO71,CrossRef!$N:$N,CrossRef!$E:$E,"Not Found"),"-") -> 336DL | AR71: =IFERROR(_xlfn.XLOOKUP(AO71,CrossRef!$N:$N,CrossRef!$G:$G,"Not Found"),"-") -> 5456 - BOOM CYLINDER | AS71: =IFERROR(_xlfn.XLOOKUP(AO71,CrossRef!$N:$N,CrossRef!$H:$H,"Not Found"),"-") -> LT - LEFT
A72: =E72&F72&U72 -> DHJHYSY-CYHY-CYSRRH | B72: =I72&D72&C72 -> EX7094 | C72: =_xlfn.XLOOKUP(A72,CrossRef!N:N,CrossRef!D:D,"",0) | D72: =_xlfn.XLOOKUP(A72,CrossRef!N:N,CrossRef!C:C,"",0) | E72: =MID(M72,FIND("DH",M72),3) -> DHJ | F72: =_xlfn.TEXTAFTER(J72,"-") -> HYSY-CYHY-CYSR | G72: M776 | H72: M11E | I72: EX7094 | J72: EXBH055-HYSY-CYHY-CYSR | K72: CATERPILLAR | L72: 6040 | M72: 170120 (DHJ40120) | N72: Active | O72: MEO | P72: Z01 | Q72: Active | R72: 111923 | S72: CC | T72: 001026 | U72: RH | V72: 10000H STICK CYLINDER CHANGE RH | W72: 10000 | X72: 86071 | Y72: A/8498/1 | Z72: 70079 | AA72: 2.64 | AB72: 68221.86 | AD72: 4620231 | AE72: 45957 | AF72: 68522 | AG72: 8443 | AH72: 0.8443 | AI72: 3198.1061 | AJ72: 49423.106 | AK72: 47574 | AL72: 1849 | AM72: 73640.36 | AN72: 0.511836 | AO72: =E72&F72&U72 -> DHJHYSY-CYHY-CYSRRH | AP72: =_xlfn.XLOOKUP(AO72,CrossRef!N:N,CrossRef!A:A,"NOT FOUND",0) -> NOT FOUND | AQ72: =IFERROR(_xlfn.XLOOKUP(AO72,CrossRef!$N:$N,CrossRef!$E:$E,"Not Found"),"-") -> Not Found | AR72: =IFERROR(_xlfn.XLOOKUP(AO72,CrossRef!$N:$N,CrossRef!$G:$G,"Not Found"),"-") -> Not Found | AS72: =IFERROR(_xlfn.XLOOKUP(AO72,CrossRef!$N:$N,CrossRef!$H:$H,"Not Found"),"-") -> Not Found
A73: =E73&F73&U73 -> RABUCRG-TCFSRH | B73: =I73&D73&C73 -> DZ81654028RI | C73: =_xlfn.XLOOKUP(A73,CrossRef!N:N,CrossRef!D:D,"",0) -> RI | D73: =_xlfn.XLOOKUP(A73,CrossRef!N:N,CrossRef!C:C,"",0) -> 4028 | E73: =LEFT(M73,3) -> RAB | F73: =_xlfn.TEXTAFTER(J73,"-") -> UCRG-TCFS | G73: M147 | H73: M11J | I73: DZ8165 | J73: DZTR020-UCRG-TCFS | K73: CATERPILLAR | L73: D10T2 | M73: RAB00868 | N73: Active | O73: MEF | P73: Z01 | Q73: Active | R73: 28687 | S73: CW | T73: 001036 | U73: RH | V73: 21000H TRACK FRAME CHANGE RH | W73: 16000 | X73: 22193 | Y73: A/27313/1 | Z73: 26343.85 | AA73: 10.54 | AB73: 184192.64 | AD73: 4929853 | AE73: 43857 | AF73: 0 | AG73: -10343.85 | AH73: -0.64649062 | AI73: -981.38994 | AJ73: 45243.61 | AK73: 46824 | AL73: -1581 | AM73: 32657.31 | AN73: 2.0410819 | AO73: =E73&F73&U73 -> RABUCRG-TCFSRH | AP73: =_xlfn.XLOOKUP(AO73,CrossRef!N:N,CrossRef!A:A,"NOT FOUND",0) -> RAB4028RI | AQ73: =IFERROR(_xlfn.XLOOKUP(AO73,CrossRef!$N:$N,CrossRef!$E:$E,"Not Found"),"-") -> D10T2 | AR73: =IFERROR(_xlfn.XLOOKUP(AO73,CrossRef!$N:$N,CrossRef!$G:$G,"Not Found"),"-") -> 4028 - TRACK FRAME | AS73: =IFERROR(_xlfn.XLOOKUP(AO73,CrossRef!$N:$N,CrossRef!$H:$H,"Not Found"),"-") -> RI - RIGHT
A74: =E74&F74&U74 -> RABUCRG-TCFSLH | B74: =I74&D74&C74 -> DZ81654028LT | C74: =_xlfn.XLOOKUP(A74,CrossRef!N:N,CrossRef!D:D,"",0) -> LT | D74: =_xlfn.XLOOKUP(A74,CrossRef!N:N,CrossRef!C:C,"",0) -> 4028 | E74: =LEFT(M74,3) -> RAB | F74: =_xlfn.TEXTAFTER(J74,"-") -> UCRG-TCFS | G74: M147 | H74: M11J | I74: DZ8165 | J74: DZTR020-UCRG-TCFS | K74: CATERPILLAR | L74: D10T2 | M74: RAB00868 | N74: Active | O74: MEF | P74: Z01 | Q74: Active | R74: 28688 | S74: CW | T74: 001036 | U74: LH | V74: 21000H TRACK FRAME CHANGE LH | W74: 16000 | X74: 22194 | Y74: A/27081/1 | Z74: 26343.85 | AA74: 10.54 | AB74: 184192.64 | AD74: 4929865 | AE74: 43857 | AF74: 0 | AG74: -10343.85 | AH74: -0.64649062 | AI74: -981.38994 | AJ74: 45243.61 | AK74: 46824 | AL74: -1581 | AM74: 32657.31 | AN74: 2.0410819 | AO74: =E74&F74&U74 -> RABUCRG-TCFSLH | AP74: =_xlfn.XLOOKUP(AO74,CrossRef!N:N,CrossRef!A:A,"NOT FOUND",0) -> RAB4028LT | AQ74: =IFERROR(_xlfn.XLOOKUP(AO74,CrossRef!$N:$N,CrossRef!$E:$E,"Not Found"),"-") -> D10T2 | AR74: =IFERROR(_xlfn.XLOOKUP(AO74,CrossRef!$N:$N,CrossRef!$G:$G,"Not Found"),"-") -> 4028 - TRACK FRAME | AS74: =IFERROR(_xlfn.XLOOKUP(AO74,CrossRef!$N:$N,CrossRef!$H:$H,"Not Found"),"-") -> LT - LEFT
A75: =E75&F75&U75 -> HCMIMAT | B75: =I75&D75&C75 -> EX7150 | C75: =_xlfn.XLOOKUP(A75,CrossRef!N:N,CrossRef!D:D,"",0) | D75: =_xlfn.XLOOKUP(A75,CrossRef!N:N,CrossRef!C:C,"",0) | E75: =LEFT(M75,3) -> HCM | F75: =_xlfn.TEXTAFTER(J75,"-") -> IMAT | G75: M147 | H75: M11J | I75: EX7150 | J75: EXBH049-IMAT | K75: HITACHI | L75: EX3600-7 | M75: HCMKFA90P00007016 | N75: Active | O75: MEF | P75: Z01 | Q75: Active | R75: 134323 | S75: CW | T75: 001028 | V75: 18000H BOOM CHANGE | W75: 18000 | X75: 104203 | Y75: A/6885/1 | Z75: 28045.6 | AA75: 16.74 | AB75: 343500 | AD75: 4571028 | AF75: 0 | AG75: -10045.6 | AH75: -0.55808889 | AI75: -600.09558 | AJ75: 45624.904 | AK75: 45652 | AL75: -28 | AM75: 18453.58 | AN75: 1.0251989 | AO75: =E75&F75&U75 -> HCMIMAT | AP75: =_xlfn.XLOOKUP(AO75,CrossRef!N:N,CrossRef!A:A,"NOT FOUND",0) -> NOT FOUND | AQ75: =IFERROR(_xlfn.XLOOKUP(AO75,CrossRef!$N:$N,CrossRef!$E:$E,"Not Found"),"-") -> Not Found | AR75: =IFERROR(_xlfn.XLOOKUP(AO75,CrossRef!$N:$N,CrossRef!$G:$G,"Not Found"),"-") -> Not Found | AS75: =IFERROR(_xlfn.XLOOKUP(AO75,CrossRef!$N:$N,CrossRef!$H:$H,"Not Found"),"-") -> Not Found
A76: =E76&F76&U76 -> HCMIMAT-SICK | B76: =I76&D76&C76 -> EX7150 | C76: =_xlfn.XLOOKUP(A76,CrossRef!N:N,CrossRef!D:D,"",0) | D76: =_xlfn.XLOOKUP(A76,CrossRef!N:N,CrossRef!C:C,"",0) | E76: =LEFT(M76,3) -> HCM | F76: =_xlfn.TEXTAFTER(J76,"-") -> IMAT-SICK | G76: M147 | H76: M11J | I76: EX7150 | J76: EXBH049-IMAT-SICK | K76: HITACHI | L76: EX3600-7 | M76: HCMKFA90P00007016 | N76: Active | O76: MEF | P76: Z01 | Q76: Active | R76: 134347 | S76: CW | T76: 001037 | V76: 18000H STICK CHANGE | W76: 18000 | X76: 104224 | Y76: A/6912/1 | Z76: 28045.6 | AA76: 16.74 | AB76: 248300 | AD76: 4571030 | AF76: 0 | AG76: -10045.6 | AH76: -0.55808889 | AI76: -600.09558 | AJ76: 45624.904 | AK76: 45652 | AL76: -28 | AM76: 18453.58 | AN76: 1.0251989 | AO76: =E76&F76&U76 -> HCMIMAT-SICK | AP76: =_xlfn.XLOOKUP(AO76,CrossRef!N:N,CrossRef!A:A,"NOT FOUND",0) -> NOT FOUND | AQ76: =IFERROR(_xlfn.XLOOKUP(AO76,CrossRef!$N:$N,CrossRef!$E:$E,"Not Found"),"-") -> Not Found | AR76: =IFERROR(_xlfn.XLOOKUP(AO76,CrossRef!$N:$N,CrossRef!$G:$G,"Not Found"),"-") -> Not Found | AS76: =IFERROR(_xlfn.XLOOKUP(AO76,CrossRef!$N:$N,CrossRef!$H:$H,"Not Found"),"-") -> Not Found
A77: =E77&F77&U77 -> DH3UCRG-TCID-TCIRRH | B77: =I77&D77&C77 -> EX70994159RI | C77: =_xlfn.XLOOKUP(A77,CrossRef!N:N,CrossRef!D:D,"",0) -> RI | D77: =_xlfn.XLOOKUP(A77,CrossRef!N:N,CrossRef!C:C,"",0) -> 4159 | E77: =MID(M77,FIND("DH",M77),3) -> DH3 | F77: =_xlfn.TEXTAFTER(J77,"-") -> UCRG-TCID-TCIR | G77: M004 | H77: M11Q | I77: EX7099 | J77: EXFS001-UCRG-TCID-TCIR | K77: CATERPILLAR | L77: 6060 FACE SHOVEL | M77: DH360164 | N77: Active | O77: MEO | P77: Z01 | Q77: Active | R77: 112460 | S77: CW | T77: 001033 | U77: RH | V77: 16000H IDLER CHANGE RH | W77: 16000 | X77: 86491 | Y77: A/25929/1 | Z77: 52668.1 | AA77: 0 | AB77: 75927.57 | AD77: 4177012 | AE77: 44363 | AF77: 27062 | AG77: -9606.1 | AH77: -0.60038125 | AI77: 0 | AJ77: 46225 | AK77: 47144 | AL77: -919 | AO77: =E77&F77&U77 -> DH3UCRG-TCID-TCIRRH | AP77: =_xlfn.XLOOKUP(AO77,CrossRef!N:N,CrossRef!A:A,"NOT FOUND",0) -> DH34159RI | AQ77: =IFERROR(_xlfn.XLOOKUP(AO77,CrossRef!$N:$N,CrossRef!$E:$E,"Not Found"),"-") -> 6060 FACE SHOVEL | AR77: =IFERROR(_xlfn.XLOOKUP(AO77,CrossRef!$N:$N,CrossRef!$G:$G,"Not Found"),"-") -> 4159 - IDLER/IDLER WHEEL | AS77: =IFERROR(_xlfn.XLOOKUP(AO77,CrossRef!$N:$N,CrossRef!$H:$H,"Not Found"),"-") -> RI - RIGHT
A78: =E78&F78&U78 -> SSPSURERHR | B78: =I78&D78&C78 -> TD6575 | C78: =_xlfn.XLOOKUP(A78,CrossRef!N:N,CrossRef!D:D,"",0) | D78: =_xlfn.XLOOKUP(A78,CrossRef!N:N,CrossRef!C:C,"",0) | E78: =LEFT(M78,3) -> SSP | F78: =_xlfn.TEXTAFTER(J78,"-") -> SURE | G78: M776 | H78: M11E | I78: TD6575 | J78: TKHL241-SURE | K78: CATERPILLAR | L78: 793F | M78: SSP00339 | N78: Active | O78: MEH | P78: Z01 | Q78: Active | R78: 194172 | S78: CC | T78: 001027 | U78: RHR | V78: 25000H SUSPENSION CYLINDER CHANGE RHR | W78: 25000 | X78: 154950 | Y78: A/24922/1 | Z78: 65903.91 | AA78: 12.54 | AB78: 36270.04 | AD78: 4642729 | AF78: 31825 | AG78: -9078.91 | AH78: -0.3631564 | AI78: -723.99601 | AJ78: 45501.004 | AK78: 45608 | AL78: -107 | AM78: 58166.73 | AN78: 1.0536692 | AO78: =E78&F78&U78 -> SSPSURERHR | AP78: =_xlfn.XLOOKUP(AO78,CrossRef!N:N,CrossRef!A:A,"NOT FOUND",0) -> NOT FOUND | AQ78: =IFERROR(_xlfn.XLOOKUP(AO78,CrossRef!$N:$N,CrossRef!$E:$E,"Not Found"),"-") -> Not Found | AR78: =IFERROR(_xlfn.XLOOKUP(AO78,CrossRef!$N:$N,CrossRef!$G:$G,"Not Found"),"-") -> Not Found | AS78: =IFERROR(_xlfn.XLOOKUP(AO78,CrossRef!$N:$N,CrossRef!$H:$H,"Not Found"),"-") -> Not Found
A79: =E79&F79&U79 -> HCMIMAT-BOOM-BOOM | B79: =I79&D79&C79 -> EX7061 | C79: =_xlfn.XLOOKUP(A79,CrossRef!N:N,CrossRef!D:D,"",0) | D79: =_xlfn.XLOOKUP(A79,CrossRef!N:N,CrossRef!C:C,"",0) | E79: =LEFT(M79,3) -> HCM | F79: =_xlfn.TEXTAFTER(J79,"-") -> IMAT-BOOM-BOOM | G79: M350 | H79: M11D | I79: EX7061 | J79: EXBH042-IMAT-BOOM-BOOM | K79: HITACHI | L79: EX3600-6 | M79: HCM18M00P00001043 | N79: Suspended | O79: MEO | P79: Z01 | Q79: Inactive | R79: 100373 | S79: CW | T79: 001028 | V79: 18000H BOOM CHANGE | W79: 18000 | X79: 77111 | Y79: A/6268/1 | Z79: 65494 | AA79: 0 | AB79: 343500 | AD79: 4413685 | AE79: 43132 | AF79: 38418 | AG79: -9076 | AH79: -0.50422222 | AI79: 0 | AJ79: 46225 | AK79: 47330 | AL79: -1105 | AO79: =E79&F79&U79 -> HCMIMAT-BOOM-BOOM | AP79: =_xlfn.XLOOKUP(AO79,CrossRef!N:N,CrossRef!A:A,"NOT FOUND",0) -> NOT FOUND | AQ79: =IFERROR(_xlfn.XLOOKUP(AO79,CrossRef!$N:$N,CrossRef!$E:$E,"Not Found"),"-") -> Not Found | AR79: =IFERROR(_xlfn.XLOOKUP(AO79,CrossRef!$N:$N,CrossRef!$G:$G,"Not Found"),"-") -> Not Found | AS79: =IFERROR(_xlfn.XLOOKUP(AO79,CrossRef!$N:$N,CrossRef!$H:$H,"Not Found"),"-") -> Not Found
A80: =E80&F80&U80 -> APXDRIV-WHGPLHF | B80: =I80&D80&C80 -> TD66604006LF | C80: =_xlfn.XLOOKUP(A80,CrossRef!N:N,CrossRef!D:D,"",0) -> LF | D80: =_xlfn.XLOOKUP(A80,CrossRef!N:N,CrossRef!C:C,"",0) -> 4006 | E80: =LEFT(M80,3) -> APX | F80: =_xlfn.TEXTAFTER(J80,"-") -> DRIV-WHGP | G80: M776 | H80: M11E | I80: TD6660 | J80: TKHL185-DRIV-WHGP | K80: CATERPILLAR | L80: 785C | M80: APX01623 | N80: Active | O80: MEH | P80: Z01 | Q80: Active | R80: 193929 | S80: CH | T80: 001020 | U80: LHF | V80: 20000H BRAKE & WHEEL SPINDLE CHANGE LHF | W80: 20000 | X80: 154735 | Y80: A/24900/1 | Z80: 56323.68 | AA80: 11.74 | AB80: 37793.87 | AD80: 4639848 | AF80: 27408 | AG80: -8915.68 | AH80: -0.445784 | AI80: -759.4276 | AJ80: 45465.572 | AK80: 45602 | AL80: -137 | AM80: 49009.66 | AN80: 1.080083 | AO80: =E80&F80&U80 -> APXDRIV-WHGPLHF | AP80: =_xlfn.XLOOKUP(AO80,CrossRef!N:N,CrossRef!A:A,"NOT FOUND",0) -> APX4006LF | AQ80: =IFERROR(_xlfn.XLOOKUP(AO80,CrossRef!$N:$N,CrossRef!$E:$E,"Not Found"),"-") -> 785C | AR80: =IFERROR(_xlfn.XLOOKUP(AO80,CrossRef!$N:$N,CrossRef!$G:$G,"Not Found"),"-") -> 4006 - WHEEL & BRAKE ASSEMBLY | AS80: =IFERROR(_xlfn.XLOOKUP(AO80,CrossRef!$N:$N,CrossRef!$H:$H,"Not Found"),"-") -> LF - LEFT FRONT
A81: =E81&F81&U81 -> APXDRIV-WHGPRHF | B81: =I81&D81&C81 -> TD66604008RF | C81: =_xlfn.XLOOKUP(A81,CrossRef!N:N,CrossRef!D:D,"",0) -> RF | D81: =_xlfn.XLOOKUP(A81,CrossRef!N:N,CrossRef!C:C,"",0) -> 4008 | E81: =LEFT(M81,3) -> APX | F81: =_xlfn.TEXTAFTER(J81,"-") -> DRIV-WHGP | G81: M776 | H81: M11E | I81: TD6660 | J81: TKHL185-DRIV-WHGP | K81: CATERPILLAR | L81: 785C | M81: APX01623 | N81: Active | O81: MEH | P81: Z01 | Q81: Active | R81: 193930 | S81: CH | T81: 001020 | U81: RHF | V81: 20000H BRAKE & WHEEL SPINDLE CHANGE RHF | W81: 20000 | X81: 154736 | Y81: A/24900/1 | Z81: 56323.68 | AA81: 11.74 | AB81: 37793.87 | AD81: 4639849 | AF81: 27408 | AG81: -8915.68 | AH81: -0.445784 | AI81: -759.4276 | AJ81: 45465.572 | AK81: 45602 | AL81: -137 | AM81: 49009.66 | AN81: 1.080083 | AO81: =E81&F81&U81 -> APXDRIV-WHGPRHF | AP81: =_xlfn.XLOOKUP(AO81,CrossRef!N:N,CrossRef!A:A,"NOT FOUND",0) -> APX4008RF | AQ81: =IFERROR(_xlfn.XLOOKUP(AO81,CrossRef!$N:$N,CrossRef!$E:$E,"Not Found"),"-") -> 785C | AR81: =IFERROR(_xlfn.XLOOKUP(AO81,CrossRef!$N:$N,CrossRef!$G:$G,"Not Found"),"-") -> 4008 - FINAL DRIVE, BRAKE & WHEEL | AS81: =IFERROR(_xlfn.XLOOKUP(AO81,CrossRef!$N:$N,CrossRef!$H:$H,"Not Found"),"-") -> RF - RIGHT FRONT
A82: =E82&F82&U82 -> 4ARDRIV-DIFF | B82: =I82&D82&C82 -> QTD29325800 | C82: =_xlfn.XLOOKUP(A82,CrossRef!N:N,CrossRef!D:D,"",0) -> 00 | D82: =_xlfn.XLOOKUP(A82,CrossRef!N:N,CrossRef!C:C,"",0) -> 3258 | E82: =LEFT(M82,3) -> 4AR | F82: =_xlfn.TEXTAFTER(J82,"-") -> DRIV-DIFF | G82: M350 | H82: M11D | I82: QTD29 | J82: TKHL118-DRIV-DIFF | K82: CATERPILLAR | L82: 793C | M82: 4AR00316 | N82: Active | O82: MEC | P82: Z01 | Q82: Active | R82: 100219 | S82: CH | T82: 001003 | V82: 16500H DIFFERENTIAL CHANGE | W82: 16500 | X82: 76993 | Y82: A/5633/1 | Z82: 146656 | AA82: 13.35 | AB82: 63540.55 | AD82: 4795451 | AE82: 43898 | AF82: 121367 | AG82: -8789 | AH82: -0.53266667 | AI82: -658.35206 | AJ82: 45566.648 | AK82: 46059 | AL82: -493 | AM82: 144439.9 | AO82: =E82&F82&U82 -> 4ARDRIV-DIFF | AP82: =_xlfn.XLOOKUP(AO82,CrossRef!N:N,CrossRef!A:A,"NOT FOUND",0) -> 4AR325800 | AQ82: =IFERROR(_xlfn.XLOOKUP(AO82,CrossRef!$N:$N,CrossRef!$E:$E,"Not Found"),"-") -> 793C | AR82: =IFERROR(_xlfn.XLOOKUP(AO82,CrossRef!$N:$N,CrossRef!$G:$G,"Not Found"),"-") -> 3258 - DIFFERENTIAL | AS82: =IFERROR(_xlfn.XLOOKUP(AO82,CrossRef!$N:$N,CrossRef!$H:$H,"Not Found"),"-") -> 00 - (NONE)
A83: =E83&F83&U83 -> DHJHYSY-CYHY-CYBLLH | B83: =I83&D83&C83 -> EX7094 | C83: =_xlfn.XLOOKUP(A83,CrossRef!N:N,CrossRef!D:D,"",0) | D83: =_xlfn.XLOOKUP(A83,CrossRef!N:N,CrossRef!C:C,"",0) | E83: =MID(M83,FIND("DH",M83),3) -> DHJ | F83: =_xlfn.TEXTAFTER(J83,"-") -> HYSY-CYHY-CYBL | G83: M776 | H83: M11E | I83: EX7094 | J83: EXBH055-HYSY-CYHY-CYBL | K83: CATERPILLAR | L83: 6040 | M83: 170120 (DHJ40120) | N83: Active | O83: MEO | P83: Z01 | Q83: Active | R83: 112019 | S83: CC | T83: 001023 | U83: LH | V83: 12000H BOOM CYLINDER CHANGE LH | W83: 12000 | X83: 86144 | Y83: A/8143/1 | Z83: 70079 | AA83: 2.64 | AB83: 96075.11 | AD83: 4190754 | AE83: 45301 | AF83: 61763 | AG83: 3684 | AH83: 0.307 | AI83: 1395.4545 | AJ83: 47620.455 | AK83: 47372 | AL83: 248 | AM83: 73107.08 | AN83: 0.94534 | AO83: =E83&F83&U83 -> DHJHYSY-CYHY-CYBLLH | AP83: =_xlfn.XLOOKUP(AO83,CrossRef!N:N,CrossRef!A:A,"NOT FOUND",0) -> NOT FOUND | AQ83: =IFERROR(_xlfn.XLOOKUP(AO83,CrossRef!$N:$N,CrossRef!$E:$E,"Not Found"),"-") -> Not Found | AR83: =IFERROR(_xlfn.XLOOKUP(AO83,CrossRef!$N:$N,CrossRef!$G:$G,"Not Found"),"-") -> Not Found | AS83: =IFERROR(_xlfn.XLOOKUP(AO83,CrossRef!$N:$N,CrossRef!$H:$H,"Not Found"),"-") -> Not Found
A84: =E84&F84&U84 -> DHJHYSY-CYHY-CYBRRH | B84: =I84&D84&C84 -> EX7094 | C84: =_xlfn.XLOOKUP(A84,CrossRef!N:N,CrossRef!D:D,"",0) | D84: =_xlfn.XLOOKUP(A84,CrossRef!N:N,CrossRef!C:C,"",0) | E84: =MID(M84,FIND("DH",M84),3) -> DHJ | F84: =_xlfn.TEXTAFTER(J84,"-") -> HYSY-CYHY-CYBR | G84: M776 | H84: M11E | I84: EX7094 | J84: EXBH055-HYSY-CYHY-CYBR | K84: CATERPILLAR | L84: 6040 | M84: 170120 (DHJ40120) | N84: Active | O84: MEO | P84: Z01 | Q84: Active | R84: 112018 | S84: CC | T84: 001023 | U84: RH | V84: 12000H BOOM CYLINDER CHANGE RH | W84: 12000 | X84: 86143 | Y84: A/8143/1 | Z84: 70079 | AA84: 2.64 | AB84: 96075.11 | AD84: 4698401 | AE84: 45643 | AF84: 66090.84 | AG84: 8011.84 | AH84: 0.66765333 | AI84: 3034.7879 | AJ84: 49259.788 | AK84: 47689 | AL84: 1570 | AM84: 73943.96 | AN84: 0.65442667 | AO84: =E84&F84&U84 -> DHJHYSY-CYHY-CYBRRH | AP84: =_xlfn.XLOOKUP(AO84,CrossRef!N:N,CrossRef!A:A,"NOT FOUND",0) -> NOT FOUND | AQ84: =IFERROR(_xlfn.XLOOKUP(AO84,CrossRef!$N:$N,CrossRef!$E:$E,"Not Found"),"-") -> Not Found | AR84: =IFERROR(_xlfn.XLOOKUP(AO84,CrossRef!$N:$N,CrossRef!$G:$G,"Not Found"),"-") -> Not Found | AS84: =IFERROR(_xlfn.XLOOKUP(AO84,CrossRef!$N:$N,CrossRef!$H:$H,"Not Found"),"-") -> Not Found
A85: =E85&F85&U85 -> DHJHYSY-PUHY-PUM1POS.1 | B85: =I85&D85&C85 -> EX7094 | C85: =_xlfn.XLOOKUP(A85,CrossRef!N:N,CrossRef!D:D,"",0) | D85: =_xlfn.XLOOKUP(A85,CrossRef!N:N,CrossRef!C:C,"",0) | E85: =MID(M85,FIND("DH",M85),3) -> DHJ | F85: =_xlfn.TEXTAFTER(J85,"-") -> HYSY-PUHY-PUM1 | G85: M776 | H85: M11E | I85: EX7094 | J85: EXBH055-HYSY-PUHY-PUM1 | K85: CATERPILLAR | L85: 6040 | M85: 170120 (DHJ40120) | N85: Active | O85: MEO | P85: Z01 | Q85: Active | R85: 114583 | S85: CH | T85: 001007 | U85: POS.1 | V85: 12000H MAIN PUMP CHANGE POS.1 | W85: 12000 | X85: 87844 | Y85: A/7646/1 | Z85: 70079 | AA85: 2.64 | AB85: 60967.99 | AD85: 4190762 | AE85: 45526 | AF85: 63412.2 | AG85: 5333.2 | AH85: 0.44443333 | AI85: 2020.1515 | AJ85: 48245.152 | AK85: 47493 | AL85: 752 | AM85: 73426.52 | AN85: 0.83452667 | AO85: =E85&F85&U85 -> DHJHYSY-PUHY-PUM1POS.1 | AP85: =_xlfn.XLOOKUP(AO85,CrossRef!N:N,CrossRef!A:A,"NOT FOUND",0) -> NOT FOUND | AQ85: =IFERROR(_xlfn.XLOOKUP(AO85,CrossRef!$N:$N,CrossRef!$E:$E,"Not Found"),"-") -> Not Found | AR85: =IFERROR(_xlfn.XLOOKUP(AO85,CrossRef!$N:$N,CrossRef!$G:$G,"Not Found"),"-") -> Not Found | AS85: =IFERROR(_xlfn.XLOOKUP(AO85,CrossRef!$N:$N,CrossRef!$H:$H,"Not Found"),"-") -> Not Found
A86: =E86&F86&U86 -> DHJHYSY-PUHY-PUM2POS.2 | B86: =I86&D86&C86 -> EX7094 | C86: =_xlfn.XLOOKUP(A86,CrossRef!N:N,CrossRef!D:D,"",0) | D86: =_xlfn.XLOOKUP(A86,CrossRef!N:N,CrossRef!C:C,"",0) | E86: =MID(M86,FIND("DH",M86),3) -> DHJ | F86: =_xlfn.TEXTAFTER(J86,"-") -> HYSY-PUHY-PUM2 | G86: M776 | H86: M11E | I86: EX7094 | J86: EXBH055-HYSY-PUHY-PUM2 | K86: CATERPILLAR | L86: 6040 | M86: 170120 (DHJ40120) | N86: Active | O86: MEO | P86: Z01 | Q86: Active | R86: 114582 | S86: CH | T86: 001007 | U86: POS.2 | V86: 12000H MAIN PUMP CHANGE POS.2 | W86: 12000 | X86: 87843 | Y86: A/7650/1 | Z86: 70079 | AA86: 2.64 | AB86: 60967.99 | AD86: 4403981 | AE86: 45561 | AF86: 63412.2 | AG86: 5333.2 | AH86: 0.44443333 | AI86: 2020.1515 | AJ86: 48245.152 | AK86: 47493 | AL86: 752 | AM86: 73426.52 | AN86: 0.83452667 | AO86: =E86&F86&U86 -> DHJHYSY-PUHY-PUM2POS.2 | AP86: =_xlfn.XLOOKUP(AO86,CrossRef!N:N,CrossRef!A:A,"NOT FOUND",0) -> NOT FOUND | AQ86: =IFERROR(_xlfn.XLOOKUP(AO86,CrossRef!$N:$N,CrossRef!$E:$E,"Not Found"),"-") -> Not Found | AR86: =IFERROR(_xlfn.XLOOKUP(AO86,CrossRef!$N:$N,CrossRef!$G:$G,"Not Found"),"-") -> Not Found | AS86: =IFERROR(_xlfn.XLOOKUP(AO86,CrossRef!$N:$N,CrossRef!$H:$H,"Not Found"),"-") -> Not Found
A87: =E87&F87&U87 -> HCMBCKT | B87: =I87&D87&C87 -> EX7112 | C87: =_xlfn.XLOOKUP(A87,CrossRef!N:N,CrossRef!D:D,"",0) | D87: =_xlfn.XLOOKUP(A87,CrossRef!N:N,CrossRef!C:C,"",0) | E87: =LEFT(M87,3) -> HCM | F87: =_xlfn.TEXTAFTER(J87,"-") -> BCKT | G87: M215 | H87: M11L | I87: EX7112 | J87: EXBH001-BCKT | K87: HITACHI | L87: EX2600-6 | M87: HCMKBA90C00002088 | N87: Active | O87: MEF | P87: Z01 | Q87: Active | R87: 172025 | S87: CW | T87: 001030 | V87: 5000H BUCKET CHANGE | W87: 5000 | X87: 135724 | Y87: A/18527/1 | Z87: 36668.8 | AA87: 13.49 | AB87: 247510 | AD87: 4859581 | AE87: 45210 | AF87: 23190 | AG87: -8478.8 | AH87: -1.69576 | AI87: -628.52483 | AJ87: 45596.475 | AK87: 46174 | AL87: -578 | AM87: 35980.81 | AN87: 2.558162 | AO87: =E87&F87&U87 -> HCMBCKT | AP87: =_xlfn.XLOOKUP(AO87,CrossRef!N:N,CrossRef!A:A,"NOT FOUND",0) -> NOT FOUND | AQ87: =IFERROR(_xlfn.XLOOKUP(AO87,CrossRef!$N:$N,CrossRef!$E:$E,"Not Found"),"-") -> Not Found | AR87: =IFERROR(_xlfn.XLOOKUP(AO87,CrossRef!$N:$N,CrossRef!$G:$G,"Not Found"),"-") -> Not Found | AS87: =IFERROR(_xlfn.XLOOKUP(AO87,CrossRef!$N:$N,CrossRef!$H:$H,"Not Found"),"-") -> Not Found
A88: =E88&F88&U88 -> FDBHYSY-CYHYLH | B88: =I88&D88&C88 -> QTD235102LT | C88: =_xlfn.XLOOKUP(A88,CrossRef!N:N,CrossRef!D:D,"",0) -> LT | D88: =_xlfn.XLOOKUP(A88,CrossRef!N:N,CrossRef!C:C,"",0) -> 5102 | E88: =LEFT(M88,3) -> FDB | F88: =_xlfn.TEXTAFTER(J88,"-") -> HYSY-CYHY | G88: M350 | H88: M11D | I88: QTD23 | J88: TKHL114-HYSY-CYHY | K88: CATERPILLAR | L88: 793D | M88: FDB00173 | N88: Active | O88: MEC | P88: Z01 | Q88: Active | R88: 96748 | S88: CC | T88: 001044 | U88: LH | V88: 20000H HOIST CYLINDER CHANGE LH | W88: 20000 | X88: 78070 | Y88: A/6619/1 | Z88: 95814 | AA88: 12.78 | AB88: 20259.99 | AD88: 4447323 | AE88: 43867 | AF88: 67479 | AG88: -8335 | AH88: -0.41675 | AI88: -652.19092 | AJ88: 45572.809 | AK88: 45372 | AL88: 200 | AM88: 84912.66 | AN88: 0.871683 | AO88: =E88&F88&U88 -> FDBHYSY-CYHYLH | AP88: =_xlfn.XLOOKUP(AO88,CrossRef!N:N,CrossRef!A:A,"NOT FOUND",0) -> FDB5102LT | AQ88: =IFERROR(_xlfn.XLOOKUP(AO88,CrossRef!$N:$N,CrossRef!$E:$E,"Not Found"),"-") -> 793D | AR88: =IFERROR(_xlfn.XLOOKUP(AO88,CrossRef!$N:$N,CrossRef!$G:$G,"Not Found"),"-") -> 5102 - LIFT/HOIST CYLINDER | AS88: =IFERROR(_xlfn.XLOOKUP(AO88,CrossRef!$N:$N,CrossRef!$H:$H,"Not Found"),"-") -> LT - LEFT
A89: =E89&F89&U89 -> HCMUCRG-TCID-TCIRRH | B89: =I89&D89&C89 -> EX70614159RI | C89: =_xlfn.XLOOKUP(A89,CrossRef!N:N,CrossRef!D:D,"",0) -> RI | D89: =_xlfn.XLOOKUP(A89,CrossRef!N:N,CrossRef!C:C,"",0) -> 4159 | E89: =LEFT(M89,3) -> HCM | F89: =_xlfn.TEXTAFTER(J89,"-") -> UCRG-TCID-TCIR | G89: M350 | H89: M11D | I89: EX7061 | J89: EXBH042-UCRG-TCID-TCIR | K89: HITACHI | L89: EX3600-6 | M89: HCM18M00P00001043 | N89: Suspended | O89: MEO | P89: Z01 | Q89: Inactive | R89: 99974 | S89: CW | T89: 001033 | U89: RH | V89: 16000H IDLER CHANGE RH | W89: 16000 | X89: 76856 | Y89: A/6552/1 | Z89: 65494 | AA89: 0 | AB89: 72536.44 | AD89: 4123142 | AE89: 43342 | AF89: 41200 | AG89: -8294 | AH89: -0.518375 | AI89: 0 | AJ89: 46225 | AK89: 47204 | AL89: -979 | AO89: =E89&F89&U89 -> HCMUCRG-TCID-TCIRRH | AP89: =_xlfn.XLOOKUP(AO89,CrossRef!N:N,CrossRef!A:A,"NOT FOUND",0) -> HCM4159RI | AQ89: =IFERROR(_xlfn.XLOOKUP(AO89,CrossRef!$N:$N,CrossRef!$E:$E,"Not Found"),"-") -> EX1900-6BE | AR89: =IFERROR(_xlfn.XLOOKUP(AO89,CrossRef!$N:$N,CrossRef!$G:$G,"Not Found"),"-") -> 4159 - IDLER/IDLER WHEEL | AS89: =IFERROR(_xlfn.XLOOKUP(AO89,CrossRef!$N:$N,CrossRef!$H:$H,"Not Found"),"-") -> RI - RIGHT
A90: =E90&F90&U90 -> ATYHYSY-CYHYRH | B90: =I90&D90&C90 -> QTD365102RI | C90: =_xlfn.XLOOKUP(A90,CrossRef!N:N,CrossRef!D:D,"",0) -> RI | D90: =_xlfn.XLOOKUP(A90,CrossRef!N:N,CrossRef!C:C,"",0) -> 5102 | E90: =LEFT(M90,3) -> ATY | F90: =_xlfn.TEXTAFTER(J90,"-") -> HYSY-CYHY | G90: M350 | H90: M11D | I90: QTD36 | J90: TKHL121-HYSY-CYHY | K90: CATERPILLAR | L90: 793C | M90: ATY00550 | N90: Active | O90: MEC | P90: Z01 | Q90: Active | R90: 96773 | S90: CC | T90: 001044 | U90: RH | V90: 20000H HOIST CYLINDER CHANGE RH | W90: 20000 | X90: 74421 | Y90: A/6620/1 | Z90: 146948 | AA90: 10.62 | AB90: 20259.99 | AD90: 4320696 | AF90: 118838 | AG90: -8110 | AH90: -0.4055 | AI90: -763.65348 | AJ90: 45461.347 | AK90: 45223 | AL90: 238 | AM90: 136306.76 | AN90: 0.873438 | AO90: =E90&F90&U90 -> ATYHYSY-CYHYRH | AP90: =_xlfn.XLOOKUP(AO90,CrossRef!N:N,CrossRef!A:A,"NOT FOUND",0) -> ATY5102RI | AQ90: =IFERROR(_xlfn.XLOOKUP(AO90,CrossRef!$N:$N,CrossRef!$E:$E,"Not Found"),"-") -> 793C | AR90: =IFERROR(_xlfn.XLOOKUP(AO90,CrossRef!$N:$N,CrossRef!$G:$G,"Not Found"),"-") -> 5102 - LIFT/HOIST CYLINDER | AS90: =IFERROR(_xlfn.XLOOKUP(AO90,CrossRef!$N:$N,CrossRef!$H:$H,"Not Found"),"-") -> RI - RIGHT
A91: =E91&F91&U91 -> ATYHYSY-CYHYLH | B91: =I91&D91&C91 -> QTD365102LT | C91: =_xlfn.XLOOKUP(A91,CrossRef!N:N,CrossRef!D:D,"",0) -> LT | D91: =_xlfn.XLOOKUP(A91,CrossRef!N:N,CrossRef!C:C,"",0) -> 5102 | E91: =LEFT(M91,3) -> ATY | F91: =_xlfn.TEXTAFTER(J91,"-") -> HYSY-CYHY | G91: M350 | H91: M11D | I91: QTD36 | J91: TKHL121-HYSY-CYHY | K91: CATERPILLAR | L91: 793C | M91: ATY00550 | N91: Active | O91: MEC | P91: Z01 | Q91: Active | R91: 96774 | S91: CC | T91: 001044 | U91: LH | V91: 20000H HOIST CYLINDER CHANGE LH | W91: 20000 | X91: 78146 | Y91: A/6618/1 | Z91: 146948 | AA91: 10.62 | AB91: 20259.99 | AD91: 4383244 | AE91: 43799 | AF91: 118838.4 | AG91: -8109.6 | AH91: -0.40548 | AI91: -763.61582 | AJ91: 45461.384 | AK91: 45252 | AL91: 209 | AM91: 136614.74 | AN91: 0.888817 | AO91: =E91&F91&U91 -> ATYHYSY-CYHYLH | AP91: =_xlfn.XLOOKUP(AO91,CrossRef!N:N,CrossRef!A:A,"NOT FOUND",0) -> ATY5102LT | AQ91: =IFERROR(_xlfn.XLOOKUP(AO91,CrossRef!$N:$N,CrossRef!$E:$E,"Not Found"),"-") -> 793C | AR91: =IFERROR(_xlfn.XLOOKUP(AO91,CrossRef!$N:$N,CrossRef!$G:$G,"Not Found"),"-") -> 5102 - LIFT/HOIST CYLINDER | AS91: =IFERROR(_xlfn.XLOOKUP(AO91,CrossRef!$N:$N,CrossRef!$H:$H,"Not Found"),"-") -> LT - LEFT
A92: =E92&F92&U92 -> SSPSURE-SPSNRHF | B92: =I92&D92&C92 -> TD6313 | C92: =_xlfn.XLOOKUP(A92,CrossRef!N:N,CrossRef!D:D,"",0) | D92: =_xlfn.XLOOKUP(A92,CrossRef!N:N,CrossRef!C:C,"",0) | E92: =LEFT(M92,3) -> SSP | F92: =_xlfn.TEXTAFTER(J92,"-") -> SURE-SPSN | G92: M776 | H92: M11E | I92: TD6313 | J92: TKHL134-SURE-SPSN | K92: CATERPILLAR | L92: 793F | M92: SSP00879 | N92: Active | O92: MEO | P92: Z01 | Q92: Active | R92: 96943 | S92: CC | T92: 001027 | U92: RHF | V92: 24000H SUSPENSION CYLINDER CHANGE RHF | W92: 24000 | X92: 74567 | Y92: A/7793/1 | Z92: 71005 | AA92: 16.03 | AB92: 68000.45 | AD92: 4580208 | AE92: 43893 | AF92: 39332.6 | AG92: -7672.4 | AH92: -0.31968333 | AI92: -478.62757 | AJ92: 45746.372 | AK92: 45673 | AL92: 73 | AM92: 62156.44 | AN92: 0.95099333 | AO92: =E92&F92&U92 -> SSPSURE-SPSNRHF | AP92: =_xlfn.XLOOKUP(AO92,CrossRef!N:N,CrossRef!A:A,"NOT FOUND",0) -> NOT FOUND | AQ92: =IFERROR(_xlfn.XLOOKUP(AO92,CrossRef!$N:$N,CrossRef!$E:$E,"Not Found"),"-") -> Not Found | AR92: =IFERROR(_xlfn.XLOOKUP(AO92,CrossRef!$N:$N,CrossRef!$G:$G,"Not Found"),"-") -> Not Found | AS92: =IFERROR(_xlfn.XLOOKUP(AO92,CrossRef!$N:$N,CrossRef!$H:$H,"Not Found"),"-") -> Not Found
A93: =E93&F93&U93 -> BXYDRIV-DIFFRR | B93: =I93&D93&C93 -> LO15823258RE | C93: =_xlfn.XLOOKUP(A93,CrossRef!N:N,CrossRef!D:D,"",0) -> RE | D93: =_xlfn.XLOOKUP(A93,CrossRef!N:N,CrossRef!C:C,"",0) -> 3258 | E93: =LEFT(M93,3) -> BXY | F93: =_xlfn.TEXTAFTER(J93,"-") -> DRIV-DIFF | G93: M350 | H93: M11D | I93: LO1582 | J93: LOFE008-DRIV-DIFF | K93: CATERPILLAR | L93: 988H | M93: BXY00982 | N93: Active | O93: MEO | P93: Z01 | Q93: Active | R93: 167224 | S93: CH | T93: 001003 | U93: RR | V93: 14000HR DIFFERENTIAL CHANGE RR | W93: 14000 | X93: 131478 | Y93: A/6474/1 | Z93: 34951 | AA93: 2.58 | AB93: 22397.5 | AD93: 4246286 | AE93: 40369 | AF93: 13446 | AG93: -7505 | AH93: -0.53607143 | AI93: -2908.9147 | AJ93: 43316.085 | AK93: 44872 | AL93: -1556 | AM93: 31460.26 | AN93: 1.2867329 | AO93: =E93&F93&U93 -> BXYDRIV-DIFFRR | AP93: =_xlfn.XLOOKUP(AO93,CrossRef!N:N,CrossRef!A:A,"NOT FOUND",0) -> BXY3258RE | AQ93: =IFERROR(_xlfn.XLOOKUP(AO93,CrossRef!$N:$N,CrossRef!$E:$E,"Not Found"),"-") -> 988H | AR93: =IFERROR(_xlfn.XLOOKUP(AO93,CrossRef!$N:$N,CrossRef!$G:$G,"Not Found"),"-") -> 3258 - DIFFERENTIAL | AS93: =IFERROR(_xlfn.XLOOKUP(AO93,CrossRef!$N:$N,CrossRef!$H:$H,"Not Found"),"-") -> RE - REAR
A94: =E94&F94&U94 -> BXYDRIV-DIFFFR | B94: =I94&D94&C94 -> LO15823258FR | C94: =_xlfn.XLOOKUP(A94,CrossRef!N:N,CrossRef!D:D,"",0) -> FR | D94: =_xlfn.XLOOKUP(A94,CrossRef!N:N,CrossRef!C:C,"",0) -> 3258 | E94: =LEFT(M94,3) -> BXY | F94: =_xlfn.TEXTAFTER(J94,"-") -> DRIV-DIFF | G94: M350 | H94: M11D | I94: LO1582 | J94: LOFE008-DRIV-DIFF | K94: CATERPILLAR | L94: 988H | M94: BXY00982 | N94: Active | O94: MEO | P94: Z01 | Q94: Active | R94: 167225 | S94: CH | T94: 001003 | U94: FR | V94: 14000H DIFFERENTIAL CHANGE FR | W94: 14000 | X94: 131479 | Y94: A/6474/1 | Z94: 34951 | AA94: 2.58 | AB94: 22397.5 | AD94: 4246291 | AE94: 40369 | AF94: 13446 | AG94: -7505 | AH94: -0.53607143 | AI94: -2908.9147 | AJ94: 43316.085 | AK94: 44872 | AL94: -1556 | AM94: 31460.26 | AN94: 1.2867329 | AO94: =E94&F94&U94 -> BXYDRIV-DIFFFR | AP94: =_xlfn.XLOOKUP(AO94,CrossRef!N:N,CrossRef!A:A,"NOT FOUND",0) -> BXY3258FR | AQ94: =IFERROR(_xlfn.XLOOKUP(AO94,CrossRef!$N:$N,CrossRef!$E:$E,"Not Found"),"-") -> 988H | AR94: =IFERROR(_xlfn.XLOOKUP(AO94,CrossRef!$N:$N,CrossRef!$G:$G,"Not Found"),"-") -> 3258 - DIFFERENTIAL | AS94: =IFERROR(_xlfn.XLOOKUP(AO94,CrossRef!$N:$N,CrossRef!$H:$H,"Not Found"),"-") -> FR - FRONT
A95: =E95&F95&U95 -> BXYDRIV-FIDVRHR | B95: =I95&D95&C95 -> LO15824050RR | C95: =_xlfn.XLOOKUP(A95,CrossRef!N:N,CrossRef!D:D,"",0) -> RR | D95: =_xlfn.XLOOKUP(A95,CrossRef!N:N,CrossRef!C:C,"",0) -> 4050 | E95: =LEFT(M95,3) -> BXY | F95: =_xlfn.TEXTAFTER(J95,"-") -> DRIV-FIDV | G95: M350 | H95: M11D | I95: LO1582 | J95: LOFE008-DRIV-FIDV | K95: CATERPILLAR | L95: 988H | M95: BXY00982 | N95: Active | O95: MEO | P95: Z01 | Q95: Active | R95: 167180 | S95: CH | T95: 001019 | U95: RHR | V95: 14000H WHEEL END CHANGE RHR | W95: 14000 | X95: 131474 | Y95: A/6359/1 | Z95: 34951 | AA95: 2.58 | AB95: 21118.53 | AD95: 4246088 | AE95: 40369 | AF95: 13446 | AG95: -7505 | AH95: -0.53607143 | AI95: -2908.9147 | AJ95: 43316.085 | AK95: 44872 | AL95: -1556 | AM95: 31460.26 | AN95: 1.2867329 | AO95: =E95&F95&U95 -> BXYDRIV-FIDVRHR | AP95: =_xlfn.XLOOKUP(AO95,CrossRef!N:N,CrossRef!A:A,"NOT FOUND",0) -> BXY4050RR | AQ95: =IFERROR(_xlfn.XLOOKUP(AO95,CrossRef!$N:$N,CrossRef!$E:$E,"Not Found"),"-") -> 988H | AR95: =IFERROR(_xlfn.XLOOKUP(AO95,CrossRef!$N:$N,CrossRef!$G:$G,"Not Found"),"-") -> 4050 - FINAL DRIVE | AS95: =IFERROR(_xlfn.XLOOKUP(AO95,CrossRef!$N:$N,CrossRef!$H:$H,"Not Found"),"-") -> RR - RIGHT REAR
A96: =E96&F96&U96 -> BXYDRIV-FIDVLHR | B96: =I96&D96&C96 -> LO15824050LR | C96: =_xlfn.XLOOKUP(A96,CrossRef!N:N,CrossRef!D:D,"",0) -> LR | D96: =_xlfn.XLOOKUP(A96,CrossRef!N:N,CrossRef!C:C,"",0) -> 4050 | E96: =LEFT(M96,3) -> BXY | F96: =_xlfn.TEXTAFTER(J96,"-") -> DRIV-FIDV | G96: M350 | H96: M11D | I96: LO1582 | J96: LOFE008-DRIV-FIDV | K96: CATERPILLAR | L96: 988H | M96: BXY00982 | N96: Active | O96: MEO | P96: Z01 | Q96: Active | R96: 167221 | S96: CH | T96: 001019 | U96: LHR | V96: 14000H WHEEL END CHANGE LHR | W96: 14000 | X96: 131475 | Y96: A/6359/1 | Z96: 34951 | AA96: 2.58 | AB96: 21118.53 | AD96: 4246098 | AE96: 40369 | AF96: 13446 | AG96: -7505 | AH96: -0.53607143 | AI96: -2908.9147 | AJ96: 43316.085 | AK96: 44872 | AL96: -1556 | AM96: 31460.26 | AN96: 1.2867329 | AO96: =E96&F96&U96 -> BXYDRIV-FIDVLHR | AP96: =_xlfn.XLOOKUP(AO96,CrossRef!N:N,CrossRef!A:A,"NOT FOUND",0) -> BXY4050LR | AQ96: =IFERROR(_xlfn.XLOOKUP(AO96,CrossRef!$N:$N,CrossRef!$E:$E,"Not Found"),"-") -> 988H | AR96: =IFERROR(_xlfn.XLOOKUP(AO96,CrossRef!$N:$N,CrossRef!$G:$G,"Not Found"),"-") -> 4050 - FINAL DRIVE | AS96: =IFERROR(_xlfn.XLOOKUP(AO96,CrossRef!$N:$N,CrossRef!$H:$H,"Not Found"),"-") -> LR - LEFT REAR
A97: =E97&F97&U97 -> BXYDRIV-FIDVRHF | B97: =I97&D97&C97 -> LO15824050RF | C97: =_xlfn.XLOOKUP(A97,CrossRef!N:N,CrossRef!D:D,"",0) -> RF | D97: =_xlfn.XLOOKUP(A97,CrossRef!N:N,CrossRef!C:C,"",0) -> 4050 | E97: =LEFT(M97,3) -> BXY | F97: =_xlfn.TEXTAFTER(J97,"-") -> DRIV-FIDV | G97: M350 | H97: M11D | I97: LO1582 | J97: LOFE008-DRIV-FIDV | K97: CATERPILLAR | L97: 988H | M97: BXY00982 | N97: Active | O97: MEO | P97: Z01 | Q97: Active | R97: 167222 | S97: CH | T97: 001019 | U97: RHF | V97: 14000H WHEEL END CHANGE RHF | W97: 14000 | X97: 131476 | Y97: A/6359/1 | Z97: 34951 | AA97: 2.58 | AB97: 21118.53 | AD97: 4246280 | AE97: 40369 | AF97: 13446 | AG97: -7505 | AH97: -0.53607143 | AI97: -2908.9147 | AJ97: 43316.085 | AK97: 44872 | AL97: -1556 | AM97: 31460.26 | AN97: 1.2867329 | AO97: =E97&F97&U97 -> BXYDRIV-FIDVRHF | AP97: =_xlfn.XLOOKUP(AO97,CrossRef!N:N,CrossRef!A:A,"NOT FOUND",0) -> BXY4050RF | AQ97: =IFERROR(_xlfn.XLOOKUP(AO97,CrossRef!$N:$N,CrossRef!$E:$E,"Not Found"),"-") -> 988H | AR97: =IFERROR(_xlfn.XLOOKUP(AO97,CrossRef!$N:$N,CrossRef!$G:$G,"Not Found"),"-") -> 4050 - FINAL DRIVE | AS97: =IFERROR(_xlfn.XLOOKUP(AO97,CrossRef!$N:$N,CrossRef!$H:$H,"Not Found"),"-") -> RF - RIGHT FRONT
A98: =E98&F98&U98 -> BXYDRIV-FIDVLHF | B98: =I98&D98&C98 -> LO15824050LF | C98: =_xlfn.XLOOKUP(A98,CrossRef!N:N,CrossRef!D:D,"",0) -> LF | D98: =_xlfn.XLOOKUP(A98,CrossRef!N:N,CrossRef!C:C,"",0) -> 4050 | E98: =LEFT(M98,3) -> BXY | F98: =_xlfn.TEXTAFTER(J98,"-") -> DRIV-FIDV | G98: M350 | H98: M11D | I98: LO1582 | J98: LOFE008-DRIV-FIDV | K98: CATERPILLAR | L98: 988H | M98: BXY00982 | N98: Active | O98: MEO | P98: Z01 | Q98: Active | R98: 167223 | S98: CH | T98: 001019 | U98: LHF | V98: 14000H WHEEL END CHANGE LHF | W98: 14000 | X98: 131477 | Y98: A/6359/1 | Z98: 34951 | AA98: 2.58 | AB98: 21118.53 | AD98: 4246284 | AE98: 40369 | AF98: 13446 | AG98: -7505 | AH98: -0.53607143 | AI98: -2908.9147 | AJ98: 43316.085 | AK98: 44872 | AL98: -1556 | AM98: 31460.26 | AN98: 1.2867329 | AO98: =E98&F98&U98 -> BXYDRIV-FIDVLHF | AP98: =_xlfn.XLOOKUP(AO98,CrossRef!N:N,CrossRef!A:A,"NOT FOUND",0) -> BXY4050LF | AQ98: =IFERROR(_xlfn.XLOOKUP(AO98,CrossRef!$N:$N,CrossRef!$E:$E,"Not Found"),"-") -> 988H | AR98: =IFERROR(_xlfn.XLOOKUP(AO98,CrossRef!$N:$N,CrossRef!$G:$G,"Not Found"),"-") -> 4050 - FINAL DRIVE | AS98: =IFERROR(_xlfn.XLOOKUP(AO98,CrossRef!$N:$N,CrossRef!$H:$H,"Not Found"),"-") -> LF - LEFT FRONT
A99: =E99&F99&U99 -> FDBDRIV-TQCV | B99: =I99&D99&C99 -> QTD27310100 | C99: =_xlfn.XLOOKUP(A99,CrossRef!N:N,CrossRef!D:D,"",0) -> 00 | D99: =_xlfn.XLOOKUP(A99,CrossRef!N:N,CrossRef!C:C,"",0) -> 3101 | E99: =LEFT(M99,3) -> FDB | F99: =_xlfn.TEXTAFTER(J99,"-") -> DRIV-TQCV | G99: M350 | H99: M11D | I99: QTD27 | J99: TKHL116-DRIV-TQCV | K99: CATERPILLAR | L99: 793D | M99: FDB00388 | N99: Active | O99: MEC | P99: Z01 | Q99: Active | R99: 99958 | S99: CH | T99: 001015 | V99: 15400H TORQUE CONVERTER CHANGE | W99: 15400 | X99: 76845 | Y99: A/5700/1 | Z99: 92692 | AA99: 11.79 | AB99: 53050.69 | AD99: 4441767 | AE99: 44134 | AF99: 69825 | AG99: -7467 | AH99: -0.48487013 | AI99: -633.33333 | AJ99: 45591.667 | AK99: 45422 | AL99: 169 | AM99: 83224.63 | AO99: =E99&F99&U99 -> FDBDRIV-TQCV | AP99: =_xlfn.XLOOKUP(AO99,CrossRef!N:N,CrossRef!A:A,"NOT FOUND",0) -> FDB310100 | AQ99: =IFERROR(_xlfn.XLOOKUP(AO99,CrossRef!$N:$N,CrossRef!$E:$E,"Not Found"),"-") -> 793D | AR99: =IFERROR(_xlfn.XLOOKUP(AO99,CrossRef!$N:$N,CrossRef!$G:$G,"Not Found"),"-") -> 3101 - TORQUE CONVERTER | AS99: =IFERROR(_xlfn.XLOOKUP(AO99,CrossRef!$N:$N,CrossRef!$H:$H,"Not Found"),"-") -> 00 - (NONE)
A100: =E100&F100&U100 -> MSYSURE-SPSNRHF | B100: =I100&D100&C100 -> TD66637201RF | C100: =_xlfn.XLOOKUP(A100,CrossRef!N:N,CrossRef!D:D,"",0) -> RF | D100: =_xlfn.XLOOKUP(A100,CrossRef!N:N,CrossRef!C:C,"",0) -> 7201 | E100: =LEFT(M100,3) -> MSY | F100: =_xlfn.TEXTAFTER(J100,"-") -> SURE-SPSN | G100: M776 | H100: M11E | I100: TD6663 | J100: TKHL188-SURE-SPSN | K100: CATERPILLAR | L100: 785D | M100: MSY00245 | N100: Active | O100: MEH | P100: Z01 | Q100: Active | R100: 193975 | S100: CC | T100: 001027 | U100: RHF | V100: 20000H SUSPENSION CYLINDER CHANGE RHF | W100: 20000 | X100: 154812 | Y100: A/24914/1 | Z100: 60760.61 | AA100: 13.98 | AB100: 44244.78 | AD100: 4642562 | AF100: 33420 | AG100: -7340.61 | AH100: -0.3670305 | AI100: -525.0794 | AJ100: 45699.921 | AK100: 45669 | AL100: 30 | AM100: 52987.73 | AN100: 0.9783865 | AO100: =E100&F100&U100 -> MSYSURE-SPSNRHF | AP100: =_xlfn.XLOOKUP(AO100,CrossRef!N:N,CrossRef!A:A,"NOT FOUND",0) -> MSY7201RF | AQ100: =IFERROR(_xlfn.XLOOKUP(AO100,CrossRef!$N:$N,CrossRef!$E:$E,"Not Found"),"-") -> 785D | AR100: =IFERROR(_xlfn.XLOOKUP(AO100,CrossRef!$N:$N,CrossRef!$G:$G,"Not Found"),"-") -> 7201 - SUSPENSION CYLINDER | AS100: =IFERROR(_xlfn.XLOOKUP(AO100,CrossRef!$N:$N,CrossRef!$H:$H,"Not Found"),"-") -> RF - RIGHT FRONT
...

Sheet AMT
A1: BULK UPLOAD CONCAT | B1: Mod Code | C1: Comp Code | D1: Asset | E1: Serial Prefix | G1: Branch | H1: Task Counter | I1: Site | J1: Fleet | K1: Model | L1: Equipment | M1: Component Code | N1: Modifier Code | O1: Frequency | P1: Life To Date | Q1: Strategy Date | R1: Primary Part Number | S1: Next Part Classification | T1: Next Part Number Required | U1: Sales Status | V1: PO Number | W1: Comments | X1: Serial Number | Y1: Value | Z1: ST Description | AA1: Strategy Usage | AB1: Customer | AC1: Task Type | AD1: Sales Responsibility | AE1: Life Remaining | AF1: LAO | AG1: NEO Predicted Change Date | AH1: NEO Next Planned WO Execution Date | AI1: NEO Upload | AJ1: AMT Lookup Key | AK1: MacMahon Functional Location | AL1: MacMahon Position Code | AM1: MacMahon Maintenance Item Desc
A2: =D2&C2&B2 -> TD6342100000 | B2: =LEFT(N2,FIND(" ",N2)-1) -> 00 | C2: =LEFT(M2,4) -> 1000 | D2: =LEFT(L2,FIND(" ",L2)-1) -> TD6342 | E2: =MID(X2,2,3) -> SSP | G2: WA - Macmahon | H2: 0 - (NONE) | I2: Macmahon-Tropicana | J2: Macmahon-Tropicana-Trucks | K2: 793F | L2: TD6342 - SSP01033 | M2: 1000 - ENGINE | N2: 00 - (NONE) | O2: 26000 | P2: 20631.183 | Q2: 46285 | R2: 5632134X | S2: CUSTOMER REBUILD | T2: 3659319X | U2: Unknown | W2: NH- Per Customer Forecast March26;Per CSM Forecast Jan 26 - TRO;Per CSM Forecast Nov 25 - TRO; Per CSM Forecast Sep 25 - TRO;Per CSM Forecast July 25 - TRO; | X2: 0SSP01033 | Y2: 641496.86 | Z2: 1000.00.RB.0 ENGINE | AA2: 45836.682 | AB2: MACMAHON CONTRACTORS PTY LTD | AC2: RB - Rebuild Workorder | AD2: J. Power | AE2: 5368.8168 | AF2: =_xlfn.XLOOKUP(A2,Macmahon!B:B,Macmahon!AE:AE,"",0) -> 46116 | AG2: =_xlfn.XLOOKUP(A2,Macmahon!B:B,Macmahon!AJ:AJ,"",0) -> 47136.752 | AH2: =_xlfn.XLOOKUP(A2,Macmahon!B:B,Macmahon!AK:AK,"",0) -> 46952 | AI2: =IF(AG2=0,AH2,IF(AH2=0,AG2,MIN(AG2,AH2))) -> 46952 | AJ2: =E2&C2&B2 -> SSP100000 | AK2: =IFERROR(_xlfn.XLOOKUP(AJ2,CrossRef!$A:$A,CrossRef!$J:$J,"Not Found"),"-") -> TKHL174-ENGI | AL2: =IFERROR(_xlfn.XLOOKUP(AJ2,CrossRef!$A:$A,CrossRef!$K:$K,"Not Found"),"-") -> 0 | AM2: =IFERROR(_xlfn.XLOOKUP(AJ2,CrossRef!$A:$A,CrossRef!$L:$L,"Not Found"),"-") -> 22000H ENGINE CHANGE
A3: =D3&C3&B3 -> TD6345100000 | B3: =LEFT(N3,FIND(" ",N3)-1) -> 00 | C3: =LEFT(M3,4) -> 1000 | D3: =LEFT(L3,FIND(" ",L3)-1) -> TD6345 | E3: =MID(X3,2,3) -> SSP | G3: WA - Macmahon | H3: 0 - (NONE) | I3: Macmahon-Tropicana | J3: Macmahon-Tropicana-Trucks | K3: 793F | L3: TD6345 - SSP01044 | M3: 1000 - ENGINE | N3: 00 - (NONE) | O3: 26000 | P3: 6078.8639 | Q3: 47147 | R3: 5632134X | S3: CUSTOMER REBUILD | T3: 3659319X | U3: Unknown | W3: NH- Per CSM Forecast Feb26Per CSM Forecast Jan 26 - TRO;Per CSM Forecast Nov 25 - TRO; Per CSM Forecast Sep 25 - TRO;Per CSM Forecast July 25 - TRO; | X3: 0SSP01044 | Y3: 641496.86 | Z3: 1000.00.RB.0 ENGINE | AA3: 57394.042 | AB3: MACMAHON CONTRACTORS PTY LTD | AC3: RB - Rebuild Workorder | AD3: J. Power | AE3: 19921.136 | AF3: =_xlfn.XLOOKUP(A3,Macmahon!B:B,Macmahon!AE:AE,"",0) -> 45802 | AG3: =_xlfn.XLOOKUP(A3,Macmahon!B:B,Macmahon!AJ:AJ,"",0) -> 46557.693 | AH3: =_xlfn.XLOOKUP(A3,Macmahon!B:B,Macmahon!AK:AK,"",0) -> 46580 | AI3: =IF(AG3=0,AH3,IF(AH3=0,AG3,MIN(AG3,AH3))) -> 46557.693 | AJ3: =E3&C3&B3 -> SSP100000 | AK3: =IFERROR(_xlfn.XLOOKUP(AJ3,CrossRef!$A:$A,CrossRef!$J:$J,"Not Found"),"-") -> TKHL174-ENGI | AL3: =IFERROR(_xlfn.XLOOKUP(AJ3,CrossRef!$A:$A,CrossRef!$K:$K,"Not Found"),"-") -> 0 | AM3: =IFERROR(_xlfn.XLOOKUP(AJ3,CrossRef!$A:$A,CrossRef!$L:$L,"Not Found"),"-") -> 22000H ENGINE CHANGE
A4: =D4&C4&B4 -> TD6347100000 | B4: =LEFT(N4,FIND(" ",N4)-1) -> 00 | C4: =LEFT(M4,4) -> 1000 | D4: =LEFT(L4,FIND(" ",L4)-1) -> TD6347 | E4: =MID(X4,2,3) -> SSP | G4: WA - Macmahon | H4: 0 - (NONE) | I4: Macmahon-Tropicana | J4: Macmahon-Tropicana-Trucks | K4: 793F | L4: TD6347 - SSP01048 | M4: 1000 - ENGINE | N4: 00 - (NONE) | O4: 26000 | P4: 6631.1238 | Q4: 47472 | R4: 5632134X | S4: CUSTOMER REBUILD | T4: 3659319X | U4: Unknown | W4: NH- Per CSM Forecast Feb26Per CSM Forecast Jan 26 - TRO;Per CSM Forecast Nov 25 - TRO; Per CSM Forecast Sep 25 - TRO;Per CSM Forecast July 25 - TRO; Per CSM Forecast May 25 - TRO; Per CSM Forecast April 25 - TRO; Per CSM Forecast Mar 25 - TRO | X4: 0SSP01048 | Y4: 641496.86 | Z4: 1000.00.RB.0 ENGINE | AA4: 59927.998 | AB4: MACMAHON CONTRACTORS PTY LTD | AC4: RB - Rebuild Workorder | AD4: J. Power | AE4: 19368.876 | AF4: =_xlfn.XLOOKUP(A4,Macmahon!B:B,Macmahon!AE:AE,"",0) -> 45708 | AG4: =_xlfn.XLOOKUP(A4,Macmahon!B:B,Macmahon!AJ:AJ,"",0) -> 46563.594 | AH4: =_xlfn.XLOOKUP(A4,Macmahon!B:B,Macmahon!AK:AK,"",0) -> 46532 | AI4: =IF(AG4=0,AH4,IF(AH4=0,AG4,MIN(AG4,AH4))) -> 46532 | AJ4: =E4&C4&B4 -> SSP100000 | AK4: =IFERROR(_xlfn.XLOOKUP(AJ4,CrossRef!$A:$A,CrossRef!$J:$J,"Not Found"),"-") -> TKHL174-ENGI | AL4: =IFERROR(_xlfn.XLOOKUP(AJ4,CrossRef!$A:$A,CrossRef!$K:$K,"Not Found"),"-") -> 0 | AM4: =IFERROR(_xlfn.XLOOKUP(AJ4,CrossRef!$A:$A,CrossRef!$L:$L,"Not Found"),"-") -> 22000H ENGINE CHANGE
A5: =D5&C5&B5 -> TD6193100000 | B5: =LEFT(N5,FIND(" ",N5)-1) -> 00 | C5: =LEFT(M5,4) -> 1000 | D5: =LEFT(L5,FIND(" ",L5)-1) -> TD6193 | E5: =MID(X5,2,3) -> 6HK | G5: WA - Macmahon | H5: 0 - (NONE) | I5: Macmahon-Parked | J5: Macmahon-Parked-Parked | K5: 785B | L5: TD6193 - 6HK00734 | M5: 1000 - ENGINE | N5: 00 - (NONE) | O5: 20000 | P5: 10381.285 | Q5: 46187 | R5: 0R3982 | S5: 000 CAT REMAN | T5: 0R3982 | U5: Unknown | W5: Per CSM Forecast Jan 26 - TRO;Per CSM Forecast Nov 25 - TRO; Per CSM Forecast Sep 25 - TRO;Per CSM Forecast July 25 - TRO; Per CSM Forecast May 25 - TRO; Per CSM Forecast April 25 - TRO; Per CSM Forecast Mar 25 - TROPer CSM Forecast Feb 25 - TROPer CSM Forecast Dec 24 - TRO; Per CSM Forecast Nov 24 - TroPer CSM Forecast April 2024 TRO; | X5: 06HK00734 | Y5: 417452.69 | Z5: 1000.00.RB.0 ENGINE | AA5: 72254.261 | AB5: MACMAHON CONTRACTORS PTY LTD | AC5: RB - Rebuild Workorder | AE5: 9618.7148 | AF5: =_xlfn.XLOOKUP(A5,Macmahon!B:B,Macmahon!AE:AE,"",0) -> 45273 | AG5: =_xlfn.XLOOKUP(A5,Macmahon!B:B,Macmahon!AJ:AJ,"",0) -> 46781.834 | AH5: =_xlfn.XLOOKUP(A5,Macmahon!B:B,Macmahon!AK:AK,"",0) -> 0 | AI5: =IF(AG5=0,AH5,IF(AH5=0,AG5,MIN(AG5,AH5))) -> 46781.834 | AJ5: =E5&C5&B5 -> 6HK100000 | AK5: =IFERROR(_xlfn.XLOOKUP(AJ5,CrossRef!$A:$A,CrossRef!$J:$J,"Not Found"),"-") -> TKHL004-ENGI | AL5: =IFERROR(_xlfn.XLOOKUP(AJ5,CrossRef!$A:$A,CrossRef!$K:$K,"Not Found"),"-") -> 0 | AM5: =IFERROR(_xlfn.XLOOKUP(AJ5,CrossRef!$A:$A,CrossRef!$L:$L,"Not Found"),"-") -> 20000H ENGINE CHANGE
A6: =D6&C6&B6 -> TD2403100000 | B6: =LEFT(N6,FIND(" ",N6)-1) -> 00 | C6: =LEFT(M6,4) -> 1000 | D6: =LEFT(L6,FIND(" ",L6)-1) -> TD2403 | E6: =MID(X6,2,3) -> AGC | G6: WA - Macmahon | H6: 0 - (NONE) | I6: Macmahon-Telfer | J6: Macmahon-Telfer-Trucks | K6: 777D | L6: TD2403 - AGC00292 | M6: 1000 - ENGINE | N6: 00 - (NONE) | O6: 20000 | P6: 4920.6069 | Q6: 46290 | R6: 0R3981 | S6: 000 CAT REMAN | T6: 0R3981 | U6: Unknown | W6: NH - CF May26-:NH- Per Customer Forecast March26;Per CSM Forecast Jan 26 - TRO;Per CSM Forecast Nov 25 - TRO; Per CSM Forecast Sep 25 - TRO;Per CSM Forecast July 25 - TRO; Per CSM Forecast May 25 - TRO; Per CSM Forecast April 25 - TRO; Per CSM Forecast Mar 25 - TROPer CSM Forecast Dec 24 - TRO; Per CSM Forecast Nov 24 - Tro | X6: 0AGC00292 | Y6: 301026.68 | Z6: 1000.00.RB.0 ENGINE | AA6: 41804.439 | AB6: MACMAHON CONTRACTORS PTY LTD | AC6: RB - Rebuild Workorder | AE6: 15079.393 | AF6: =_xlfn.XLOOKUP(A6,Macmahon!B:B,Macmahon!AE:AE,"",0) -> 44973 | AG6: =_xlfn.XLOOKUP(A6,Macmahon!B:B,Macmahon!AJ:AJ,"",0) -> 50534.333 | AH6: =_xlfn.XLOOKUP(A6,Macmahon!B:B,Macmahon!AK:AK,"",0) -> 46290 | AI6: =IF(AG6=0,AH6,IF(AH6=0,AG6,MIN(AG6,AH6))) -> 46290 | AJ6: =E6&C6&B6 -> AGC100000 | AK6: =IFERROR(_xlfn.XLOOKUP(AJ6,CrossRef!$A:$A,CrossRef!$J:$J,"Not Found"),"-") -> TKHL018-ENGI | AL6: =IFERROR(_xlfn.XLOOKUP(AJ6,CrossRef!$A:$A,CrossRef!$K:$K,"Not Found"),"-") -> 0 | AM6: =IFERROR(_xlfn.XLOOKUP(AJ6,CrossRef!$A:$A,CrossRef!$L:$L,"Not Found"),"-") -> 20000H ENGINE CHANGE
A7: =D7&C7&B7 -> TD2405100000 | B7: =LEFT(N7,FIND(" ",N7)-1) -> 00 | C7: =LEFT(M7,4) -> 1000 | D7: =LEFT(L7,FIND(" ",L7)-1) -> TD2405 | E7: =MID(X7,2,3) -> AGC | G7: WA - Macmahon | H7: 0 - (NONE) | I7: Macmahon-Telfer | J7: Macmahon-Telfer-Trucks | K7: 777D | L7: TD2405 - AGC01022 | M7: 1000 - ENGINE | N7: 00 - (NONE) | O7: 20000 | P7: 7591.0556 | Q7: 46238 | R7: 0R3981 | S7: 000 CAT REMAN | T7: 0R3981 | U7: Unknown | W7: NH - CF May26-:NH- Per Customer Forecast March26;Per CSM Forecast Jan 26 - TRO;Per CSM Forecast Nov 25 - TRO; Per CSM Forecast Sep 25 - TRO;Per CSM Forecast July 25 - TRO; Per CSM Forecast May 25 - TRO; Per CSM Forecast April 25 - TRO; Per CSM Forecast Mar 25 - TROPer CSM Forecast Feb 25 - TROPer CSM Forecast Dec 24 - TRO; Per CSM Forecast Nov 24 - Tro | X7: 0AGC01022 | Y7: 301026.68 | Z7: 1000.00.RB.0 ENGINE | AA7: 63843.966 | AB7: MACMAHON CONTRACTORS PTY LTD | AC7: RB - Rebuild Workorder | AE7: 12408.944 | AF7: =_xlfn.XLOOKUP(A7,Macmahon!B:B,Macmahon!AE:AE,"",0) -> 44829 | AG7: =_xlfn.XLOOKUP(A7,Macmahon!B:B,Macmahon!AJ:AJ,"",0) -> 46225 | AH7: =_xlfn.XLOOKUP(A7,Macmahon!B:B,Macmahon!AK:AK,"",0) -> 48236 | AI7: =IF(AG7=0,AH7,IF(AH7=0,AG7,MIN(AG7,AH7))) -> 46225 | AJ7: =E7&C7&B7 -> AGC100000 | AK7: =IFERROR(_xlfn.XLOOKUP(AJ7,CrossRef!$A:$A,CrossRef!$J:$J,"Not Found"),"-") -> TKHL018-ENGI | AL7: =IFERROR(_xlfn.XLOOKUP(AJ7,CrossRef!$A:$A,CrossRef!$K:$K,"Not Found"),"-") -> 0 | AM7: =IFERROR(_xlfn.XLOOKUP(AJ7,CrossRef!$A:$A,CrossRef!$L:$L,"Not Found"),"-") -> 20000H ENGINE CHANGE
A8: =D8&C8&B8 -> TD2406100000 | B8: =LEFT(N8,FIND(" ",N8)-1) -> 00 | C8: =LEFT(M8,4) -> 1000 | D8: =LEFT(L8,FIND(" ",L8)-1) -> TD2406 | E8: =MID(X8,2,3) -> AGC | G8: WA - Macmahon | H8: 0 - (NONE) | I8: Macmahon-Telfer | J8: Macmahon-Telfer-Trucks | K8: 777D | L8: TD2406 - AGC01231 | M8: 1000 - ENGINE | N8: 00 - (NONE) | O8: 20000 | P8: 2661.5177 | Q8: 45866 | R8: 0R3981 | S8: 000 CAT REMAN | T8: 0R3981 | U8: Unknown | W8: Per CSM Forecast July 25 - TRO; Per CSM Forecast May 25 - TRO; Per CSM Forecast Mar 25 - TRO | X8: 0AGC01231 | Y8: 301026.68 | Z8: 1000.00.RB.0 ENGINE | AA8: 61843 | AB8: MACMAHON CONTRACTORS PTY LTD | AC8: RB - Rebuild Workorder | AE8: 17338.482 | AF8: =_xlfn.XLOOKUP(A8,Macmahon!B:B,Macmahon!AE:AE,"",0) -> 45379 | AG8: =_xlfn.XLOOKUP(A8,Macmahon!B:B,Macmahon!AJ:AJ,"",0) -> 46225 | AH8: =_xlfn.XLOOKUP(A8,Macmahon!B:B,Macmahon!AK:AK,"",0) -> 0 | AI8: =IF(AG8=0,AH8,IF(AH8=0,AG8,MIN(AG8,AH8))) -> 46225 | AJ8: =E8&C8&B8 -> AGC100000 | AK8: =IFERROR(_xlfn.XLOOKUP(AJ8,CrossRef!$A:$A,CrossRef!$J:$J,"Not Found"),"-") -> TKHL018-ENGI | AL8: =IFERROR(_xlfn.XLOOKUP(AJ8,CrossRef!$A:$A,CrossRef!$K:$K,"Not Found"),"-") -> 0 | AM8: =IFERROR(_xlfn.XLOOKUP(AJ8,CrossRef!$A:$A,CrossRef!$L:$L,"Not Found"),"-") -> 20000H ENGINE CHANGE
A9: =D9&C9&B9 -> TD6107100000 | B9: =LEFT(N9,FIND(" ",N9)-1) -> 00 | C9: =LEFT(M9,4) -> 1000 | D9: =LEFT(L9,FIND(" ",L9)-1) -> TD6107 | E9: =MID(X9,2,3) -> APX | G9: WA - Macmahon | H9: 0 - (NONE) | I9: Macmahon-Greenbushes | J9: Macmahon-Greenbushes-Trucks | K9: 785C | L9: TD6107 - APX00780 | M9: 1000 - ENGINE | N9: 00 - (NONE) | O9: 20000 | P9: 5699.2331 | Q9: 47114 | R9: 1755285X | S9: CUSTOMER REBUILD | T9: 1755285X | U9: Unknown | W9: NH - CF May26-:NH- Per CSM Forecast Feb26Per CSM Forecast Jan 26 - TRO;Per CSM Forecast Nov 25 - TRO; Per CSM Forecast Sep 25 - TRO;Per CSM Forecast July 25 - TRO; Per CSM Forecast May 25 - TRO; | X9: 0APX00780 | Y9: 359627.99 | Z9: 1000.00.RB.0 ENGINE CHANGE | AA9: 85467.295 | AB9: MACMAHON CONTRACTORS PTY LTD | AC9: RB - Rebuild Workorder | AE9: 14300.767 | AF9: =_xlfn.XLOOKUP(A9,Macmahon!B:B,Macmahon!AE:AE,"",0) -> 45832 | AG9: =_xlfn.XLOOKUP(A9,Macmahon!B:B,Macmahon!AJ:AJ,"",0) -> 47170.067 | AH9: =_xlfn.XLOOKUP(A9,Macmahon!B:B,Macmahon!AK:AK,"",0) -> 47127 | AI9: =IF(AG9=0,AH9,IF(AH9=0,AG9,MIN(AG9,AH9))) -> 47127 | AJ9: =E9&C9&B9 -> APX100000 | AK9: =IFERROR(_xlfn.XLOOKUP(AJ9,CrossRef!$A:$A,CrossRef!$J:$J,"Not Found"),"-") -> TKHL005-ENGI | AL9: =IFERROR(_xlfn.XLOOKUP(AJ9,CrossRef!$A:$A,CrossRef!$K:$K,"Not Found"),"-") -> 0 | AM9: =IFERROR(_xlfn.XLOOKUP(AJ9,CrossRef!$A:$A,CrossRef!$L:$L,"Not Found"),"-") -> 20000H ENGINE CHANGE
A10: =D10&C10&B10 -> TD6069100000 | B10: =LEFT(N10,FIND(" ",N10)-1) -> 00 | C10: =LEFT(M10,4) -> 1000 | D10: =LEFT(L10,FIND(" ",L10)-1) -> TD6069 | E10: =MID(X10,2,3) -> APX | G10: WA - Macmahon | H10: 0 - (NONE) | I10: Macmahon-Greenbushes | J10: Macmahon-Greenbushes-Trucks | K10: 785C | L10: TD6069 - APX00211 | M10: 1000 - ENGINE | N10: 00 - (NONE) | O10: 20000 | P10: 20150.328 | Q10: 46375 | R10: 1755285X | S10: CUSTOMER REBUILD | T10: 1755285X | U10: Confident | W10: Per CSM Forecast Jan 26 - TRO;Per CSM Forecast Nov 25 - TRO; Per CSM Forecast Sep 25 - TRO;Per CSM Forecast July 25 - TRO; Per CSM Forecast May 25 - TRO; Per CSM Forecast April 25 - TRO; Per CSM Forecast Mar 25 - TROPer CSM Forecast Feb 25 - TROPer CSM Forecast Dec 24 - TRO; Per CSM Forecast Nov 24 - TroPer CSM August Forecast 2024 - TROPer CSM July 2024 Forecast - TROPer CSM June 2024 Forecast - TRO;Per CSM Forecast April 2024 TRO;Per CSM Sales Status Report April 2024 - TR0; Aug 2023 Monthly Forecast Data - MSC Returned Summary Report June 2022 - MSC | X10: 0APX00211 | Y10: 359627.99 | Z10: 1000.00.RB.0 ENGINE CHANGE | AA10: 81103.422 | AB10: MACMAHON CONTRACTORS PTY LTD | AC10: RB - Rebuild Workorder | AE10: -150.32824 | AF10: =_xlfn.XLOOKUP(A10,Macmahon!B:B,Macmahon!AE:AE,"",0) -> 44187 | AG10: =_xlfn.XLOOKUP(A10,Macmahon!B:B,Macmahon!AJ:AJ,"",0) -> 46196.831 | AH10: =_xlfn.XLOOKUP(A10,Macmahon!B:B,Macmahon!AK:AK,"",0) -> 0 | AI10: =IF(AG10=0,AH10,IF(AH10=0,AG10,MIN(AG10,AH10))) -> 46196.831 | AJ10: =E10&C10&B10 -> APX100000 | AK10: =IFERROR(_xlfn.XLOOKUP(AJ10,CrossRef!$A:$A,CrossRef!$J:$J,"Not Found"),"-") -> TKHL005-ENGI | AL10: =IFERROR(_xlfn.XLOOKUP(AJ10,CrossRef!$A:$A,CrossRef!$K:$K,"Not Found"),"-") -> 0 | AM10: =IFERROR(_xlfn.XLOOKUP(AJ10,CrossRef!$A:$A,CrossRef!$L:$L,"Not Found"),"-") -> 20000H ENGINE CHANGE
A11: =D11&C11&B11 -> TD6491100000 | B11: =LEFT(N11,FIND(" ",N11)-1) -> 00 | C11: =LEFT(M11,4) -> 1000 | D11: =LEFT(L11,FIND(" ",L11)-1) -> TD6491 | E11: =MID(X11,2,3) -> APX | G11: WA - Macmahon | H11: 0 - (NONE) | I11: Macmahon-Greenbushes | J11: Macmahon-Greenbushes-Trucks | K11: 785C | L11: TD6491 - APX01319 | M11: 1000 - ENGINE | N11: 00 - (NONE) | O11: 20000 | P11: 11606.307 | Q11: 46735 | R11: 1755285X | S11: CUSTOMER REBUILD | T11: 1755285X | U11: Unknown | W11: NH - CF May26-:NH- Per Customer Forecast March26;NH- Per CSM Forecast Feb26Per CSM Forecast Jan 26 - TRO;Per CSM Forecast Nov 25 - TRO; Per CSM Forecast Sep 25 - TRO;Per CSM Forecast July 25 - TRO; Per CSM Forecast May 25 - TRO; Per CSM Forecast April 25 - TRO; Per CSM Forecast Mar 25 - TROPer CSM Forecast Feb 25 - TROPer CSM Forecast Dec 24 - TRO; Per CSM Forecast Nov 24 - TroPer CSM August Forecast 2024 - TROPer CSM July 2024 Forecast - TROPer CSM June 2024 Forecast - TRO;Per CSM Forecast April 2024 TRO;Per CSM forcast data Mar 2024 - TRO;Oct 2023 Monthly Forecast - NIH; Aug 2023 Monthly Forecast Data - MSC Per Monthly Forecast Data July 2023 - MSC Per Sales Status Update Returned Summary Report May 2023 - MSC Per Monthly Forecast Data May 2023 - MSC Per Monthly Forecast Data Feb23 - MSC | X11: 0APX01319 | Y11: 359627.99 | Z11: 1000.00.RB.0 ENGINE CHANGE | AA11: 71121.987 | AB11: MACMAHON CONTRACTORS PTY LTD | AC11: RB - Rebuild Workorder | AE11: 8393.6931 | AF11: =_xlfn.XLOOKUP(A11,Macmahon!B:B,Macmahon!AE:AE,"",0) -> 45172 | AG11: =_xlfn.XLOOKUP(A11,Macmahon!B:B,Macmahon!AJ:AJ,"",0) -> 47958.05 | AH11: =_xlfn.XLOOKUP(A11,Macmahon!B:B,Macmahon!AK:AK,"",0) -> 47287 | AI11: =IF(AG11=0,AH11,IF(AH11=0,AG11,MIN(AG11,AH11))) -> 47287 | AJ11: =E11&C11&B11 -> APX100000 | AK11: =IFERROR(_xlfn.XLOOKUP(AJ11,CrossRef!$A:$A,CrossRef!$J:$J,"Not Found"),"-") -> TKHL005-ENGI | AL11: =IFERROR(_xlfn.XLOOKUP(AJ11,CrossRef!$A:$A,CrossRef!$K:$K,"Not Found"),"-") -> 0 | AM11: =IFERROR(_xlfn.XLOOKUP(AJ11,CrossRef!$A:$A,CrossRef!$L:$L,"Not Found"),"-") -> 20000H ENGINE CHANGE
A12: =D12&C12&B12 -> TD6493100000 | B12: =LEFT(N12,FIND(" ",N12)-1) -> 00 | C12: =LEFT(M12,4) -> 1000 | D12: =LEFT(L12,FIND(" ",L12)-1) -> TD6493 | E12: =MID(X12,2,3) -> APX | G12: WA - Macmahon | H12: 0 - (NONE) | I12: Macmahon-Greenbushes | J12: Macmahon-Greenbushes-Trucks | K12: 785C | L12: TD6493 - APX00394 | M12: 1000 - ENGINE | N12: 00 - (NONE) | O12: 20000 | P12: 4589.3505 | Q12: 48118 | R12: 1755285X | S12: CUSTOMER REBUILD | T12: 1755285X | U12: Unknown | W12: Per CSM Forecast Jan 26 - TRO;Per CSM Forecast Nov 25 - TRO; Per CSM Forecast Sep 25 - TRO;Per CSM Forecast July 25 - TRO; Per CSM Forecast May 25 - TRO; Per CSM Forecast April 25 - TRO; Per CSM Forecast Mar 25 - TRO | X12: 0APX00394 | Y12: 359627.99 | Z12: 1000.00.RB.0 ENGINE CHANGE | AA12: 82920.004 | AB12: MACMAHON CONTRACTORS PTY LTD | AC12: RB - Rebuild Workorder | AE12: 15410.65 | AF12: =_xlfn.XLOOKUP(A12,Macmahon!B:B,Macmahon!AE:AE,"",0) -> 45688 | AG12: =_xlfn.XLOOKUP(A12,Macmahon!B:B,Macmahon!AJ:AJ,"",0) -> 49050.085 | AH12: =_xlfn.XLOOKUP(A12,Macmahon!B:B,Macmahon!AK:AK,"",0) -> 0 | AI12: =IF(AG12=0,AH12,IF(AH12=0,AG12,MIN(AG12,AH12))) -> 49050.085 | AJ12: =E12&C12&B12 -> APX100000 | AK12: =IFERROR(_xlfn.XLOOKUP(AJ12,CrossRef!$A:$A,CrossRef!$J:$J,"Not Found"),"-") -> TKHL005-ENGI | AL12: =IFERROR(_xlfn.XLOOKUP(AJ12,CrossRef!$A:$A,CrossRef!$K:$K,"Not Found"),"-") -> 0 | AM12: =IFERROR(_xlfn.XLOOKUP(AJ12,CrossRef!$A:$A,CrossRef!$L:$L,"Not Found"),"-") -> 20000H ENGINE CHANGE
A13: =D13&C13&B13 -> TD6492100000 | B13: =LEFT(N13,FIND(" ",N13)-1) -> 00 | C13: =LEFT(M13,4) -> 1000 | D13: =LEFT(L13,FIND(" ",L13)-1) -> TD6492 | E13: =MID(X13,2,3) -> APX | G13: WA - Macmahon | H13: 0 - (NONE) | I13: Macmahon-Telfer | J13: Macmahon-Telfer-Trucks | K13: 785C | L13: TD6492 - APX01321 | M13: 1000 - ENGINE | N13: 00 - (NONE) | O13: 20000 | P13: 8222.821 | Q13: 46825 | R13: 1755285X | S13: CUSTOMER REBUILD | T13: 1755285X | U13: Unknown | W13: NH - CF May26-:NH- Per Customer Forecast March26;NH- Per CSM Forecast Feb26Per CSM Forecast Jan 26 - TRO;Per CSM Forecast Nov 25 - TRO; Per CSM Forecast Sep 25 - TRO;Per CSM Forecast July 25 - TRO; | X13: 0APX01321 | Y13: 359627.99 | Z13: 1000.00.RB.0 ENGINE CHANGE | AA13: 73609.8 | AB13: MACMAHON CONTRACTORS PTY LTD | AC13: RB - Rebuild Workorder | AE13: 11777.179 | AF13: =_xlfn.XLOOKUP(A13,Macmahon!B:B,Macmahon!AE:AE,"",0) -> 45522 | AG13: =_xlfn.XLOOKUP(A13,Macmahon!B:B,Macmahon!AJ:AJ,"",0) -> 48792.123 | AH13: =_xlfn.XLOOKUP(A13,Macmahon!B:B,Macmahon!AK:AK,"",0) -> 46825 | AI13: =IF(AG13=0,AH13,IF(AH13=0,AG13,MIN(AG13,AH13))) -> 46825 | AJ13: =E13&C13&B13 -> APX100000 | AK13: =IFERROR(_xlfn.XLOOKUP(AJ13,CrossRef!$A:$A,CrossRef!$J:$J,"Not Found"),"-") -> TKHL005-ENGI | AL13: =IFERROR(_xlfn.XLOOKUP(AJ13,CrossRef!$A:$A,CrossRef!$K:$K,"Not Found"),"-") -> 0 | AM13: =IFERROR(_xlfn.XLOOKUP(AJ13,CrossRef!$A:$A,CrossRef!$L:$L,"Not Found"),"-") -> 20000H ENGINE CHANGE
A14: =D14&C14&B14 -> LO1649100000 | B14: =LEFT(N14,FIND(" ",N14)-1) -> 00 | C14: =LEFT(M14,4) -> 1000 | D14: =LEFT(L14,FIND(" ",L14)-1) -> LO1649 | E14: =MID(X14,2,3) -> Z8Z | G14: WA - Macmahon | H14: 0 - (NONE) | I14: Macmahon-Tropicana | J14: Macmahon-Tropicana-Loaders | K14: 993K-HL | L14: LO1649 - Z8Z00187 | M14: 1000 - ENGINE | N14: 00 - (NONE) | O14: 15000 | P14: 8035.5483 | Q14: 47177 | R14: 5875939X | S14: CUSTOMER REBUILD | T14: 5875939X | U14: Confident | W14: NH- Per Customer Forecast March26;NH- Per CSM Forecast Feb26Per CSM Forecast Jan 26 - TRO;Per CSM Forecast Nov 25 - TRO; Per CSM Forecast Sep 25 - TRO;Per CSM Forecast July 25 - TRO; Per CSM Forecast May 25 - TRO; Per CSM Forecast April 25 - TRO; Per CSM Forecast Mar 25 - TROPer CSM Forecast Feb 25 - TRO | X14: 0Z8Z00187 | Y14: 191053.57 | Z14: 1000.00.RB.0 ENGINE | AA14: 35707.376 | AB14: MACMAHON CONTRACTORS PTY LTD | AC14: RB - Rebuild Workorder | AE14: 6964.4517 | AF14: =_xlfn.XLOOKUP(A14,Macmahon!B:B,Macmahon!AE:AE,"",0) -> 46108 | AG14: =_xlfn.XLOOKUP(A14,Macmahon!B:B,Macmahon!AJ:AJ,"",0) -> 47050.019 | AH14: =_xlfn.XLOOKUP(A14,Macmahon!B:B,Macmahon!AK:AK,"",0) -> 47205 | AI14: =IF(AG14=0,AH14,IF(AH14=0,AG14,MIN(AG14,AH14))) -> 47050.019 | AJ14: =E14&C14&B14 -> Z8Z100000 | AK14: =IFERROR(_xlfn.XLOOKUP(AJ14,CrossRef!$A:$A,CrossRef!$J:$J,"Not Found"),"-") -> LOFE150-ENGI | AL14: =IFERROR(_xlfn.XLOOKUP(AJ14,CrossRef!$A:$A,CrossRef!$K:$K,"Not Found"),"-") -> 0 | AM14: =IFERROR(_xlfn.XLOOKUP(AJ14,CrossRef!$A:$A,CrossRef!$L:$L,"Not Found"),"-") -> 15000H ENGINE CHANGE
A15: =D15&C15&B15 -> GD1419100000 | B15: =LEFT(N15,FIND(" ",N15)-1) -> 00 | C15: =LEFT(M15,4) -> 1000 | D15: =LEFT(L15,FIND(" ",L15)-1) -> GD1419 | E15: =MID(X15,2,3) -> NN5 | G15: WA - Macmahon | H15: 0 - (NONE) | I15: Macmahon-Tropicana | J15: Macmahon-Tropicana-Graders | K15: 16 | L15: GD1419 - NN500165 | M15: 1000 - ENGINE | N15: 00 - (NONE) | O15: 14000 | P15: 1306.3864 | Q15: 47570.038 | R15: 30R0237 | S15: 000 CAT REMAN | T15: 11R1242 | U15: Unknown | X15: 0NN500165 | Y15: 98542.59 | Z15: 1000.00.RB.0 ENGINE | AA15: 30072.574 | AB15: MACMAHON CONTRACTORS PTY LTD | AC15: RB - Rebuild Workorder | AE15: 12693.614 | AF15: =_xlfn.XLOOKUP(A15,Macmahon!B:B,Macmahon!AE:AE,"",0) -> 46109 | AG15: =_xlfn.XLOOKUP(A15,Macmahon!B:B,Macmahon!AJ:AJ,"",0) -> 47154.157 | AH15: =_xlfn.XLOOKUP(A15,Macmahon!B:B,Macmahon!AK:AK,"",0) -> 47233 | AI15: =IF(AG15=0,AH15,IF(AH15=0,AG15,MIN(AG15,AH15))) -> 47154.157 | AJ15: =E15&C15&B15 -> NN5100000 | AK15: =IFERROR(_xlfn.XLOOKUP(AJ15,CrossRef!$A:$A,CrossRef!$J:$J,"Not Found"),"-") -> GDGN051-ENGI | AL15: =IFERROR(_xlfn.XLOOKUP(AJ15,CrossRef!$A:$A,CrossRef!$K:$K,"Not Found"),"-") -> 0 | AM15: =IFERROR(_xlfn.XLOOKUP(AJ15,CrossRef!$A:$A,CrossRef!$L:$L,"Not Found"),"-") -> 14000H ENGINE CHANGE
A16: =D16&C16&B16 -> QEX0101000LT | B16: =LEFT(N16,FIND(" ",N16)-1) -> LT | C16: =LEFT(M16,4) -> 1000 | D16: =LEFT(L16,FIND(" ",L16)-1) -> QEX010 | E16: =MID(X16,2,3) -> DHN | G16: WA - Macmahon | H16: 0 - (NONE) | I16: Macmahon-Telfer | J16: Macmahon-Telfer-Excavators | K16: 6060 | L16: QEX010 - DHN60137 | M16: 1000 - ENGINE | N16: LT - LEFT | O16: 14300 | P16: 3939.0833 | Q16: 47302 | R16: 20R2674 | S16: 000 CAT REMAN | T16: 20R2674 | U16: Unknown | W16: Per CSM Forecast Jan 26 - TRO;Per CSM Forecast Nov 25 - TRO; Per CSM Forecast Sep 25 - TRO; | X16: 0DHN60137 | Y16: 0 | Z16: 1000.LT.RB.0 ENGINE LHS | AA16: 86202.889 | AB16: MACMAHON CONTRACTORS PTY LTD | AC16: RB - Rebuild Workorder | AD16: J. Power | AE16: 10360.917 | AF16: =_xlfn.XLOOKUP(A16,Macmahon!B:B,Macmahon!AE:AE,"",0) -> 45899 | AG16: =_xlfn.XLOOKUP(A16,Macmahon!B:B,Macmahon!AJ:AJ,"",0) -> 47513.717 | AH16: =_xlfn.XLOOKUP(A16,Macmahon!B:B,Macmahon!AK:AK,"",0) -> 47201 | AI16: =IF(AG16=0,AH16,IF(AH16=0,AG16,MIN(AG16,AH16))) -> 47201 | AJ16: =E16&C16&B16 -> DHN1000LT | AK16: =IFERROR(_xlfn.XLOOKUP(AJ16,CrossRef!$A:$A,CrossRef!$J:$J,"Not Found"),"-") -> EXBH009-ENG1 | AL16: =IFERROR(_xlfn.XLOOKUP(AJ16,CrossRef!$A:$A,CrossRef!$K:$K,"Not Found"),"-") -> 0 | AM16: =IFERROR(_xlfn.XLOOKUP(AJ16,CrossRef!$A:$A,CrossRef!$L:$L,"Not Found"),"-") -> 14300H ENGINE CHANGE LH
A17: =D17&C17&B17 -> EX71081000LT | B17: =LEFT(N17,FIND(" ",N17)-1) -> LT | C17: =LEFT(M17,4) -> 1000 | D17: =LEFT(L17,FIND(" ",L17)-1) -> EX7108 | E17: =MID(X17,2,3) -> DHN | G17: WA - Macmahon | H17: 0 - (NONE) | I17: Macmahon-Tropicana | J17: Macmahon-Tropicana-EMP Excavators | K17: 6060 | L17: EX7108 - DHN60189 | M17: 1000 - ENGINE | N17: LT - LEFT | O17: 15000 | P17: 12338.923 | Q17: 46381 | R17: 20R2674 | S17: 000 CAT REMAN | T17: 20R2674 | U17: Unknown | W17: NH - CF May26-:NH- Per Customer Forecast March26;Per CSM Forecast Jan 26 - TRO;Per CSM Forecast Nov 25 - TRO; Per CSM Forecast Sep 25 - TRO;Per CSM Forecast July 25 - TRO; | X17: 0DHN60189 | Y17: 0 | Z17: 1000.LT.RB.0 ENGINE LHS | AA17: 54639.526 | AB17: MACMAHON CONTRACTORS PTY LTD | AC17: RB - Rebuild Workorder | AD17: J. Power | AE17: 2661.0771 | AF17: =_xlfn.XLOOKUP(A17,Macmahon!B:B,Macmahon!AE:AE,"",0) | AG17: =_xlfn.XLOOKUP(A17,Macmahon!B:B,Macmahon!AJ:AJ,"",0) | AH17: =_xlfn.XLOOKUP(A17,Macmahon!B:B,Macmahon!AK:AK,"",0) | AI17: =IF(AG17=0,AH17,IF(AH17=0,AG17,MIN(AG17,AH17))) -> 0 | AJ17: =E17&C17&B17 -> DHN1000LT | AK17: =IFERROR(_xlfn.XLOOKUP(AJ17,CrossRef!$A:$A,CrossRef!$J:$J,"Not Found"),"-") -> EXBH009-ENG1 | AL17: =IFERROR(_xlfn.XLOOKUP(AJ17,CrossRef!$A:$A,CrossRef!$K:$K,"Not Found"),"-") -> 0 | AM17: =IFERROR(_xlfn.XLOOKUP(AJ17,CrossRef!$A:$A,CrossRef!$L:$L,"Not Found"),"-") -> 14300H ENGINE CHANGE LH
A18: =D18&C18&B18 -> EX71081000RI | B18: =LEFT(N18,FIND(" ",N18)-1) -> RI | C18: =LEFT(M18,4) -> 1000 | D18: =LEFT(L18,FIND(" ",L18)-1) -> EX7108 | E18: =MID(X18,2,3) -> DHN | G18: WA - Macmahon | H18: 0 - (NONE) | I18: Macmahon-Tropicana | J18: Macmahon-Tropicana-EMP Excavators | K18: 6060 | L18: EX7108 - DHN60189 | M18: 1000 - ENGINE | N18: RI - RIGHT | O18: 15000 | P18: 3410.6578 | Q18: 47218 | R18: 20R2674 | S18: 000 CAT REMAN | T18: 20R2674 | U18: Unknown | W18: Per CSM Forecast Jan 26 - TRO; | X18: 0DHN60189 | Y18: 0 | Z18: 1000.RI.RB.0 ENGINE RHS | AA18: 68389.012 | AB18: MACMAHON CONTRACTORS PTY LTD | AC18: RB - Rebuild Workorder | AD18: J. Power | AE18: 11589.342 | AF18: =_xlfn.XLOOKUP(A18,Macmahon!B:B,Macmahon!AE:AE,"",0) | AG18: =_xlfn.XLOOKUP(A18,Macmahon!B:B,Macmahon!AJ:AJ,"",0) | AH18: =_xlfn.XLOOKUP(A18,Macmahon!B:B,Macmahon!AK:AK,"",0) | AI18: =IF(AG18=0,AH18,IF(AH18=0,AG18,MIN(AG18,AH18))) -> 0 | AJ18: =E18&C18&B18 -> DHN1000RI | AK18: =IFERROR(_xlfn.XLOOKUP(AJ18,CrossRef!$A:$A,CrossRef!$J:$J,"Not Found"),"-") -> EXBH047-ENG2 | AL18: =IFERROR(_xlfn.XLOOKUP(AJ18,CrossRef!$A:$A,CrossRef!$K:$K,"Not Found"),"-") -> 0 | AM18: =IFERROR(_xlfn.XLOOKUP(AJ18,CrossRef!$A:$A,CrossRef!$L:$L,"Not Found"),"-") -> 14300H ENGINE CHANGE RH
A19: =D19&C19&B19 -> QEX0101000RI | B19: =LEFT(N19,FIND(" ",N19)-1) -> RI | C19: =LEFT(M19,4) -> 1000 | D19: =LEFT(L19,FIND(" ",L19)-1) -> QEX010 | E19: =MID(X19,2,3) -> DHN | G19: WA - Macmahon | H19: 0 - (NONE) | I19: Macmahon-Telfer | J19: Macmahon-Telfer-Excavators | K19: 6060 | L19: QEX010 - DHN60137 | M19: 1000 - ENGINE | N19: RI - RIGHT | O19: 14300 | P19: 15157.874 | Q19: 46177 | R19: 20R2674 | S19: 000 CAT REMAN | T19: 20R2674 | U19: Confident | W19: NH - CF May26-:NH- Per Customer Forecast March26;Per CSM Forecast Jan 26 - TRO;Per CSM Forecast Nov 25 - TRO; Per CSM Forecast Sep 25 - TRO;Per CSM Forecast July 25 - TRO; Per CSM Forecast May 25 - TRO; Per CSM Forecast April 25 - TRO; Per CSM Forecast Mar 25 - TROPer CSM Forecast Feb 25 - TROPer CSM Forecast Dec 24 - TRO; Per CSM Forecast Nov 24 - TroPer CSM August Forecast 2024 - TROPer CSM July 2024 Forecast - TROPer CSM June 2024 Forecast - TRO;Per CSM Forecast April 2024 TRO;Nov 2023 Forecast-NIH Oct 2023 Monthly Forecast - NIH; Aug 2023 Monthly Forecast Data - MSC Per Monthly Forecast Data July 2023 - MSC Per Monthly Forecast Data June 2023 - MSC Per Sales Status Update Returned Summary Report May 2023 - MSC Per Monthly Forecast Data May 2023 - MSC Per Monthly Forecast Data Feb23 - MSC | X19: 0DHN60137 | Y19: 0 | Z19: 1000.RI.RB.0 ENGINE RHS | AA19: 67722.396 | AB19: MACMAHON CONTRACTORS PTY LTD | AC19: RB - Rebuild Workorder | AD19: J. Power | AE19: -857.87402 | AF19: =_xlfn.XLOOKUP(A19,Macmahon!B:B,Macmahon!AE:AE,"",0) -> 44970 | AG19: =_xlfn.XLOOKUP(A19,Macmahon!B:B,Macmahon!AJ:AJ,"",0) -> 46281.969 | AH19: =_xlfn.XLOOKUP(A19,Macmahon!B:B,Macmahon!AK:AK,"",0) -> 0 | AI19: =IF(AG19=0,AH19,IF(AH19=0,AG19,MIN(AG19,AH19))) -> 46281.969 | AJ19: =E19&C19&B19 -> DHN1000RI | AK19: =IFERROR(_xlfn.XLOOKUP(AJ19,CrossRef!$A:$A,CrossRef!$J:$J,"Not Found"),"-") -> EXBH047-ENG2 | AL19: =IFERROR(_xlfn.XLOOKUP(AJ19,CrossRef!$A:$A,CrossRef!$K:$K,"Not Found"),"-") -> 0 | AM19: =IFERROR(_xlfn.XLOOKUP(AJ19,CrossRef!$A:$A,CrossRef!$L:$L,"Not Found"),"-") -> 14300H ENGINE CHANGE RH
A20: =D20&C20&B20 -> TD6642100000 | B20: =LEFT(N20,FIND(" ",N20)-1) -> 00 | C20: =LEFT(M20,4) -> 1000 | D20: =LEFT(L20,FIND(" ",L20)-1) -> TD6642 | E20: =MID(X20,2,3) -> SPD | G20: WA - Macmahon | H20: 0 - (NONE) | I20: Macmahon-King of the Hill | J20: Macmahon-King of the Hill -Trucks | K20: 789D | L20: TD6642 - SPD01084 | M20: 1000 - ENGINE | N20: 00 - (NONE) | O20: 22000 | P20: 21781.471 | Q20: 46209 | R20: 3659316X | S20: 503 PEX CONTRACT | T20: 3659316X | U20: Sale Confirmed | V20: 4500459654 | W20: Per PEX status - 23/04 JDI; NH- Per Customer Forecast March26;Per CSM Forecast Jan 26 - TRO;Per CSM Forecast Nov 25 - TRO; Per CSM Forecast Sep 25 - TRO;Per CSM Forecast July 25 - TRO; Per CSM Forecast May 25 - TRO; Per CSM Forecast April 25 - TRO; Per CSM Forecast Mar 25 - TROPer CSM Forecast Feb 25 - TROPer CSM Forecast Dec 24 - TRO; Per CSM Forecast Nov 24 - TroPer CSM July 2024 Forecast - TROPer CSM June 2024 Forecast - TRO;Per CSM Forecast April 2024 TRO;Per CSM Sales Status Report April 2024 - TR0; Per CSM forcast data Mar 2024 - TRO;Oct 2023 Monthly Forecast - NIH; Per Sales Status Update Returned Summary Report May 2023 - MSC Per Monthly Forecast Data May 2023 - MSC Per Monthly Forecast Data Feb23 - MSC | X20: 0SPD01084 | Y20: 455016.09 | Z20: 1000.00.RB.0 ENGINE | AA20: 21347 | AB20: NEW CATERPILLAR MACHINES | AC20: RB - Rebuild Workorder | AE20: 218.52888 | AF20: =_xlfn.XLOOKUP(A20,Macmahon!B:B,Macmahon!AE:AE,"",0) -> 0 | AG20: =_xlfn.XLOOKUP(A20,Macmahon!B:B,Macmahon!AJ:AJ,"",0) -> 46256.19 | AH20: =_xlfn.XLOOKUP(A20,Macmahon!B:B,Macmahon!AK:AK,"",0) -> 46259 | AI20: =IF(AG20=0,AH20,IF(AH20=0,AG20,MIN(AG20,AH20))) -> 46256.19 | AJ20: =E20&C20&B20 -> SPD100000 | AK20: =IFERROR(_xlfn.XLOOKUP(AJ20,CrossRef!$A:$A,CrossRef!$J:$J,"Not Found"),"-") -> TKHL234-ENGI | AL20: =IFERROR(_xlfn.XLOOKUP(AJ20,CrossRef!$A:$A,CrossRef!$K:$K,"Not Found"),"-") -> 0 | AM20: =IFERROR(_xlfn.XLOOKUP(AJ20,CrossRef!$A:$A,CrossRef!$L:$L,"Not Found"),"-") -> 20000H ENGINE CHANGE
A21: =D21&C21&B21 -> TD6641100000 | B21: =LEFT(N21,FIND(" ",N21)-1) -> 00 | C21: =LEFT(M21,4) -> 1000 | D21: =LEFT(L21,FIND(" ",L21)-1) -> TD6641 | E21: =MID(X21,2,3) -> SPD | G21: WA - Macmahon | H21: 0 - (NONE) | I21: Macmahon-King of the Hill | J21: Macmahon-King of the Hill -Trucks | K21: 789D | L21: TD6641 - SPD01047 | M21: 1000 - ENGINE | N21: 00 - (NONE) | O21: 22000 | P21: 20540.925 | Q21: 46328 | R21: 3659316X | S21: 503 PEX CONTRACT | T21: 3659316X | U21: Sale Confirmed | V21: 4500460935 | W21: Per PEX status - 23/04 JDI; NH- Per Customer Forecast March26;Per CSM Forecast Jan 26 - TRO;Per CSM Forecast Nov 25 - TRO; Per CSM Forecast Sep 25 - TRO;Per CSM Forecast July 25 - TRO; Per CSM Forecast May 25 - TRO; Per CSM Forecast April 25 - TRO; Per CSM Forecast Mar 25 - TROPer CSM Forecast Feb 25 - TROPer CSM Forecast Dec 24 - TRO; Per CSM Forecast Nov 24 - TroPer CSM July 2024 Forecast - TROPer CSM Forecast April 2024 TRO;Per CSM Sales Status Report April 2024 - TR0; Per CSM forcast data Mar 2024 - TRO;Oct 2023 Monthly Forecast - NIH; Per Sales Status Update Returned Summary Report May 2023 - MSC Per Monthly Forecast Data May 2023 - MSC Per Monthly Forecast Data Feb23 - MSC | X21: 0SPD01047 | Y21: 455016.09 | Z21: 1000.00.RB.0 ENGINE | AA21: 21626.833 | AB21: NEW CATERPILLAR MACHINES | AC21: RB - Rebuild Workorder | AE21: 1459.0751 | AF21: =_xlfn.XLOOKUP(A21,Macmahon!B:B,Macmahon!AE:AE,"",0) -> 0 | AG21: =_xlfn.XLOOKUP(A21,Macmahon!B:B,Macmahon!AJ:AJ,"",0) -> 46354.766 | AH21: =_xlfn.XLOOKUP(A21,Macmahon!B:B,Macmahon!AK:AK,"",0) -> 46363 | AI21: =IF(AG21=0,AH21,IF(AH21=0,AG21,MIN(AG21,AH21))) -> 46354.766 | AJ21: =E21&C21&B21 -> SPD100000 | AK21: =IFERROR(_xlfn.XLOOKUP(AJ21,CrossRef!$A:$A,CrossRef!$J:$J,"Not Found"),"-") -> TKHL234-ENGI | AL21: =IFERROR(_xlfn.XLOOKUP(AJ21,CrossRef!$A:$A,CrossRef!$K:$K,"Not Found"),"-") -> 0 | AM21: =IFERROR(_xlfn.XLOOKUP(AJ21,CrossRef!$A:$A,CrossRef!$L:$L,"Not Found"),"-") -> 20000H ENGINE CHANGE
A22: =D22&C22&B22 -> TD6643100000 | B22: =LEFT(N22,FIND(" ",N22)-1) -> 00 | C22: =LEFT(M22,4) -> 1000 | D22: =LEFT(L22,FIND(" ",L22)-1) -> TD6643 | E22: =MID(X22,2,3) -> SPD | G22: WA - Macmahon | H22: 0 - (NONE) | I22: Macmahon-King of the Hill | J22: Macmahon-King of the Hill -Trucks | K22: 789D | L22: TD6643 - SPD01086 | M22: 1000 - ENGINE | N22: 00 - (NONE) | O22: 22000 | P22: 21497.883 | Q22: 46304 | R22: 3659316X | S22: 503 PEX CONTRACT | T22: 3659316X | U22: Sale Confirmed | V22: 4500459661 | W22: Per PEX status - 23/04 JDI; NH- Per Customer Forecast March26;Per CSM Forecast Jan 26 - TRO;Per CSM Forecast Nov 25 - TRO; Per CSM Forecast Sep 25 - TRO;Per CSM Forecast July 25 - TRO; Per CSM Forecast May 25 - TRO; Per CSM Forecast April 25 - TRO; Per CSM Forecast Mar 25 - TROPer CSM Forecast Feb 25 - TROPer CSM Forecast Dec 24 - TRO; Per CSM Forecast Nov 24 - TroPer CSM July 2024 Forecast - TROPer CSM June 2024 Forecast - TRO;Per CSM Forecast April 2024 TRO;Per CSM Sales Status Report April 2024 - TR0; Per CSM forcast data Mar 2024 - TRO;Oct 2023 Monthly Forecast - NIH; Per Sales Status Update Returned Summary Report May 2023 - MSC Per Monthly Forecast Data May 2023 - MSC Per Monthly Forecast Data Feb23 - MSC | X22: 0SPD01086 | Y22: 455016.09 | Z22: 1000.00.RB.0 ENGINE | AA22: 22268.39 | AB22: NEW CATERPILLAR MACHINES | AC22: RB - Rebuild Workorder | AE22: 502.11729 | AF22: =_xlfn.XLOOKUP(A22,Macmahon!B:B,Macmahon!AE:AE,"",0) -> 0 | AG22: =_xlfn.XLOOKUP(A22,Macmahon!B:B,Macmahon!AJ:AJ,"",0) -> 46284.697 | AH22: =_xlfn.XLOOKUP(A22,Macmahon!B:B,Macmahon!AK:AK,"",0) -> 46297 | AI22: =IF(AG22=0,AH22,IF(AH22=0,AG22,MIN(AG22,AH22))) -> 46284.697 | AJ22: =E22&C22&B22 -> SPD100000 | AK22: =IFERROR(_xlfn.XLOOKUP(AJ22,CrossRef!$A:$A,CrossRef!$J:$J,"Not Found"),"-") -> TKHL234-ENGI | AL22: =IFERROR(_xlfn.XLOOKUP(AJ22,CrossRef!$A:$A,CrossRef!$K:$K,"Not Found"),"-") -> 0 | AM22: =IFERROR(_xlfn.XLOOKUP(AJ22,CrossRef!$A:$A,CrossRef!$L:$L,"Not Found"),"-") -> 20000H ENGINE CHANGE
A23: =D23&C23&B23 -> TD6638100000 | B23: =LEFT(N23,FIND(" ",N23)-1) -> 00 | C23: =LEFT(M23,4) -> 1000 | D23: =LEFT(L23,FIND(" ",L23)-1) -> TD6638 | E23: =MID(X23,2,3) -> SPD | G23: WA - Macmahon | H23: 0 - (NONE) | I23: Macmahon-King of the Hill | J23: Macmahon-King of the Hill -Trucks | K23: 789D | L23: TD6638 - SPD01067 | M23: 1000 - ENGINE | N23: 00 - (NONE) | O23: 22000 | P23: 22187.197 | Q23: 46164 | R23: 3659316X | S23: 503 PEX CONTRACT | T23: 3659316X | U23: Lost | W23: NH - Lost sale 18062026 | X23: 0SPD01067 | Y23: 455016.09 | Z23: 1000.00.RB.0 ENGINE | AA23: 21085.026 | AB23: NEW CATERPILLAR MACHINES | AC23: RB - Rebuild Workorder | AE23: -187.19734 | AF23: =_xlfn.XLOOKUP(A23,Macmahon!B:B,Macmahon!AE:AE,"",0) -> 46174 | AG23: =_xlfn.XLOOKUP(A23,Macmahon!B:B,Macmahon!AJ:AJ,"",0) -> 47832.991 | AH23: =_xlfn.XLOOKUP(A23,Macmahon!B:B,Macmahon!AK:AK,"",0) -> 0 | AI23: =IF(AG23=0,AH23,IF(AH23=0,AG23,MIN(AG23,AH23))) -> 47832.991 | AJ23: =E23&C23&B23 -> SPD100000 | AK23: =IFERROR(_xlfn.XLOOKUP(AJ23,CrossRef!$A:$A,CrossRef!$J:$J,"Not Found"),"-") -> TKHL234-ENGI | AL23: =IFERROR(_xlfn.XLOOKUP(AJ23,CrossRef!$A:$A,CrossRef!$K:$K,"Not Found"),"-") -> 0 | AM23: =IFERROR(_xlfn.XLOOKUP(AJ23,CrossRef!$A:$A,CrossRef!$L:$L,"Not Found"),"-") -> 20000H ENGINE CHANGE
A24: =D24&C24&B24 -> TW2391100000 | B24: =LEFT(N24,FIND(" ",N24)-1) -> 00 | C24: =LEFT(M24,4) -> 1000 | D24: =LEFT(L24,FIND(" ",L24)-1) -> TW2391 | E24: =MID(X24,2,3) -> 3PR | G24: WA - Macmahon | H24: 0 - (NONE) | I24: Macmahon-Telfer | J24: Macmahon-Telfer-Trucks | K24: 777D | L24: TW2391 - 3PR00252 | M24: 1000 - ENGINE | N24: 00 - (NONE) | O24: 20000 | P24: 11604.378 | Q24: 47436 | R24: 0R3981 | S24: 000 CAT REMAN | T24: 0R3981 | U24: Unlikely | W24: NH - CF May26-:NH- Per CSM Forecast Feb26Per CSM Forecast Jan 26 - TRO;Per CSM Forecast Nov 25 - TRO; Per CSM Forecast Sep 25 - TRO;Per CSM Forecast July 25 - TRO; Per CSM Forecast May 25 - TRO; Per CSM Forecast April 25 - TRO; Per CSM Forecast Mar 25 - TROPer CSM Forecast Feb 25 - TROPer CSM Forecast Dec 24 - TRO; Per CSM Forecast Nov 24 - Tro | X24: 03PR00252 | Y24: 301026.68 | Z24: 1000.00.RB.0 ENGINE | AA24: 99566.341 | AB24: MACMAHON CONTRACTORS PTY LTD | AC24: RB - Rebuild Workorder | AE24: 8395.6218 | AF24: =_xlfn.XLOOKUP(A24,Macmahon!B:B,Macmahon!AE:AE,"",0) -> 44686 | AG24: =_xlfn.XLOOKUP(A24,Macmahon!B:B,Macmahon!AJ:AJ,"",0) -> 46225 | AH24: =_xlfn.XLOOKUP(A24,Macmahon!B:B,Macmahon!AK:AK,"",0) -> 0 | AI24: =IF(AG24=0,AH24,IF(AH24=0,AG24,MIN(AG24,AH24))) -> 46225 | AJ24: =E24&C24&B24 -> 3PR100000 | AK24: =IFERROR(_xlfn.XLOOKUP(AJ24,CrossRef!$A:$A,CrossRef!$J:$J,"Not Found"),"-") -> TKHL017-ENGI | AL24: =IFERROR(_xlfn.XLOOKUP(AJ24,CrossRef!$A:$A,CrossRef!$K:$K,"Not Found"),"-") -> 0 | AM24: =IFERROR(_xlfn.XLOOKUP(AJ24,CrossRef!$A:$A,CrossRef!$L:$L,"Not Found"),"-") -> 20000H ENGINE CHANGE
A25: =D25&C25&B25 -> TW2394100000 | B25: =LEFT(N25,FIND(" ",N25)-1) -> 00 | C25: =LEFT(M25,4) -> 1000 | D25: =LEFT(L25,FIND(" ",L25)-1) -> TW2394 | E25: =MID(X25,2,3) -> 3PR | G25: WA - Macmahon | H25: 0 - (NONE) | I25: Macmahon-Telfer | J25: Macmahon-Telfer-Trucks | K25: 777D | L25: TW2394 - 3PR00889 | M25: 1000 - ENGINE | N25: 00 - (NONE) | O25: 20000 | P25: 7552.9142 | Q25: 48024 | R25: 0R3981 | S25: 000 CAT REMAN | T25: 0R3981 | U25: Unknown | W25: NH- Per CSM Forecast Feb26Per CSM Forecast Jan 26 - TRO;Per CSM Forecast Nov 25 - TRO; Per CSM Forecast Sep 25 - TRO;Per CSM Forecast July 25 - TRO; Per CSM Forecast May 25 - TRO; Per CSM Forecast April 25 - TRO; Per CSM Forecast Mar 25 - TROPer CSM Forecast Feb 25 - TROPer CSM Forecast Dec 24 - TRO; Per CSM Forecast Nov 24 - TroPer CSM July 2024 Forecast - TROPer CSM June 2024 Forecast - TRO; | X25: 03PR00889 | Y25: 301026.68 | Z25: 1000.00.RB.0 ENGINE | AA25: 49132.694 | AB25: MACMAHON CONTRACTORS PTY LTD | AC25: RB - Rebuild Workorder | AE25: 12447.086 | AF25: =_xlfn.XLOOKUP(A25,Macmahon!B:B,Macmahon!AE:AE,"",0) -> 45193 | AG25: =_xlfn.XLOOKUP(A25,Macmahon!B:B,Macmahon!AJ:AJ,"",0) -> 50755.405 | AH25: =_xlfn.XLOOKUP(A25,Macmahon!B:B,Macmahon!AK:AK,"",0) -> 0 | AI25: =IF(AG25=0,AH25,IF(AH25=0,AG25,MIN(AG25,AH25))) -> 50755.405 | AJ25: =E25&C25&B25 -> 3PR100000 | AK25: =IFERROR(_xlfn.XLOOKUP(AJ25,CrossRef!$A:$A,CrossRef!$J:$J,"Not Found"),"-") -> TKHL017-ENGI | AL25: =IFERROR(_xlfn.XLOOKUP(AJ25,CrossRef!$A:$A,CrossRef!$K:$K,"Not Found"),"-") -> 0 | AM25: =IFERROR(_xlfn.XLOOKUP(AJ25,CrossRef!$A:$A,CrossRef!$L:$L,"Not Found"),"-") -> 20000H ENGINE CHANGE
A26: =D26&C26&B26 -> TD6039100000 | B26: =LEFT(N26,FIND(" ",N26)-1) -> 00 | C26: =LEFT(M26,4) -> 1000 | D26: =LEFT(L26,FIND(" ",L26)-1) -> TD6039 | E26: =MID(X26,2,3) -> 6HK | G26: WA - Macmahon | H26: 0 - (NONE) | I26: Macmahon-Greenbushes | J26: Macmahon-Greenbushes-Trucks | K26: 785B | L26: TD6039 - 6HK00379 | M26: 1000 - ENGINE | N26: 00 - (NONE) | O26: 20000 | P26: 77822.696 | Q26: 46144 | R26: 0R3982 | S26: 000 CAT REMAN | T26: 0R3982 | U26: Unknown | W26: NH- Per CSM Forecast Feb26;Per CSM Forecast Jan 26 - TRO;Per CSM Forecast Nov 25 - TRO; Per CSM Forecast Sep 25 - TRO;Per CSM Forecast July 25 - TRO; | X26: 06HK00379 | Y26: 417452.69 | Z26: 1000.00.RB.0 ENGINE | AA26: 143220.9 | AB26: MACMAHON CONTRACTORS PTY LTD | AC26: RB - Rebuild Workorder | AE26: -57822.696 | AF26: =_xlfn.XLOOKUP(A26,Macmahon!B:B,Macmahon!AE:AE,"",0) -> 43745 | AG26: =_xlfn.XLOOKUP(A26,Macmahon!B:B,Macmahon!AJ:AJ,"",0) -> 46226.72 | AH26: =_xlfn.XLOOKUP(A26,Macmahon!B:B,Macmahon!AK:AK,"",0) -> 0 | AI26: =IF(AG26=0,AH26,IF(AH26=0,AG26,MIN(AG26,AH26))) -> 46226.72 | AJ26: =E26&C26&B26 -> 6HK100000 | AK26: =IFERROR(_xlfn.XLOOKUP(AJ26,CrossRef!$A:$A,CrossRef!$J:$J,"Not Found"),"-") -> TKHL004-ENGI | AL26: =IFERROR(_xlfn.XLOOKUP(AJ26,CrossRef!$A:$A,CrossRef!$K:$K,"Not Found"),"-") -> 0 | AM26: =IFERROR(_xlfn.XLOOKUP(AJ26,CrossRef!$A:$A,CrossRef!$L:$L,"Not Found"),"-") -> 20000H ENGINE CHANGE
A27: =D27&C27&B27 -> TD6311100000 | B27: =LEFT(N27,FIND(" ",N27)-1) -> 00 | C27: =LEFT(M27,4) -> 1000 | D27: =LEFT(L27,FIND(" ",L27)-1) -> TD6311 | E27: =MID(X27,2,3) -> SSP | G27: WA - Macmahon | H27: 0 - (NONE) | I27: Macmahon-Tropicana | J27: Macmahon-Tropicana-Trucks | K27: 793F | L27: TD6311 - SSP00865 | M27: 1000 - ENGINE | N27: 00 - (NONE) | O27: 26000 | P27: 3479.9399 | Q27: 47585 | R27: 5632134X | S27: CUSTOMER REBUILD | T27: 3659319X | U27: Unknown | W27: NH- Per CSM Forecast Feb26Per CSM Forecast Jan 26 - TRO;Per CSM Forecast Nov 25 - TRO; Per CSM Forecast Sep 25 - TRO;Per CSM Forecast July 25 - TRO; Per CSM Forecast May 25 - TRO; Per CSM Forecast April 25 - TRO; Per CSM Forecast Mar 25 - TROPer CSM Forecast Feb 25 - TROPer CSM Forecast Dec 24 - TRO; Per CSM Forecast Nov 24 - TroPer CSM June 2024 Forecast - TRO;Per CSM Forecast April 2024 TRO;Per CSM forcast data Mar 2024 - TRO;Oct 2023 Monthly Forecast - NIH; Aug 2023 Monthly Forecast Data - MSC Per Monthly Forecast Data July 2023 - MSC Per Monthly Forecast Data June 2023 - MSC Per Sales Status Update Returned Summary Report May 2023 - MSC Per Monthly Forecast Data May 2023 - MSC Per Monthly Forecast Data Feb23 - MSC | X27: 0SSP00865 | Y27: 641496.86 | Z27: 1000.00.RB.0 ENGINE | AA27: 89097.222 | AB27: MACMAHON CONTRACTORS PTY LTD | AC27: RB - Rebuild Workorder | AE27: 22520.06 | AF27: =_xlfn.XLOOKUP(A27,Macmahon!B:B,Macmahon!AE:AE,"",0) -> 45984 | AG27: =_xlfn.XLOOKUP(A27,Macmahon!B:B,Macmahon!AJ:AJ,"",0) -> 46755.659 | AH27: =_xlfn.XLOOKUP(A27,Macmahon!B:B,Macmahon!AK:AK,"",0) -> 46701 | AI27: =IF(AG27=0,AH27,IF(AH27=0,AG27,MIN(AG27,AH27))) -> 46701 | AJ27: =E27&C27&B27 -> SSP100000 | AK27: =IFERROR(_xlfn.XLOOKUP(AJ27,CrossRef!$A:$A,CrossRef!$J:$J,"Not Found"),"-") -> TKHL174-ENGI | AL27: =IFERROR(_xlfn.XLOOKUP(AJ27,CrossRef!$A:$A,CrossRef!$K:$K,"Not Found"),"-") -> 0 | AM27: =IFERROR(_xlfn.XLOOKUP(AJ27,CrossRef!$A:$A,CrossRef!$L:$L,"Not Found"),"-") -> 22000H ENGINE CHANGE
A28: =D28&C28&B28 -> TD6314100000 | B28: =LEFT(N28,FIND(" ",N28)-1) -> 00 | C28: =LEFT(M28,4) -> 1000 | D28: =LEFT(L28,FIND(" ",L28)-1) -> TD6314 | E28: =MID(X28,2,3) -> SSP | G28: WA - Macmahon | H28: 0 - (NONE) | I28: Macmahon-Tropicana | J28: Macmahon-Tropicana-Trucks | K28: 793F | L28: TD6314 - SSP00880 | M28: 1000 - ENGINE | N28: 00 - (NONE) | O28: 26000 | P28: 6517.2791 | Q28: 47290 | R28: 5632134X | S28: CUSTOMER REBUILD | T28: 3659319X | U28: Unknown | W28: NH- Per CSM Forecast Feb26Per CSM Forecast Jan 26 - TRO; | X28: 0SSP00880 | Y28: 641496.86 | Z28: 1000.00.RB.0 ENGINE | AA28: 86033.526 | AB28: MACMAHON CONTRACTORS PTY LTD | AC28: RB - Rebuild Workorder | AE28: 19482.721 | AF28: =_xlfn.XLOOKUP(A28,Macmahon!B:B,Macmahon!AE:AE,"",0) -> 45787 | AG28: =_xlfn.XLOOKUP(A28,Macmahon!B:B,Macmahon!AJ:AJ,"",0) -> 46648.623 | AH28: =_xlfn.XLOOKUP(A28,Macmahon!B:B,Macmahon!AK:AK,"",0) -> 46623 | AI28: =IF(AG28=0,AH28,IF(AH28=0,AG28,MIN(AG28,AH28))) -> 46623 | AJ28: =E28&C28&B28 -> SSP100000 | AK28: =IFERROR(_xlfn.XLOOKUP(AJ28,CrossRef!$A:$A,CrossRef!$J:$J,"Not Found"),"-") -> TKHL174-ENGI | AL28: =IFERROR(_xlfn.XLOOKUP(AJ28,CrossRef!$A:$A,CrossRef!$K:$K,"Not Found"),"-") -> 0 | AM28: =IFERROR(_xlfn.XLOOKUP(AJ28,CrossRef!$A:$A,CrossRef!$L:$L,"Not Found"),"-") -> 22000H ENGINE CHANGE
A29: =D29&C29&B29 -> TD6315100000 | B29: =LEFT(N29,FIND(" ",N29)-1) -> 00 | C29: =LEFT(M29,4) -> 1000 | D29: =LEFT(L29,FIND(" ",L29)-1) -> TD6315 | E29: =MID(X29,2,3) -> SND | G29: WA - Macmahon | H29: 0 - (NONE) | I29: Macmahon-Tropicana | J29: Macmahon-Tropicana-Trucks | K29: 793F XQ | L29: TD6315 - SND00128 | M29: 1000 - ENGINE | N29: 00 - (NONE) | O29: 22000 | P29: 18163.751 | Q29: 46699 | R29: 3659319X | S29: CUSTOMER REBUILD | T29: 3659319X | U29: Confident | W29: NH - CF May26-:NH- Per Customer Forecast March26;NH- Per CSM Forecast Feb26Per CSM Forecast Jan 26 - TRO;Per CSM Forecast Nov 25 - TRO; Per CSM Forecast Sep 25 - TRO;Per CSM Forecast August 25 - TRO;Per CSM Forecast July 25 - TRO; | X29: 0SND00128 | Y29: 641496.86 | Z29: 1000.00.RB.0 ENGINE | AA29: 68301.528 | AB29: MACMAHON CONTRACTORS PTY LTD | AC29: RB - Rebuild Workorder | AD29: J. Power | AE29: 3836.2495 | AF29: =_xlfn.XLOOKUP(A29,Macmahon!B:B,Macmahon!AE:AE,"",0) -> 44993 | AG29: =_xlfn.XLOOKUP(A29,Macmahon!B:B,Macmahon!AJ:AJ,"",0) -> 46511.41 | AH29: =_xlfn.XLOOKUP(A29,Macmahon!B:B,Macmahon!AK:AK,"",0) -> 46653 | AI29: =IF(AG29=0,AH29,IF(AH29=0,AG29,MIN(AG29,AH29))) -> 46511.41 | AJ29: =E29&C29&B29 -> SND100000 | AK29: =IFERROR(_xlfn.XLOOKUP(AJ29,CrossRef!$A:$A,CrossRef!$J:$J,"Not Found"),"-") -> TKHL158-ENGI | AL29: =IFERROR(_xlfn.XLOOKUP(AJ29,CrossRef!$A:$A,CrossRef!$K:$K,"Not Found"),"-") -> 0 | AM29: =IFERROR(_xlfn.XLOOKUP(AJ29,CrossRef!$A:$A,CrossRef!$L:$L,"Not Found"),"-") -> 22000H ENGINE CHANGE
A30: =D30&C30&B30 -> TD6348100000 | B30: =LEFT(N30,FIND(" ",N30)-1) -> 00 | C30: =LEFT(M30,4) -> 1000 | D30: =LEFT(L30,FIND(" ",L30)-1) -> TD6348 | E30: =MID(X30,2,3) -> SSP | G30: WA - Macmahon | H30: 0 - (NONE) | I30: Macmahon-Tropicana | J30: Macmahon-Tropicana-Trucks | K30: 793F | L30: TD6348 - SSP01073 | M30: 1000 - ENGINE | N30: 00 - (NONE) | O30: 26000 | P30: 24490.511 | Q30: 46085 | R30: 5632134X | S30: CUSTOMER REBUILD | T30: 3659319X | U30: Confident | W30: Per CSM Forecast Jan 26 - TRO;Per CSM Forecast Nov 25 - TRO; Per CSM Forecast Sep 25 - TRO;Per CSM Forecast July 25 - TRO; Per CSM Forecast May 25 - TRO; Per CSM Forecast April 25 - TRO; Per CSM Forecast Mar 25 - TROPer CSM Forecast Feb 25 - TROPer CSM Forecast Dec 24 - TRO; Per CSM Forecast Nov 24 - TroPer CSM August Forecast 2024 - TROPer CSM July 2024 Forecast - TROPer CSM June 2024 Forecast - TRO;Per CSM Forecast April 2024 TRO;Per CSM forcast data Mar 2024 - TRO;Oct 2023 Monthly Forecast - NIH; Aug 2023 Monthly Forecast Data - MSC Per Monthly Forecast Data July 2023 - MSC Per Sales Status Update Returned Summary Report May 2023 - MSC Per Monthly Forecast Data May 2023 - MSC Per Monthly Forecast Data Feb23 - MSC | X30: 0SSP01073 | Y30: 641496.86 | Z30: 1000.00.RB.0 ENGINE | AA30: 46589.742 | AB30: MACMAHON CONTRACTORS PTY LTD | AC30: RB - Rebuild Workorder | AD30: J. Power | AE30: 1509.4893 | AF30: =_xlfn.XLOOKUP(A30,Macmahon!B:B,Macmahon!AE:AE,"",0) -> 46213 | AG30: =_xlfn.XLOOKUP(A30,Macmahon!B:B,Macmahon!AJ:AJ,"",0) -> 47219.158 | AH30: =_xlfn.XLOOKUP(A30,Macmahon!B:B,Macmahon!AK:AK,"",0) -> 47123 | AI30: =IF(AG30=0,AH30,IF(AH30=0,AG30,MIN(AG30,AH30))) -> 47123 | AJ30: =E30&C30&B30 -> SSP100000 | AK30: =IFERROR(_xlfn.XLOOKUP(AJ30,CrossRef!$A:$A,CrossRef!$J:$J,"Not Found"),"-") -> TKHL174-ENGI | AL30: =IFERROR(_xlfn.XLOOKUP(AJ30,CrossRef!$A:$A,CrossRef!$K:$K,"Not Found"),"-") -> 0 | AM30: =IFERROR(_xlfn.XLOOKUP(AJ30,CrossRef!$A:$A,CrossRef!$L:$L,"Not Found"),"-") -> 22000H ENGINE CHANGE
